Workbook

Sheet Sheet1
A1: ໂລໂກ້ | G1: Logo Company
A2: ບໍລິສັດ………….. | G2: BCEL-KT Securities Co.,Ltd
A3: ເບີໂທ..……………. | G3: Tel: , Fax:
B4: ໃບລາຍງານກະແສເງິນສົດ | H4: Cash flow statment
B5: ປະຈຳປີ............... | H5: Yearly:...............
B6: ຫົວໜ່ວຍ: 1.000.000ກີບ | H6: Unit: 1.000.000 Lak
A7: ລຳດັບ | B7: ລາຍການ | C7: ເອກະສານຊ້ອນທ້າຍ | D7: ຈຳນວນເງິນ | G7: No | H7: Descriptions | I7: Note | J7: Amount
D8: ປີນີ້ | E8: ປີກ່ອນ | J8: This Year | K8: Last Year
A9: I | B9: ກະແສເງິນສົດຈາກກິດຈະກຳການດຳເນີນງານ | G9: I | H9: Cash flows from operating activities
B10: 1. ​ກໍາໄລ ຫຼື ຂາດທຶນສຸດທິກ່ອນອາກອນ | D10: 0 | E10: 0 | H10: 1. ​Net profit before tax for the period | J10: 0 | K10: 0
B11: 2. ລາຍການປັບປຸງຍອດກຳໄລ ຫຼື ຍອດຂາດທຶນເປັນເງິນສົດຮັບ-ຈ່າຍ | D11: =+D12+D13+D14+D15+D16+D17 -> 0 | E11: =+E12+E13+E14+E15+E16+E17 -> 0 | H11: 2. Adjustments to reconcile net profit to | J11: =+J12+J13+J14+J15+J16+J17 -> 0 | K11: =+K12+K13+K14+K15+K16+K17 -> 0
B12: 2.1. ຄ່າຫຼຸ້ຍຫ້ຽນ ແລະ ຄ່າເສື່ອມມູນຄ່າສຸດທິຂອງຊັບສົມບັດຄົງທີ່ມີຕົວຕົນ ແລະ ບໍ່ມີຕົວຕົນ | D12: 0 | E12: 0 | H12: 2.1. Depreciation | J12: 0 | K12: 0
B13: 2.2. ຄ່າເສື່ອມມູນຄ່າສຸດທິຂອງເງິນລົງທຶນໃນຫຼັກຊັບ ແລະ ລາຍການອື່ນໆ | D13: 0 | E13: 0 | H13: 2.2. Amortization | J13: 0 | K13: 0
B14: 2.3. ຂາດທຶນຈາກການຂາຍຊັບສົມບັດຄົງທີ່ | D14: 0 | E14: 0 | H14: 2.3. Loss on Disposal | J14: 0 | K14: 0
B15: 2.4. ກຳໄລຈາກການຂາຍຊັບສົມບັດຄົງທີ່ | D15: 0 | E15: 0 | H15: 2.4. Gain on Disposal | J15: 0 | K15: 0
B16: 2.5. ສ່ວນປ່ຽນແປງໃນລາຍການດອກເບ້ຍ ແລະ ລາຍຮັບອື່ນໆຄ້າງຮັບ | D16: 0 | E16: 0 | H16: 2.5. Unrealized (gain) loss on investment | J16: 0 | K16: 0
B17: 2.6. ສ່ວນປ່ຽນແປງໃນລາຍການດອກເບ້ຍ ແລະ ລາຍຈ່າຍອື່ນໆຄ້າງຈ່າຍ | D17: 0 | E17: 0 | H17: 2.6. Unrealized gain(loss) on exchange rate | J17: 0 | K17: 0
B18: ກ. ກະແສເງິນສົດສຸດທິຈາກກິດຈະກຳການດຳເນີນງານກ່ອນການປ່ຽນແປງໃນລາຍການຊັບສິນ ແລະ ໜີ້ສິນໝູນວຽນ | D18: =+D10+D11 -> 0 | E18: =+E10+E11 -> 0 | H18: A. Net loss from operating activities before changes in operating assets and liabilities | J18: =+J10+J11 -> 0 | K18: =+K10+K11 -> 0
B19: 3. ການປ່ຽນແປງ(ເພີ່ມຂຶ້ນ ຫຼື ຫຼຸດລົງ) ໃນລາຍການຊັບສິນໝູນວຽນ | D19: =+D20+D21+D22+D23+D24+D25+D26+D27 -> 0 | E19: =+E20+E21+E22+E23+E24+E25+E26+E27 -> 0 | H19: 3. Increase/Decrease in operating assets:- | J19: =+J20+J21+J22+J23+J24+J25+J26+J27 -> 0 | K19: =+K20+K21+K22+K23+K24+K25+K26+K27 -> 0
B20: 3.1. ເງິນຝາກທະນາຄານ ແລະ ສະຖາບັນການເງິນ | D20: 0 | E20: 0 | H20: 3.1. Deposit with banks and financial institutions | J20: 0 | K20: 0
B21: 3.2. ເງິນລົງທຶນໄລຍະສັ້ນ | D21: 0 | E21: 0 | H21: 3.2. Shorterm Investement "Investment in securities" | J21: 0 | K21: 0
B22: 3.3. ໜີ້ຕ້ອງຮັບທາງການຄ້າ | D22: 0 | E22: 0 | H22: 3.3. A/R on business | J22: 0 | K22: 0
B23: 3.4. ໜີ້ຕ້ອງຮັບທາງທຸລະກຳຫຼັກຊັບ | D23: 0 | E23: 0 | H23: 3.4. A/R Securities on Business | J23: 0 | K23: 0
B24: 3.5. ໜີ້ຕ້ອງຮັບລະຫວ່າງບໍລິສັດໃນກຸ່ມ | D24: 0 | E24: 0 | H24: 3.5. A/R clearing house | J24: 0 | K24: 0
B25: 3.6. ໜີ້ຕ້ອງຮັບອື່ນໆ | D25: 0 | E25: 0 | H25: 3.6. Other account receivable | J25: 0 | K25: 0
B26: 3.7. ເຄື່ອງໃນສາງ | D26: 0 | E26: 0 | H26: 3.7. Inventory | J26: 0 | K26: 0
B27: 3.8. ຊັບສິນໝູນວຽນອື່ນໆ | D27: 0 | E27: 0 | H27: 3.8. Other current assets | J27: 0 | K27: 0
B28: ຂ. ກະແສເງິນສົດສຸດທິຈາກການປ່ຽນແປງໃນຊັບສິນໝູນວຽນ | D28: =+D19 -> 0 | E28: =+E19 -> 0 | H28: B. Net Cash flow statement in operating assets | J28: =+J19 -> 0 | K28: =+K19 -> 0
B29: 4. ການປ່ຽນແປງ(ເພີ່ມຂຶ້ນ ຫຼື ຫຼຸດລົງ) ໃນລາຍການໜີ້ສິນໝູນວຽນ | D29: =+D30+D31+D32+D33+D34+D35 -> 0 | E29: =+E30+E31+E32+E33+E34+E35 -> 0 | H29: 4. Increase/Decrease in operating liabilities:- | J29: =+J30+J31+J32+J33+J34+J35 -> 0 | K29: =+K30+K31+K32+K33+K34+K35 -> 0
B30: 4.1. ໜີ້ຕ້ອງສົ່ງທາງການຄ້າ | D30: 0 | E30: 0 | H30: 4.1. A/P on business | J30: 0 | K30: 0
B31: 4.2. ໜີ້ຕ້ອງສົ່ງທາງທຸລະກຳຫຼັກຊັບ | D31: 0 | E31: 0 | H31: 4.2. A/P Securities on Business | J31: 0 | K31: 0
B32: 4.3. ໜີ້ຕ້ອງສົ່ງລະຫວ່າງບໍລິສັດໃນກຸ່ມ | D32: 0 | E32: 0 | H32: 4.3. A/R clearing house | J32: 0 | K32: 0
B33: 4.4. ອາກອນກຳໄລຄ້າງຈ່າຍ | D33: 0 | E33: 0 | H33: 4.4. Accrued corporate income tax | J33: 0 | K33: 0
B34: 4.5. ໜີ້ຕ້ອງສົ່ງອື່ນໆ | D34: 0 | E34: 0 | H34: 4.5. Other liabilities | J34: 0 | K34: 0
B35: 4.6. ໜີ້ສິນໝູນວຽນອື່ນໆ | D35: 0 | E35: 0 | H35: 4.6. Subscription payable | J35: 0 | K35: 0
B36: ຄ. ກະແສເງິນສົດສຸດທິຈາກການປ່ຽນແປງໃນໜີ້ສິນໝູນວຽນ | D36: =+D29 -> 0 | E36: =+E29 -> 0 | H36: C. Net Cash flow statement in operating Liabilities | J36: =+J29 -> 0 | K36: =+K29 -> 0
B37: ກະແສເງິນສົດສຸດທິຈາກກິດຈະກຳດຳເນີນງານ | D37: =+D18+D28+D36 -> 0 | E37: =+E18+E28+E36 -> 0 | H37: Net Cash flows from operating activities | J37: =+J18+J28+J36 -> 0 | K37: =+K18+K28+K36 -> 0
A38: II | B38: ​ກະແສເງິນສົດຈາກກິດຈະກໍາລົງທຶນ | G38: II | H38: Cash flows from investing activities
B39: 1. ສ່ວນເພີ່ມຫຼືຫຼຸດໃນລາຍການເງິນລົງທຶນໄລຍະຍາວ | D39: 0 | E39: 0 | H39: 1. Increase/Decrease on long term investment | J39: 0 | K39: 0
B40: 2. ສ່ວນເພີ່ມຫຼືຫຼຸດໃນລາຍໜີ້ຕ້ອງຮັບໄລຍະຍາວ ແລະ ຊັບສິນໄລຍະຍາວອື່ນໆ | D40: 0 | E40: 0 | H40: 2. Increase/Decrease A/R and other assets on long term investment | J40: 0 | K40: 0
B41: 3. ສ່ວນເພີ່ມຫຼືຫຼຸດໃນລາຍການຊັບສົມບັດຄົງທີ່ | D41: 0 | E41: 0 | H41: 3. Increase/Decrease of fix assets | J41: 0 | K41: 0
B42: ກະແສເງິນສົດສຸດທິຈາກກິດຈະກຳລົງທຶນ | D42: =+SUM(D39:D41) -> 0 | E42: =+SUM(E39:E41) -> 0 | H42: Net cash flows used in investing activities | J42: =+SUM(J39:J41) -> 0 | K42: =+SUM(K39:K41) -> 0
A43: III | B43: ກະແສເງິນສົດຈາກກິດຈະກຳຈັດຫາເງິນ | G43: III | H43: Cash flows from financing activities
B44: 1. ສ່ວນເພີ່ມຫຼືຫຼຸດໃນລາຍການເງິນກູ້ຢືມມາ ແລະ ໜີ້ຕ້ອງສົ່ງໄລຍະຍາວອື່ນໆ | D44: 0 | E44: 0 | H44: 1. Increase/Decrease on loan and other long term liabilities | J44: 0 | K44: 0
B45: 2. ສ່ວນເພີ່ມຫຼືຫຼຸດໃນການອອກຮຸ້ນ | D45: 0 | E45: 0 | H45: 2. Proceeds from issue of ordinary shares | J45: 0 | K45: 0
B46: 3. ທຶນປະກອບທີ່ໄດ້ຮັບໃນປີ | D46: 0 | E46: 0 | H46: 3. Proceeds from paid-up of ordinary shares | J46: 0 | K46: 0
B47: 4. ຈ່າຍເງິນປັນຜົນ | D47: 0 | E47: 0 | H47: 4. Paid dividend | J47: 0 | K47: 0
B48: ກະແສເງິນສົດສຸດທິຈາກກິດຈະກຳຈັດຫາເງິນ | D48: =+SUM(D44:D47) -> 0 | E48: =+SUM(E44:E47) -> 0 | H48: Net cash flow provided by financing activities | J48: =+SUM(J44:J47) -> 0 | K48: =+SUM(K44:K47) -> 0
A49: IV | B49: ເງິນສົດ ແລະ ທຽບເທົ່າເງິນສົດ | G49: IV | H49: Cash and cash equivalents
B50: ເງິນສົດ ແລະ ທຽບເທົ່າເງິນສົດເພີ່ມຂຶ້ນ ຫຼື ຫຼຸດລົງສຸດທິໃນປີ | D50: =+D37+D42+D48 -> 0 | E50: =+E37+E42+E48 -> 0 | H50: Net increase in cash and cash equivalents for the year | J50: =+J37+J42+J48 -> 0 | K50: =+K37+K42+K48 -> 0
B51: ເງິນສົດ ແລະ ທຽບເທົ່າເງິນສົດຍັງເຫຼືອທ້າຍປີກ່ອນ | D51: 0 | E51: 0 | H51: Cash and cash equivalents at beginning of the year | J51: 0 | K51: 0
B52: ເງິນສົດ ແລະ ທຽບເທົ່າເງິນສົດຍັງເຫຼືອທ້າຍປີນີ້ | D52: =+SUM(D50:D51) -> 0 | E52: =+SUM(E50:E51) -> 0 | H52: Cash and cash equivalents at end of the year | J52: =+SUM(J50:J51) -> 0 | K52: =+SUM(K50:K51) -> 0
D54: ວັນທີ .. ../… ./2013 | J54: Vientiane, Date: / /2013
A55: ຜູ້ອຳນວຍການ ທີ່ປຶກສາບັນຊີ ຫົວໜ້າພະແນກບັນຊີ ຜູ້ສັງລວມ | G55: General Manager Consultant Chief of account | J55: Accounting:
H72: 2.1. ຄ່າຫຼຸ້ຍຫ້ຽນ ແລະ ຄ່າເສື່ອມມູນຄ່າສຸດທິຂອງຊັບສົມບັດຄົງທີ່ມີຕົວຕົນ ແລະ ບໍ່ມີຕົວຕົນ
H73: 2.2. ຄ່າເສື່ອມມູນຄ່າສຸດທິຂອງເງິນລົງທຶນໃນຫຼັກຊັບ ແລະ ລາຍການອື່ນໆ
H74: 2.3. ຂາດທຶນຈາກການຂາຍຊັບສົມບັດຄົງທີ່
H75: 2.4. ກຳໄລຈາກການຂາຍຊັບສົມບັດຄົງທີ່

Sheet Sheet2
A1: ໂລໂກ້
A2: ບໍລິສັດ…………..
A3: ເບີໂທ..…………….
B4: ໃບລາຍງານກະແສເງິນສົດ
B5: ປະຈຳປີ...............
B6: ຫົວໜ່ວຍ: 1.000.000ກີບ
A7: ລຳດັບ | B7: ລາຍການ
B8: ລາຍການ | C8: ເຄື່ອງໝາຍ | D8: ເລກບັນຊີ
A9: I | B9: ກະແສເງິນສົດຈາກກິດຈະກຳການດຳເນີນງານ
B10: 1. ​ກໍາໄລ ຫຼື ຂາດທຶນສຸດທິກ່ອນອາກອນ | D10: ຍອດເຫຼືອບັນຊີ 3901
B11: 2. ລາຍການປັບປຸງຍອດກຳໄລ ຫຼື ຍອດຂາດທຶນເປັນເງິນສົດຮັບ-ຈ່າຍ
B12: 2.1. ຄ່າຫຼຸ້ຍຫ້ຽນ ແລະ ຄ່າເສື່ອມມູນຄ່າສຸດທິຂອງຊັບສົມບັດຄົງທີ່ມີຕົວຕົນ ແລະ ບໍ່ມີຕົວຕົນ | C12: +/- | D12: ບ/ຊ 148
B13: 2.2. ຄ່າເສື່ອມມູນຄ່າສຸດທິຂອງເງິນລົງທຶນໃນຫຼັກຊັບ ແລະ ລາຍການອື່ນໆ | C13: +/- | D13: ບ/ຊ 1319+1419+1199111+1199121+1199131+1199141+1199211+1199231+1199241+
D14: 1299111+1299121+1299131+1299141+1299211+1299221+1299231+1199241+1199112+
D15: 1199113+1199122+1199123+1199132+1199133+1199142+1199143+1199212+1199213+
D16: 1199222+1199223+1199232+1199233+1199242+1199243+1299112+1299113+1299122+
D17: 1299123+1299132+1299133+1299142+1299143+1299212+1299222+1299232+1299142
B18: 2.3. ຂາດທຶນຈາກການຂາຍຊັບສົມບັດຄົງທີ່ | C18: + | D18: ບ/ຊ 4506+410416
B19: 2.4. ກຳໄລຈາກການຂາຍຊັບສົມບັດຄົງທີ່ | C19: - | D19: ບ/ຊ 5506+510416+510426
B20: 2.5. ສ່ວນປ່ຽນແປງໃນລາຍການດອກເບ້ຍ ແລະ ລາຍຮັບອື່ນໆຄ້າງຮັບ | D20: What account No ??????? | E20: None
B21: 2.6. ສ່ວນປ່ຽນແປງໃນລາຍການດອກເບ້ຍ ແລະ ລາຍຈ່າຍອື່ນໆຄ້າງຈ່າຍ | D21: What account No ??????? | E21: None
B22: ກ. ກະແສເງິນສົດສຸດທິຈາກກິດຈະກຳການດຳເນີນງານກ່ອນການປ່ຽນແປງໃນລາຍການຊັບສິນ ແລະ ໜີ້ສິນໝູນວຽນ | D22: ກ=3(Item 3.1 to Item 3.8)
B24: 3. ການປ່ຽນແປງ(ເພີ່ມຂຶ້ນ ຫຼື ຫຼຸດລົງ) ໃນລາຍການຊັບສິນໝູນວຽນ
B25: 3.1. ເງິນຝາກທະນາຄານ ແລະ ສະຖາບັນການເງິນ | C25: -/+ | D25: ບ/ຊ 1121+1131+1122
B26: 3.2. ເງິນລົງທຶນໄລຍະສັ້ນ | C26: -/+ | D26: ບ/ຊ 13011+13021+13025+13026+(130311-130391)+(130312-130392)+130351+130352+1311
B27: 3.3. ໜີ້ຕ້ອງຮັບທາງການຄ້າ | C27: -/+ | D27: ບ/ຊ 12011
B28: 3.4. ໜີ້ຕ້ອງຮັບທາງທຸລະກຳຫຼັກຊັບ | C28: -/+ | D28: ບ/ຊ 120611+12311+123151+1241+1261
B29: 3.5. ໜີ້ຕ້ອງຮັບລະຫວ່າງບໍລິສັດໃນກຸ່ມ | C29: -/+ | D29: ບ/ຊ 12111+121121
B30: 3.6. ໜີ້ຕ້ອງຮັບອື່ນໆ | C30: -/+ | D30: ບ/ຊ 113211+1132121+113221+1132221+119111+119121+119131+119141+119211+
D31: 119221+119231+119241+1207+129111+12921+129131+129141+129211+129221+129231+
D32: 129241
B33: 3.7. ເຄື່ອງໃນສາງ | C33: -/+ | D33: ບ/ຊ 1371+1373+1376+1378-1379
B34: 3.8. ຊັບສິນໝູນວຽນອື່ນໆ | C34: -/+ | D34: ບ/ຊ 1361+1362+138+1138
B35: ຂ. ກະແສເງິນສົດສຸດທິຈາກການປ່ຽນແປງໃນຊັບສິນໝູນວຽນ
B36: 4. ການປ່ຽນແປງ(ເພີ່ມຂຶ້ນ ຫຼື ຫຼຸດລົງ) ໃນລາຍການໜີ້ສິນໝູນວຽນ
B37: 4.1. ໜີ້ຕ້ອງສົ່ງທາງການຄ້າ | C37: +/- | D37: ບ/ຊ 2127+2137+21472167+2237+2247+2267+23017+23027+23317+23327+23357+23367+
D38: 2347+2367
B39: 4.2. ໜີ້ຕ້ອງສົ່ງທາງທຸລະກຳຫຼັກຊັບ | C39: +/- | D39: ບ/ຊ 23011+23021+23022+231+23311+23321+23351+2341+2342+2343+2344+2346
B40: 4.3. ໜີ້ຕ້ອງສົ່ງລະຫວ່າງບໍລິສັດໃນກຸ່ມ | C40: + | D40: ບ/ຊ 22111+22121
B41: 4.4. ອາກອນກຳໄລຄ້າງຈ່າຍ | C41: +/- | D41: ບ/ຊ 236111
B42: 4.5. ໜີ້ຕ້ອງສົ່ງອື່ນໆ | C42: +/- | D42: ບ/ຊ 2161+2261+23361+236112+236113+236114+236118+2362
B43: 4.6. ໜີ້ສິນໝູນວຽນອື່ນໆ | C43: +/- | D43: ບ/ຊ 23612+23613+23614+23618+238+2238
B44: ຄ. ກະແສເງິນສົດສຸດທິຈາກການປ່ຽນແປງໃນໜີ້ສິນໝູນວຽນ
B45: ກະແສເງິນສົດສຸດທິຈາກກິດຈະກຳດຳເນີນງານ
A46: II | B46: ​ກະແສເງິນສົດຈາກກິດຈະກໍາລົງທຶນ
B47: 1. ສ່ວນເພີ່ມຫຼືຫຼຸດໃນລາຍການເງິນລົງທຶນໄລຍະຍາວ | C47: -/+ | D47: ບ/ຊ 1411+(130411-130491)+(130412-130492)+130451+130452+13046+1412+1413+1414+
D48: 1415
B49: 2. ສ່ວນເພີ່ມຫຼືຫຼຸດໃນລາຍໜີ້ຕ້ອງຮັບໄລຍະຍາວ ແລະ ຊັບສິນໄລຍະຍາວອື່ນໆ | C49: -/+ | D49: ບ/ຊ 121122+121123+1132122+1132123+1132222+1132223+119112+119113+119122+
D50: 119123+119132+119133+119142+119143+119212+119213+119222+119223+119232+
D51: 119233+119242+119243+120612+120613+123152+129112+129113+129122+129123+
D52: 129132+129133+129142+129143+129212+129222+129232+129242
B53: 3. ສ່ວນເພີ່ມຫຼືຫຼຸດໃນລາຍການຊັບສົມບັດຄົງທີ່ | C53: -/+ | D53: ບ/ຊ 1431+1432-1439+1441-14491+1451-14951+1442-14492+1452-144952
B54: ກະແສເງິນສົດສຸດທິຈາກກິດຈະກຳລົງທຶນ
A55: III | B55: ກະແສເງິນສົດຈາກກິດຈະກຳຈັດຫາເງິນ
B56: 1. ສ່ວນເພີ່ມຫຼືຫຼຸດໃນລາຍການເງິນກູ້ຢືມມາ ແລະ ໜີ້ຕ້ອງສົ່ງໄລຍະຍາວອື່ນໆ | C56: +/- | D56: ບ/ຊ 212211+212212+2122151+212221+212222+2122251+213211+213212+2132151+
D57: 213221+213222+2132251+2141+2142+2231+22351+2241+2122152+2122153+2122252+
D58: 2122253+2132152+2132153+2132252+2132253+221122+221123
B59: 2. ສ່ວນເພີ່ມຫຼືຫຼຸດໃນການອອກຮຸ້ນ
B60: 3. ທຶນປະກອບທີ່ໄດ້ຮັບໃນປີ | C60: +/- | D60: ບ/ຊ 3101+3103+3104+3102+3108+3201
B61: 4. ຈ່າຍເງິນປັນຜົນ
B62: ກະແສເງິນສົດສຸດທິຈາກກິດຈະກຳຈັດຫາເງິນ
A63: IV | B63: ເງິນສົດ ແລະ ທຽບເທົ່າເງິນສົດ
B64: ເງິນສົດ ແລະ ທຽບເທົ່າເງິນສົດເພີ່ມຂຶ້ນ ຫຼື ຫຼຸດລົງສຸດທິໃນປີ
B65: ເງິນສົດ ແລະ ທຽບເທົ່າເງິນສົດຍັງເຫຼືອທ້າຍປີກ່ອນ | D65: ບ/ຊ 1101+1108
B66: ເງິນສົດ ແລະ ທຽບເທົ່າເງິນສົດຍັງເຫຼືອທ້າຍປີນີ້ | D66: ບ/ຊ 1101+1108
A70: ຜູ້ອຳນວຍການ ຫົວໜ້າພະແນກກວດກາ ຫົວໜ້າພະແນກບັນຊີ ຜູ້ສັງລວມ

Sheet FinalFormwFx2
A1: ໂລໂກ້
A2: ບໍລິສັດ…………..
A3: ເບີໂທ..…………….
B4: ໃບລາຍງານກະແສເງິນສົດ
B5: ປະຈຳປີ...............
B6: ຫົວໜ່ວຍ: 1.000.000ກີບ
A7: ລຳດັບ | B7: ລາຍການ
B8: ລາຍການ | C8: ເຄື່ອງໝາຍ | D8: ເລກບັນຊີ
A9: I | B9: ກະແສເງິນສົດຈາກກິດຈະກຳການດຳເນີນງານ
B10: 1. ​ກໍາໄລ ຫຼື ຂາດທຶນສຸດທິກ່ອນອາກອນ | D10: ຍອດເຫຼືອບັນຊີ 3901
B11: 2. ລາຍການປັບປຸງຍອດກຳໄລ ຫຼື ຍອດຂາດທຶນເປັນເງິນສົດຮັບ-ຈ່າຍ
B12: 2.1. ຄ່າຫຼຸ້ຍຫ້ຽນ ແລະ ຄ່າເສື່ອມມູນຄ່າສຸດທິຂອງຊັບສົມບັດຄົງທີ່ມີຕົວຕົນ ແລະ ບໍ່ມີຕົວຕົນ | C12: +/- | D12: ບ/ຊ 148
B13: 2.2. ຄ່າເສື່ອມມູນຄ່າສຸດທິຂອງເງິນລົງທຶນໃນຫຼັກຊັບ ແລະ ລາຍການອື່ນໆ | C13: +/- | D13: ບ/ຊ 1319+1419+1199111+1199121+1199131+1199141+1199211+1199231+1199241+
D14: 1299111+1299121+1299131+1299141+1299211+1299221+1299231+1199241+1199112+
D15: 1199113+1199122+1199123+1199132+1199133+1199142+1199143+1199212+1199213+
D16: 1199222+1199223+1199232+1199233+1199242+1199243+1299112+1299113+1299122+
D17: 1299123+1299132+1299133+1299142+1299143+1299212+1299222+1299232+1299142
B18: 2.3. ຂາດທຶນຈາກການຂາຍຊັບສົມບັດຄົງທີ່ | C18: + | D18: ບ/ຊ 4506+410416
B19: 2.4. ກຳໄລຈາກການຂາຍຊັບສົມບັດຄົງທີ່ | C19: - | D19: ບ/ຊ 5506+510416+510426
B20: 2.5. ສ່ວນປ່ຽນແປງໃນລາຍການດອກເບ້ຍ ແລະ ລາຍຮັບອື່ນໆຄ້າງຮັບ
B21: 2.6. ສ່ວນປ່ຽນແປງໃນລາຍການດອກເບ້ຍ ແລະ ລາຍຈ່າຍອື່ນໆຄ້າງຈ່າຍ
B22: ກ. ກະແສເງິນສົດສຸດທິຈາກກິດຈະກຳການດຳເນີນງານກ່ອນການປ່ຽນແປງໃນລາຍການຊັບສິນ ແລະ ໜີ້ສິນໝູນວຽນ
B24: 3. ການປ່ຽນແປງ(ເພີ່ມຂຶ້ນ ຫຼື ຫຼຸດລົງ) ໃນລາຍການຊັບສິນໝູນວຽນ
B25: 3.1. ເງິນຝາກທະນາຄານ ແລະ ສະຖາບັນການເງິນ | C25: -/+ | D25: ບ/ຊ 1121+1131+1122
B26: 3.2. ເງິນລົງທຶນໄລຍະສັ້ນ | C26: -/+ | D26: ບ/ຊ 13011+13021+13025+13026+(130311-130391)+(130312-130392)+130351+130352+1311
B27: 3.3. ໜີ້ຕ້ອງຮັບທາງການຄ້າ | C27: -/+ | D27: ບ/ຊ 12011
B28: 3.4. ໜີ້ຕ້ອງຮັບທາງທຸລະກຳຫຼັກຊັບ | C28: -/+ | D28: ບ/ຊ 120611+12311+123151+1241+1261
B29: 3.5. ໜີ້ຕ້ອງຮັບລະຫວ່າງບໍລິສັດໃນກຸ່ມ | C29: -/+ | D29: ບ/ຊ 12111+121121
B30: 3.6. ໜີ້ຕ້ອງຮັບອື່ນໆ | C30: -/+ | D30: ບ/ຊ 113211+1132121+113221+1132221+119111+119121+119131+119141+119211+
D31: 119221+119231+119241+1207+129111+12921+129131+129141+129211+129221+129231+
D32: 129241
B33: 3.7. ເຄື່ອງໃນສາງ | C33: -/+ | D33: ບ/ຊ 1371+1373+1376+1378-1379
B34: 3.8. ຊັບສິນໝູນວຽນອື່ນໆ | C34: -/+ | D34: ບ/ຊ 1361+1362+138+1138+1360000 | E34: ????????????
B35: ຂ. ກະແສເງິນສົດສຸດທິຈາກການປ່ຽນແປງໃນຊັບສິນໝູນວຽນ
B36: 4. ການປ່ຽນແປງ(ເພີ່ມຂຶ້ນ ຫຼື ຫຼຸດລົງ) ໃນລາຍການໜີ້ສິນໝູນວຽນ
B37: 4.1. ໜີ້ຕ້ອງສົ່ງທາງການຄ້າ | C37: +/- | D37: ບ/ຊ 2127+2137+21472167+2237+2247+2267+23017+23027+23317+23327+23357+23367+
D38: 2347+2367
B39: 4.2. ໜີ້ຕ້ອງສົ່ງທາງທຸລະກຳຫຼັກຊັບ | C39: +/- | D39: ບ/ຊ 23011+23021+23022+231+23311+23321+23351+2341+2342+2343+2344+2346
B40: 4.3. ໜີ້ຕ້ອງສົ່ງລະຫວ່າງບໍລິສັດໃນກຸ່ມ | C40: + | D40: ບ/ຊ 22111+22121
B41: 4.4. ອາກອນກຳໄລຄ້າງຈ່າຍ | C41: +/- | D41: ບ/ຊ 236111
B42: 4.5. ໜີ້ຕ້ອງສົ່ງອື່ນໆ | C42: +/- | D42: ບ/ຊ 2161+2261+23361+236112+236113+236114+236118+2362
B43: 4.6. ໜີ້ສິນໝູນວຽນອື່ນໆ | C43: +/- | D43: ບ/ຊ 23612+23613+23614+23618+238+2238
B44: ຄ. ກະແສເງິນສົດສຸດທິຈາກການປ່ຽນແປງໃນໜີ້ສິນໝູນວຽນ
B45: ກະແສເງິນສົດສຸດທິຈາກກິດຈະກຳດຳເນີນງານ
A46: II | B46: ​ກະແສເງິນສົດຈາກກິດຈະກໍາລົງທຶນ
B47: 1. ສ່ວນເພີ່ມຫຼືຫຼຸດໃນລາຍການເງິນລົງທຶນໄລຍະຍາວ | C47: -/+ | D47: ບ/ຊ 1411+(130411-130491)+(130412-130492)+130451+130452+13046+1412+1413+1414+
D48: 1415
B49: 2. ສ່ວນເພີ່ມຫຼືຫຼຸດໃນລາຍໜີ້ຕ້ອງຮັບໄລຍະຍາວ ແລະ ຊັບສິນໄລຍະຍາວອື່ນໆ | C49: -/+ | D49: ບ/ຊ 121122+121123+1132122+1132123+1132222+1132223+119112+119113+119122+
D50: 119123+119132+119133+119142+119143+119212+119213+119222+119223+119232+
D51: 119233+119242+119243+120612+120613+123152+129112+129113+129122+129123+
D52: 129132+129133+129142+129143+129212+129222+129232+129242
B53: 3. ສ່ວນເພີ່ມຫຼືຫຼຸດໃນລາຍການຊັບສົມບັດຄົງທີ່ | C53: -/+ | D53: ບ/ຊ 1431+1432-1439+1441-14491+1451-14951+1442-14492+1452-144952
B54: ກະແສເງິນສົດສຸດທິຈາກກິດຈະກຳລົງທຶນ
A55: III | B55: ກະແສເງິນສົດຈາກກິດຈະກຳຈັດຫາເງິນ
B56: 1. ສ່ວນເພີ່ມຫຼືຫຼຸດໃນລາຍການເງິນກູ້ຢືມມາ ແລະ ໜີ້ຕ້ອງສົ່ງໄລຍະຍາວອື່ນໆ | C56: +/- | D56: ບ/ຊ 212211+212212+2122151+212221+212222+2122251+213211+213212+2132151+
D57: 213221+213222+2132251+2141+2142+2231+22351+2241+2122152+2122153+2122252+
D58: 2122253+2132152+2132153+2132252+2132253+221122+221123
B59: 2. ສ່ວນເພີ່ມຫຼືຫຼຸດໃນການອອກຮຸ້ນ
B60: 3. ທຶນປະກອບທີ່ໄດ້ຮັບໃນປີ | C60: +/- | D60: ບ/ຊ 3101+3103+3104+3102+3108+3201
B61: 4. ຈ່າຍເງິນປັນຜົນ
B62: ກະແສເງິນສົດສຸດທິຈາກກິດຈະກຳຈັດຫາເງິນ
A63: IV | B63: ເງິນສົດ ແລະ ທຽບເທົ່າເງິນສົດ
B64: ເງິນສົດ ແລະ ທຽບເທົ່າເງິນສົດເພີ່ມຂຶ້ນ ຫຼື ຫຼຸດລົງສຸດທິໃນປີ
B65: ເງິນສົດ ແລະ ທຽບເທົ່າເງິນສົດຍັງເຫຼືອທ້າຍປີກ່ອນ | D65: ບ/ຊ 1101+1108
B66: ເງິນສົດ ແລະ ທຽບເທົ່າເງິນສົດຍັງເຫຼືອທ້າຍປີນີ້ | D66: ບ/ຊ 1101+1108
A70: ຜູ້ອຳນວຍການ ຫົວໜ້າພະແນກກວດກາ ຫົວໜ້າພະແນກບັນຊີ ຜູ້ສັງລວມ

Sheet Cash flow statement 
A1: ໂລໂກ້
A2: ບໍລິສັດ…………..
A3: ເບີໂທ..…………….
B4: ໃບລາຍງານກະແສເງິນສົດ
B5: ປະຈຳປີ: 2012 | K5: Note for A/C
B6: ຫົວໜ່ວຍ: 1.000.000ກີບ
A7: ລຳດັບ | B7: ລາຍການ | C7: ເອກະສານຊ້ອນທ້າຍ | D7: ຈຳນວນເງິນ
D8: ປີນີ້ | E8: Jan'13 | F8: Feb'13 | G8: Mar'13 | H8: June'13 | I8: Dec'13
A9: I | B9: ກະແສເງິນສົດຈາກກິດຈະກຳການດຳເນີນງານ
B10: 1. ​ກໍາໄລ ຫຼື ຂາດທຶນສຸດທິກ່ອນອາກອນ | D10: =SUM('TB 2012'!J86:J172)/1000 -> 3764215.6 | E10: =+SUM('TB JAn''13'!I80:I136) -> 2.4392347e+08 | F10: =+SUM('TB Feb''13'!I80:I139) -> 3.8434523e+08 | G10: =+SUM('TB March''13'!I81:I149) -> 869899.41 | H10: =+SUM('TB June''13'!I83:I159) -> 1.611895e+08 | I10: =+SUM('TB for 2013'!F89) -> 3.2704856e+09 | K10: Cr-Dr " Movement of 4-5 "+ A/C: 39
B11: 2. ລາຍການປັບປຸງຍອດກຳໄລ ຫຼື ຍອດຂາດທຶນເປັນເງິນສົດຮັບ-ຈ່າຍ | D11: =+D12+D13+D14+D15+D16+D17 -> 418699.01 | E11: =+E12+E13+E14+E15+E16+E17 -> 39596229 | F11: =+F12+F13+F14+F15+F16+F17 -> 28187123 | G11: =+G12+G13+G14+G15+G16+G17 -> 37983112 | H11: =+H12+H13+H14+H15+H16+H17 -> 37654393 | I11: =+I12+I13+I14+I15+I16+I17 -> 4.5097972e+08
B12: 2.1. ຄ່າຫຼຸ້ຍຫ້ຽນ ແລະ ຄ່າເສື່ອມມູນຄ່າສຸດທິຂອງຊັບສົມບັດຄົງທີ່ມີຕົວຕົນ ແລະ ບໍ່ມີຕົວຕົນ | D12: =SUM('TB 2012'!J50:J56)/1000 -> 418699.01 | E12: =+SUM('TB JAn''13'!J47:J52) -> 39596229 | F12: =+SUM('TB Feb''13'!J47:J52) -> 28187123 | G12: =+SUM('TB March''13'!J48:J53) -> 37983112 | H12: =+SUM('TB June''13'!J49:J54) -> 37654393 | I12: =+SUM('TB for 2013'!J57:J62) -> 4.5097972e+08 | K12: 1481
B13: 2.2. ຄ່າເສື່ອມມູນຄ່າສຸດທິຂອງເງິນລົງທຶນໃນຫຼັກຊັບ ແລະ ລາຍການອື່ນໆ | D13: 0 | E13: 0 | F13: 0 | G13: 0 | H13: 0 | I13: 0
B14: 2.3. ຂາດທຶນຈາກການຂາຍຊັບສົມບັດຄົງທີ່ | D14: 0 | E14: 0 | F14: 0 | G14: 0 | H14: 0 | I14: 0 | K14: 4506…
B15: 2.4. ກຳໄລຈາກການຂາຍຊັບສົມບັດຄົງທີ່ | D15: 0 | E15: 0 | F15: 0 | G15: 0 | H15: 0 | I15: 0
B16: 2.5. ສ່ວນປ່ຽນແປງໃນລາຍການດອກເບ້ຍ ແລະ ລາຍຮັບອື່ນໆຄ້າງຮັບ | D16: 0 | E16: 0 | F16: 0 | G16: 0 | H16: 0 | I16: 0
B17: 2.6. ສ່ວນປ່ຽນແປງໃນລາຍການດອກເບ້ຍ ແລະ ລາຍຈ່າຍອື່ນໆຄ້າງຈ່າຍ | D17: 0 | E17: 0 | F17: 0 | G17: 0 | H17: 0 | I17: 0
B18: ກ. ກະແສເງິນສົດສຸດທິຈາກກິດຈະກຳການດຳເນີນງານກ່ອນການປ່ຽນແປງໃນລາຍການຊັບສິນ ແລະ ໜີ້ສິນໝູນວຽນ | D18: =+D10+D11 -> 4182914.6 | E18: =+E10+E11 -> 2.8351969e+08 | F18: =+F10+F11 -> 4.1253235e+08 | G18: =+G10+G11 -> 38853011 | H18: =+H10+H11 -> 1.9884389e+08 | I18: =+I10+I11 -> 3.7214653e+09 | K18: 1+2
B19: 3. ການປ່ຽນແປງ (ເພີ່ມຂຶ້ນ) ຫຼື ຫຼຸດລົງ ໃນລາຍການຊັບສິນໝູນວຽນ | D19: =+D20+D21+D22+D23+D24+D25+D26+D27 -> -21876577 | E19: =+E20+E21+E22+E23+E24+E25+E26+E27 -> 1.1847e+10 | F19: =+F20+F21+F22+F23+F24+F25+F26+F27 -> 8.7998332e+09 | G19: =+G20+G21+G22+G23+G24+G25+G26+G27 -> 3.575521e+09 | H19: =+H20+H21+H22+H23+H24+H25+H26+H27 -> 2.8487901e+09 | I19: =+I20+I21+I22+I23+I24+I25+I26+I27 -> -2.0980819e+10 | N19: 9
B20: 3.1. ເງິນຝາກທະນາຄານ ແລະ ສະຖາບັນການເງິນ | D20: =-SUM('TB 2012'!I6:I25)/1000 -> -20185460 | E20: =-SUM('TB JAn''13'!I6:I24) -> 1.172383e+10 | F20: =-SUM('TB Feb''13'!I6:I24) -> 9.1610587e+09 | G20: =-SUM('TB March''13'!I6:I24) -> 4.4869567e+09 | H20: =-SUM('TB June''13'!I6:I25) -> 3.2601373e+09 | I20: =-SUM('TB for 2013'!I6:I25) -> -2.0271093e+10 | K20: 1121+1131
B21: 3.2. ເງິນລົງທຶນໄລຍະສັ້ນ | D21: =-('TB 2012'!I33+'TB 2012'!I34)/1000 -> -434990.2 | E21: =-SUM('TB JAn''13'!I31:I32) -> -1.550254e+08 | F21: =-SUM('TB Feb''13'!I31:I32) -> -4.332526e+08 | G21: =-SUM('TB March''13'!I32:I33) -> -261499400 | H21: =-SUM('TB June''13'!I33:I34) -> -1.976227e+08 | I21: =-SUM('TB for 2013'!I39:I40) -> -1.0555983e+09 | K21: 1302216+1302218
B22: 3.3. ໜີ້ຕ້ອງຮັບທາງການຄ້າ | D22: =-'TB 2012'!I30/1000 -> -54536.206 | E22: =-SUM('TB JAn''13'!I28) -> 56396718 | F22: =-SUM('TB Feb''13'!I28) -> -87819167 | G22: =-SUM('TB March''13'!I29) -> 90243338 | H22: =-'TB June''13'!I30 -> -9765615 | I22: =-SUM('TB for 2013'!I36) -> -368515318 | K22: 1201181
B23: 3.4. ໜີ້ຕ້ອງຮັບທາງທຸລະກຳຫຼັກຊັບ | D23: 0 | E23: 0 | F23: 0 | G23: 0 | H23: 0 | I23: 0 | K23: ບ/ຊ 120611+12311+123151+1241+1261
B24: 3.5. ໜີ້ຕ້ອງຮັບລະຫວ່າງບໍລິສັດໃນກຸ່ມ | D24: =-'TB 2012'!I31/1000 -> 23823.233 | E24: =-SUM('TB JAn''13'!I29) -> -139167192 | F24: =-SUM('TB Feb''13'!I29) -> 139167192 | G24: =-SUM('TB March''13'!I30) -> -759514740 | H24: =-SUM('TB June''13'!I31) -> 10467164 | I24: =-SUM('TB for 2013'!I37) -> -10142696 | K24: 1211110
B25: 3.6. ໜີ້ຕ້ອງຮັບອື່ນໆ | D25: =-('TB 2012'!I26+'TB 2012'!I32)/1000 -> -1027703.1 | E25: =-SUM('TB JAn''13'!I25+'TB JAn''13'!I30) -> 3.3382056e+08 | F25: =-SUM('TB Feb''13'!I25+'TB Feb''13'!I30) -> -32451481 | G25: =-SUM('TB March''13'!I25+'TB March''13'!I31) -> 7298891.9 | H25: =-SUM('TB June''13'!I26+'TB June''13'!I32) -> 38698630 | I25: =-('TB for 2013'!I32+'TB for 2013'!I38) -> 5.466529e+08 | K25: 1137111+1301720
B26: 3.7. ເຄື່ອງໃນສາງ | D26: 0 | E26: 0 | F26: 0 | G26: 0 | H26: 0 | I26: 0 | K26: ບ/ຊ 1371+1373+1376+1378-1379
B27: 3.8. ຊັບສິນໝູນວຽນອື່ນໆ | D27: =-SUM('TB 2012'!I35:I43)/1000-SUM('TB 2012'!I27:I29)/1000 -> -197710.1 | E27: =-SUM('TB JAn''13'!I26:I27)-SUM('TB JAn''13'!I33:I40) -> 27145528 | F27: =-SUM('TB Feb''13'!I26:I27)-SUM('TB Feb''13'!I33:I40) -> 53130620 | G27: =-SUM('TB March''13'!I26:I28)-SUM('TB March''13'!I34:I41) -> 12036143 | H27: =-SUM('TB June''13'!I27:I29)-SUM('TB June''13'!I35:I42) -> -2.5312468e+08 | I27: =-SUM('TB for 2013'!I33:I35)-SUM('TB for 2013'!I41:I50) -> 1.7787792e+08 | K27: 1138100+1138810+1138830+1360000+1361100+1361300+1361500+1362100+1388110+1388120+1388170+1388180
B28: ຂ. ກະແສເງິນສົດສຸດທິຈາກການປ່ຽນແປງໃນຊັບສິນໝູນວຽນ | D28: =+D19 -> -21876577 | E28: =+E19 -> 1.1847e+10 | F28: =+F19 -> 8.7998332e+09 | G28: =+G19 -> 3.575521e+09 | H28: =+H19 -> 2.8487901e+09 | I28: =+I19 -> -2.0980819e+10 | L28: =+G28+'TB March''13'!L41 -> 0 | M28: ok | N28: =+G28+G36 -> -74581361
B29: 4. ການປ່ຽນແປງ ເພີ່ມຂຶ້ນ ຫຼື (ຫຼຸດລົງ) ໃນລາຍການໜີ້ສິນໝູນວຽນ | D29: =+D30+D31+D32+D33+D34+D35 -> 17872192 | E29: =+E30+E31+E32+E33+E34+E35 -> -1.2124988e+10 | F29: =+F30+F31+F32+F33+F34+F35 -> -9.2144256e+09 | G29: =+G30+G31+G32+G33+G34+G35 -> -3.6501023e+09 | H29: =+H30+H31+H32+H33+H34+H35 -> -3.4617652e+09 | I29: =+I30+I31+I32+I33+I34+I35 -> 1.6818077e+10 | L29: =+'TB March''13'!L71-'Cash flow statement '!G36 -> 0 | N29: =+N28+G18 -> -35728350
B30: 4.1. ໜີ້ຕ້ອງສົ່ງທາງການຄ້າ | D30: 0 | E30: 0 | F30: 0 | G30: 0 | H30: 0 | I30: 0 | N30: =+N29+G42 -> -35663705
B31: 4.2. ໜີ້ຕ້ອງສົ່ງທາງທຸລະກຳຫຼັກຊັບ | D31: =SUM('TB 2012'!J59:J62)/1000 -> 15911349 | E31: =+SUM('TB JAn''13'!J54:J57) -> -1.1983988e+10 | F31: =+SUM('TB Feb''13'!J54:J57) -> -7856401088 | G31: =+SUM('TB March''13'!J55:J58) -> -3868953821 | H31: =+SUM('TB June''13'!J56:J59) -> -3296695737 | I31: =+SUM('TB for 2013'!J65:J69) -> 1.6862262e+10 | K31: 2344100+2344200+2344600+2344700
B32: 4.3. ໜີ້ຕ້ອງສົ່ງລະຫວ່າງບໍລິສັດໃນກຸ່ມ | D32: ='TB 2012'!J57/1000 -> 53391.814 | E32: =+SUM('TB JAn''13'!J53) -> -56406512 | F32: =+SUM('TB Feb''13'!J53) -> 84359070 | G32: =+SUM('TB March''13'!J54) -> -85190134 | H32: =+SUM('TB June''13'!J55) -> 8130534 | I32: =+SUM('TB for 2013'!J64) -> 237683525 | K32: 2211110
B33: 4.4. ອາກອນກຳໄລຄ້າງຈ່າຍ | D33: ='TB 2012'!J63/1000 -> 1455561.6 | E33: =+SUM('TB JAn''13'!J58) -> 0 | F33: =+'TB Feb''13'!J58 -> -1.4555616e+09 | G33: =+'TB March''13'!J59 -> 2.1782006e+08 | H33: =+'TB June''13'!J60 -> -0.21999999 | I33: =+SUM('TB for 2013'!J70) -> -1.0781391e+09 | K33: 2361110
B34: 4.5. ໜີ້ຕ້ອງສົ່ງອື່ນໆ | D34: =SUM('TB 2012'!J64:J72)/1000 -> 134141.94 | E34: =+SUM('TB JAn''13'!J59:J67) -> -84593623 | F34: =+SUM('TB Feb''13'!J59:J67) -> 40218052 | G34: =+SUM('TB March''13'!J60:J68) -> 86221580 | H34: =+SUM('TB June''13'!J61:J69)-SUM('TB June''13'!I61:I69) -> 82961781 | I34: =+SUM('TB for 2013'!J71:J79) -> -1.3474711e+08 | K34: 2361120+2361130+2361140+2361410+2361420+2361430+2361440+2361830+2361831
B35: 4.6. ໜີ້ສິນໝູນວຽນອື່ນໆ | D35: =SUM('TB 2012'!J73:J76)/1000 -> 317746.77 | E35: =+SUM('TB JAn''13'!J68:J70) -> 0 | F35: =+SUM('TB Feb''13'!J68:J70) -> -27040033 | G35: =+SUM('TB March''13'!J69:J71) -> 0 | H35: =+SUM('TB June''13'!J70:J72) -> -2.5616179e+08 | I35: =+SUM('TB for 2013'!J80:J82) -> 9.3101849e+08 | K35: 2363682+2363683+2363684
B36: ຄ. ກະແສເງິນສົດສຸດທິຈາກການປ່ຽນແປງໃນໜີ້ສິນໝູນວຽນ | D36: =+D29 -> 17872192 | E36: =+E29 -> -1.2124988e+10 | F36: =+F29 -> -9.2144256e+09 | G36: =+G29 -> -3.6501023e+09 | H36: =+H29 -> -3.4617652e+09 | I36: =+I29 -> 1.6818077e+10 | J36: ok for the formula | L36: =+G36-'TB March''13'!L71 -> 0 | M36: ok
B37: ກະແສເງິນສົດສຸດທິຈາກກິດຈະກຳດຳເນີນງານ | D37: =+D18+D28+D36 -> 178529.32 | E37: =+E18+E28+E36 -> 5532000 | F37: =+F18+F28+F36 -> -2060000 | G37: =+G18+G28+G36 -> -35728350 | H37: =+H18+H28+H36 -> -414131207 | I37: =+I18+I28+I36 -> -4.4127616e+08
A38: II | B38: ​ກະແສເງິນສົດຈາກກິດຈະກໍາລົງທຶນ
B39: 1. ສ່ວນ (ເພີ່ມຂຶ້ນ) ຫຼື ຫຼຸດລົງ ໃນລາຍການເງິນລົງທຶນໄລຍະຍາວ | D39: 0 | E39: 0 | F39: 0 | G39: 0 | H39: 0 | I39: 0
B40: 2. ສ່ວນ (ເພີ່ມຂຶ້ນ) ຫຼື ຫຼຸດລົງ ໃນລາຍໜີ້ຕ້ອງຮັບໄລຍະຍາວ ແລະ ຊັບສິນໄລຍະຍາວອື່ນໆ | D40: 0 | E40: 0 | F40: 0 | G40: 0 | H40: 0 | I40: 0
B41: 3. ສ່ວນ (ເພີ່ມຂຶ້ນ) ຫຼື ຫຼຸດລົງ ໃນລາຍການຊັບສົມບັດຄົງທີ່ | D41: =-SUM('TB 2012'!I44:I49)/1000 -> -184061.32 | E41: =-SUM('TB JAn''13'!I41:I46) -> 0 | F41: =-SUM('TB Feb''13'!I41:I46) -> 2060000 | G41: =-SUM('TB March''13'!I42:I47) -> 64644.92 | H41: =-SUM('TB June''13'!I43:I48) -> -3194500 | I41: =-SUM('TB for 2013'!I51:I55) -> -6181255.1 | K41: 1441810+1442400+1442510+1442610+1442710+1442720
B42: ກະແສເງິນສົດສຸດທິຈາກກິດຈະກຳລົງທຶນ | D42: =+SUM(D39:D41) -> -184061.32 | E42: =+SUM(E39:E41) -> 0 | F42: =+SUM(F39:F41) -> 2060000 | G42: =+SUM(G39:G41) -> 64644.92 | H42: =+SUM(H39:H41) -> -3194500 | I42: =+SUM(I39:I41) -> -6181255.1
A43: III | B43: ກະແສເງິນສົດຈາກກິດຈະກຳຈັດຫາເງິນ
B44: 1. ສ່ວນ ເພີ່ມຂຶ້ນ ຫຼື (ຫຼຸດລົງ) ໃນລາຍການເງິນກູ້ຢືມມາ ແລະ ໜີ້ຕ້ອງສົ່ງໄລຍະຍາວອື່ນໆ | D44: 0 | E44: 0 | F44: 0 | G44: 0 | H44: 0 | I44: 0
B45: 2. ສ່ວນ ເພີ່ມຂຶ້ນ ຫຼື (ຫຼຸດລົງ) ໃນການອອກຮຸ້ນ | D45: 0 | E45: 0 | F45: 0 | G45: 0 | H45: 0 | I45: 0
B46: 3. ທຶນປະກອບທີ່ໄດ້ຮັບໃນປີ | D46: 0 | E46: 0 | F46: 0 | G46: =+SUM('TB March''13'!J72:J75) -> 35663705 | H46: =+SUM('TB June''13'!J73:J77) -> 417325707 | I46: =+SUM('TB for 2013'!J83:J87)-SUM('TB for 2013'!I83:I87) -> 4.5298941e+08 | K46: 3108210+3202000+3810000+3901000+3908000
B47: 4. ຈ່າຍເງິນປັນຜົນ | D47: 0 | E47: 0 | F47: 0 | G47: 0 | H47: 0 | I47: 0
B48: ກະແສເງິນສົດສຸດທິຈາກກິດຈະກຳຈັດຫາເງິນ | D48: =+SUM(D44:D47) -> 0 | E48: =+SUM(E44:E47) -> 0 | F48: =+SUM(F44:F47) -> 0 | G48: =+SUM(G44:G47) -> 35663705 | H48: =+SUM(H44:H47) -> 417325707 | I48: =+SUM(I44:I47) -> 4.5298941e+08
A49: IV | B49: ເງິນສົດ ແລະ ທຽບເທົ່າເງິນສົດ
B50: ເງິນສົດ ແລະ ທຽບເທົ່າເງິນສົດເພີ່ມຂຶ້ນ ຫຼື ຫຼຸດລົງສຸດທິໃນປີ | D50: =+D37+D42+D48 -> -5532 | E50: =+E37+E42+E48 -> 5532000 | F50: =+F37+F42+F48 -> 0 | G50: =+G37+G42+G48 -> -1.0728836e-06 | H50: =+H37+H42+H48 -> 0 | I50: =+I37+I42+I48 -> 5532000 | J50: =+'TB 2012'!L21/10000 -> -4482007.2 | K50: =+'TB 2012'!I5/1000 -> -5532 | L50: =+H50 -> 0
B51: ເງິນສົດ ແລະ ທຽບເທົ່າເງິນສົດຍັງເຫຼືອທ້າຍປີກ່ອນ | D51: ='TB 2012'!C5/1000 -> 10000 | E51: =+'TB JAn''13'!C5 -> 4468000 | F51: =+'TB Feb''13'!C5 -> 10000000 | G51: =+'TB March''13'!C5 -> 10000000 | H51: =+'TB June''13'!C5 -> 10000000 | I51: =+'TB for 2013'!C5 -> 4468000 | J51: =+#REF!/10000 -> #REF! | K51: =+K50-D50 -> -4.9950031e-05 | L51: =+'TB June''13'!J73+'TB June''13'!J74+'TB June''13'!J75+'TB June''13'!J76+'TB June''13'!J77 -> 417325707
B52: ເງິນສົດ ແລະ ທຽບເທົ່າເງິນສົດຍັງເຫຼືອທ້າຍປີນີ້ | D52: =+SUM(D50:D51) -> 4468 | E52: =+SUM(E50:E51) -> 10000000 | F52: =+SUM(F50:F51) -> 10000000 | G52: =+SUM(G50:G51) -> 10000000 | H52: =+SUM(H50:H51) -> 10000000 | I52: =+SUM(I50:I51) -> 10000000 | J52: =+SUM(J50:J51) -> #REF! | L52: =+L50+L51 -> 417325707
D53: Ok" Correct " | E53: Ok" Correct " | F53: Ok" Correct " | G53: Ok" Correct " | H53: Ok" Correct " | I53: Ok" Correct "
A55: ຜູ້ອຳນວຍການ ຫົວໜ້າພະແນກກວດກາ ຫົວໜ້າພະແນກບັນຊີ ຜູ້ສັງລວມ | I55: 0

Sheet TB 2012
A1: ສາທາລະນະລັດ ປະຊາທິປະໄຕ ປະຊາຊົນລາວ | B1: ສັນຕິພາບ ເອກະລາດ ປະຊາທິປະໄຕ ເອກະພາບ ວັດທະນາຖາວອນ | F1: 2012
A2: ບໍລິສັດຫຼັກຊັບ ທຄຕລ-ກທ ຈຳກັດ_x000D_ ຊັ້ນ7, ຕຶກຕະຫຼາກຫຼັກຊັບລາວ, ຖະໜົນກຳແພງເມືອງ_x000D_ +856-21-265477+856-21-265488
C3: Opening | E3: Movement | G3: Balance | I3: Change
C4: ໜີ້ | D4: ມີ | E4: ໜີ້ | F4: ມີ | G4: ໜີ້ | H4: ມີ | I4: ໜີ້ | J4: ມີ
A5: 1101100 | B5: ເງິນສົດໃນຄັງ " HO " ກີບ | C5: 10000000 | D5: 0 | E5: 1.4693651e+08 | F5: 1.5246851e+08 | G5: 4468000 | H5: 0 | I5: =G5-C5 -> -5532000 | L5: =+E5-F5 -> -5532000
A6: 1121110 | B6: ບັນຊີທຶນຈົດທະບຽນຂອງ ທຄຕລ-ກທ ຈຳກັດ ( ກີບ ) | C6: 7.2281614e+10 | D6: 0 | E6: 0 | F6: 70000010000 | G6: 2.2816035e+09 | H6: 0 | I6: =G6-C6 -> -70000010000 | L6: =+E6-F6 -> -70000010000
A7: 1131110 | B7: ບັນຊີກະແສລາຍວັນ ທຄຕລ: 010.0.11.00.24740 ( ກີບ ) | C7: 652607.74 | D7: 0 | E7: 2.6829711e+08 | F7: 268812113 | G7: 137607.24 | H7: 0 | I7: =G7-C7 -> -515000.5 | L7: =+E7-F7 -> -515000.5
A8: 1131111 | B8: ບັນຊີກະແສລາຍວັນ ທຄຕລ: 010.7.11.02.08233 ( ບາດ ) | C8: 713249.55 | D8: 0 | E8: 1196931.5 | F8: 121655.66 | G8: 1788525.4 | H8: 0 | I8: =G8-C8 -> 1075275.8 | L8: =+E8-F8 -> 1075275.8
A9: 1131112 | B9: ບັນຊີກະແສລາຍວັນ ທຄຕລ: 010.9.11.01.19243 ( ໂດລ່າ ) | C9: 1641620.4 | D9: 0 | E9: 69481101 | F9: 69528404 | G9: 1594317.1 | H9: 0 | I9: =G9-C9 -> -47303.28 | L9: =+E9-F9 -> -47303.28
A10: 1131113 | B10: ບັນຊີກະແສລາຍວັນ ທຄຕລ Proprietary AC: 010.4.19.00.00009 ( ກີບ ) | C10: 92595445 | D10: 0 | E10: 154946789255 | F10: 154744754910 | G10: 294629790 | H10: 0 | I10: =G10-C10 -> 202034345 | L10: =+E10-F10 -> 202034345
A11: 1131115 | B11: ບັນຊີກະແສລາຍວັນ ທຄຕລ Aggregate AC: 010.4.19.00.00010 ( ກີບ ) | C11: 39741098167 | D11: 0 | E11: 669329114813 | F11: 653419265157 | G11: 55650947823 | H11: 0 | I11: =G11-C11 -> 15909849656 | L11: =+E11-F11 -> 15909849656
A12: 1131116 | B12: ບັນຊີກະແສລາຍວັນ ທຄຕລ for ETL staff IPO AC: 010.9.00.00001 ( ກີບ ) | C12: 100000 | D12: 0 | E12: 0 | F12: 0 | G12: 100000 | H12: 0 | I12: =G12-C12 -> 0
A13: 1131117 | B13: ບັນຊີກະແສລາຍວັນ ທຄຕລ ສຳລັບການຈອງ RO EDL-Gen :010.8.19.00.00012 LAk | C13: 0 | D13: 0 | E13: 405151388000 | F13: 405151388000 | G13: 0 | H13: 0 | I13: =G13-C13 -> 0
A14: 1131119 | B14: ບັນຊີກະແສລາຍວັນ ທຄຕລ ສຳລັບການ​ຈອງ PO EDL: 010.5.19.00.00013 Lak | C14: 0 | D14: 0 | E14: 1.7653324e+10 | F14: 1.7653324e+10 | G14: 0 | H14: 0 | I14: =G14-C14 -> 0
A15: 1131120 | B15: ບັນຊີກະແສລາຍວັນ ທຄຕລ ສຳລັບການ​ຈອງ PO EDL: 010.4.19.01.00006 USD | C15: 0 | D15: 0 | E15: 1.7085271e+11 | F15: 1.7085271e+11 | G15: 0 | H15: 0 | I15: =G15-C15 -> 0 | L15: =+SUM(I5:I20) -> -4.4820072e+10 | M15: OK
A16: 1131121 | B16: ບັນຊີກະແສລາຍວັນ ເອຊີລີດາ 123359-1-1-101 | C16: 0 | D16: 0 | E16: 1000000 | F16: 0 | G16: 1000000 | H16: 0 | I16: =G16-C16 -> 1000000 | L16: =+L15-L21 -> 0
A17: 1131130 | B17: ບັນຊີຝາກປະຢັດທີ່ ທຄຕລ: 013.2.12.00.00036 ກີບ | C17: 2.2618014e+09 | D17: 0 | E17: 1.1798555e+11 | F17: 1.10998e+11 | G17: 9.2493495e+09 | H17: 0 | I17: =G17-C17 -> 6.9875481e+09
A18: 1131131 | B18: ບັນຊີຝາກປະຢັດທີ່ ທຄຕລ: 013.9.12.01.00001 ( ໂດລ່າ ) | C18: 8.9027339e+08 | D18: 0 | E18: 3.5927276e+10 | F18: 3.6787536e+10 | G18: 30012667 | H18: 0 | I18: =G18-C18 -> -8.6026073e+08 | L18: =+SUM(C5:C20) -> 1.1663937e+11 | M18: Cash for 2011
A19: 1131134 | B19: ບັນຊີຝາກປະຢັດທີ່ ທສກ: 0402.0.00.220130 ( ກີບ ) | C19: 1358879432 | D19: 0 | E19: 2110287566 | F19: 0 | G19: 3469166998 | H19: 0 | I19: =G19-C19 -> 2110287566 | L19: =+SUM(G5:G20) -> 7.1819297e+10 | M19: Cash for 2012
A20: 1131137 | B20: ບັນຊີຝາກປະຍັດ ທຄຕລ-ກທ ທີ່ ເອຊີລີດາ 123359-1-0-0101 ( ກີບ ) | C20: 0 | D20: 0 | E20: 3.5834499e+10 | F20: 35000000000 | G20: 8.3449851e+08 | H20: 0 | I20: =G20-C20 -> 8.3449851e+08
A21: 1131153 | B21: ບັນຊີຝາກມີກຳນົດທີ່ ທສກ: 0402.0402.00.2131315.47.00000003 ( ກີບ ) | C21: 20000000000 | D21: 0 | E21: 0 | F21: 0 | G21: 20000000000 | H21: 0 | I21: =G21-C21 -> 0 | L21: =+L19-L18 -> -4.4820072e+10 | M21: Change for the year
A22: 1131154 | B22: ບັນຊີຝາກມີກຳນົດທີ່ ທສກ: 0402.0402.00.2131315.47.00000004 ( ກີບ ) | C22: 0 | D22: 0 | E22: 25000000000 | F22: 0 | G22: 25000000000 | H22: 0 | I22: =G22-C22 -> 25000000000 | L22: =+L18 -> 1.1663937e+11 | M22: Cash and cash equarvalent for the last year / beginning for the year
A23: 1131156 | B23: ບັນຊີຝາກມີກຳນົດທີ່ Sacom Bank: 40.000006310.8 ( ກີບ ) | C23: 0 | D23: 0 | E23: 30000000000 | F23: 30000000000 | G23: 0 | H23: 0 | I23: =G23-C23 -> 0 | L23: =+SUM(L21:L22) -> 7.1819297e+10
A24: 1131159 | B24: ບັນຊີຝາກມີກຳນົດທີ່ ST Bank: 010.5.35.00.08899 ( ກີບ ) | C24: 0 | D24: 0 | E24: 5000000000 | F24: 0 | G24: 5000000000 | H24: 0 | I24: =G24-C24 -> 5000000000
A25: 1131162 | B25: ບັນຊີເງິນຝາກມີກຳນົດ ທີ່ ທະນາຄານ ເອຊີລີດາ ( ກີບ ) | C25: 0 | D25: 0 | E25: 35000000000 | F25: 0 | G25: 35000000000 | H25: 0 | I25: =G25-C25 -> 35000000000
A26: 1137111 | B26: ດອກເບ້ຍຝາກມີກຳນົດ ຄ້າງຮັບ 1 ປີລົງມາ | C26: 169863014 | D26: 0 | E26: 5824469182 | F26: 5.3326256e+09 | G26: 6.6170662e+08 | H26: 0 | I26: =G26-C26 -> 4.9184361e+08
A27: 1138100 | B27: ກອງທຶນປົກປ້ອງຄວາມສ່ຽງໃນການຊຳລະສະສາງ | C27: 136517614 | D27: 0 | E27: 18938509 | F27: 342 | G27: 155455781 | H27: 0 | I27: =G27-C27 -> 18938167
A28: 1138810 | B28: ເງິນມັດຈຳຄ່າເຊົ່າ | C28: 11888910 | D28: 0 | E28: 0 | F28: 0 | G28: 11888910 | H28: 0 | I28: =G28-C28 -> 0
A29: 1138830 | B29: ເງິນມັດຈຳອື່ນໆ | C29: 0 | D29: 0 | E29: 4449332 | F29: 4449332 | G29: 0 | H29: 0 | I29: =G29-C29 -> 0
A30: 1201181 | B30: ລູກໜີ້ຊື້ຫຼັກຊັບຕາມຄຳສັ່ງຊື້-ບັນຊີເງິນສົດ | C30: 4284683 | D30: 0 | E30: 23279067826 | F30: 23224531620 | G30: 58820889 | H30: 0 | I30: =G30-C30 -> 54536206
A31: 1211110 | B31: ລູກໜີ້ບັນຊີຊື້-ຂາຍຫຼັກຊັບລະຫວ່າງບ/ສ ກັບ LSX | C31: 23823233 | D31: 0 | E31: 5742141356 | F31: 5765964589 | G31: 0 | H31: 0 | I31: =G31-C31 -> -23823233
A32: 1301720 | B32: ຄ່າທີ່ປຶກສາຄ້າງຮັບ | C32: 0 | D32: 0 | E32: 1024442620 | F32: 488583100 | G32: 535859520 | H32: 0 | I32: =G32-C32 -> 535859520 | L32: =-SUM('TB 2012'!I35:I43)/1000-SUM('TB 2012'!I27:I29)/1000 -> -197710.1
A33: 1302216 | B33: ເງິນລົງທືນຊົ່ວຄາວຫຼັກຊັບ-ເພື່ອຄ້າ-Port Trading | C33: 117180970 | D33: 0 | E33: 5.5465994e+08 | F33: 197620970 | G33: 4.7421994e+08 | H33: 0 | I33: =G33-C33 -> 3.5703897e+08
A34: 1302218 | B34: ຄ່າປັບມູນຄ່າເງິນລົງທືນຊົ່ວຄາວຫຼັກຊັບ-ເພື່ອຄ້າ-Port trading | C34: 0 | D34: 37250970 | E34: 4.0190649e+08 | F34: 3.2395527e+08 | G34: 40700260 | H34: 0 | I34: =G34-C34+D34 -> 77951230 | L34: =+E34-F34 -> 77951230
A35: 1360000 | B35: ລູກໜີ້ອື່ນໆ | C35: 61100181 | D35: 0 | E35: 4846066 | F35: 59977664 | G35: 5968583 | H35: 0 | I35: =G35-C35 -> -55131598 | L35: =+E35-F35 -> -55131598
A36: 1361100 | B36: ອາກອນກຳໄລມອບລ່ວງໜ້າ | C36: 27761356 | D36: 0 | E36: 99581906 | F36: 1.2734326e+08 | G36: 0 | H36: 0 | I36: =G36-C36 -> -27761356 | L36: =+E36-F36 -> -27761356
A37: 1361300 | B37: ອາກອນອື່ນໆທີ່ຕ້ອງຮັບຄືນ | C37: 27382364 | D37: 0 | E37: 6845600 | F37: 34227964 | G37: 0 | H37: 4.7683716e-09 | I37: =G37-C37 -> -27382364 | L37: =+E37-F37 -> -27382364
A38: 1361500 | B38: ລູນໜີ້ ເຄທີຂີມີໂກ້ ຈຳກັດ | C38: 0 | D38: 0 | E38: 94848000 | F38: 94848000 | G38: 0 | H38: 0 | I38: =G38-C38 -> 0 | L38: =+E38-F38 -> 0
A39: 1362100 | B39: ເງິນຈ່າຍລ່ວງໜ້າເພື່ອເຄື່ອນໄຫວວຽກງານ | C39: 36400000 | D39: 0 | E39: 243979076 | F39: 279879076 | G39: 500000 | H39: 0 | I39: =G39-C39 -> -35900000 | L39: =+E39-F39 -> -35900000
A40: 1388110 | B40: ຄ່າເຊົ່າຈ່າຍລ່ວງໜ້າ | C40: 23950902 | D40: 0 | E40: 9.7255238e+08 | F40: 5.5573423e+08 | G40: 4.4076906e+08 | H40: 0 | I40: =G40-C40 -> 4.1681815e+08 | L40: =+E40-F40 -> 4.1681815e+08
A41: 1388120 | B41: ຄ່າປະກັນໄພຈ່າຍລ່ວງໜ້າ | C41: 2097153.1 | D41: 0 | E41: 2.447531e+08 | F41: 1.2655419e+08 | G41: 1.2029605e+08 | H41: 0 | I41: =G41-C41 -> 1.181989e+08 | L41: =+E41-F41 -> 1.181989e+08
A42: 1388170 | B42: ຄ່າໜັງສືພີມ ຈ່າຍລ່ວງໜ້າອື່ນໆ | C42: 2.1599591e+08 | D42: 0 | E42: 5280000 | F42: 2.2105951e+08 | G42: 216393.45 | H42: 0 | I42: =G42-C42 -> -2.1577951e+08 | L42: =+E42-F42 -> -2.1577951e+08
A43: 1388180 | B43: ລາຍຈ່າຍ ຈ່າຍລ່ວງໜ້າອື່ນໆ | C43: 0 | D43: 0 | E43: 9971500 | F43: 4261791.8 | G43: 5709708.2 | H43: 0 | I43: =G43-C43 -> 5709708.2 | L43: =+E43-F43 -> 5709708.2
A44: 1441810 | B44: ຊັອບແວຄອມພີວເຕີ່ | C44: 2.7021397e+08 | D44: 0 | E44: 48000000 | F44: 10435920 | G44: 3.0777805e+08 | H44: 0 | I44: =G44-C44 -> 37564080 | L44: =+E44-F44 -> 37564080
A45: 1442400 | B45: ພາຫະນະຂົນສົ່ງ | C45: 615368000 | D45: 0 | E45: 14000000 | F45: 0 | G45: 629368000 | H45: 0 | I45: =G45-C45 -> 14000000 | L45: =+E45-F45 -> 14000000
A46: 1442510 | B46: ຄ່າຕົບແຕ່ງສຳນັກງານ | C46: 1.5394821e+09 | D46: 0 | E46: 8190000 | F46: 0 | G46: 1.5476721e+09 | H46: 0 | I46: =G46-C46 -> 8190000 | L46: =+E46-F46 -> 8190000
... A49: 1442720 | B49: ອຸປະກອນເຟີນີເຈີ່ | C49: 3.7393916e+08 | D49: 0 | E49: 8485500 | F49: 1335000 | G49: 3.8108966e+08 | H49: 0 | I49: =G49-C49 -> 7150500 | L49: =+E49-F49 -> 7150500
A50: 1481181 | B50: ຄ່າຕັດຈຳໜ່າຍຄອມພີວເຕີ່ຊ້ອບແວສະສົມ | C50: 0 | D50: 33563188 | E50: 10435920 | F50: 35543316 | G50: 0 | H50: 58670585 | J50: =H50-D50 -> 25107396
A51: 1481240 | B51: ຄ່າຫຼຸ່ຍຫ້ຽນສະສົມພາຫະນະ | C51: 0 | D51: 1.1976696e+08 | E51: 0 | F51: 1.2444235e+08 | G51: 0 | H51: 2.4420932e+08 | J51: =H51-D51 -> 1.2444235e+08
A52: 1481251 | B52: ຄ່າຫຼຸ່ຍຫ້ຽນສະສົມ ຄ່າຕົບແຕ່ງສຳນັກງານ | C52: 0 | D52: 1.5065818e+08 | E52: 27897.87 | F52: 1.5581786e+08 | G52: 0 | H52: 3.0644814e+08 | J52: =H52-D52 -> 1.5578996e+08
A53: 1481261 | B53: ຄ່າຫຼຸ່ຍຫ້ຽນສະສົມ ອຸປະກອນຄອມພີວເຕີ່ | C53: 0 | D53: 49361921 | E53: 506325.48 | F53: 63897227 | G53: 0 | H53: 1.1275282e+08 | J53: =H53-D53 -> 63390901
A54: 1481271 | B54: ຄ່າຫຼຸ່ຍຫ້ຽນສະສົມ ອຸປະກອນສຳນັກງານ | C54: 0 | D54: 7995341.2 | E54: 579192.2 | F54: 12830355 | G54: 0 | H54: 20246504 | J54: =H54-D54 -> 12251163
A55: 1481272 | B55: ຄ່າຫຼຸ່ຍຫ້ຽນສະສົມ ເຟີນີເຈີ່ | C55: 0 | D55: 35686254 | E55: 260933.48 | F55: 37978167 | G55: 0 | H55: 73403487 | J55: =H55-D55 -> 37717233
A56: 1482280 | B56: ບັນຊີພັກອື່ນໆ | C56: 0 | D56: 0 | E56: 24371500 | F56: 24371500 | G56: 0 | H56: 0 | J56: =H56-D56 -> 0
A57: 2211110 | B57: ເຈົ້າໜີ້ຕະຫຼາດຫຼັກຊັບ LSX | C57: 0 | D57: 3845762 | E57: 23018403859 | F57: 23071795673 | G57: 0 | H57: 57237576 | J57: =H57-D57 -> 53391814
A58: 2267100 | B58: ຄ່າເບ້ຍປະຊຸມຄ້າງຈ່າຍ | C58: 0 | D58: 0 | E58: 3500000 | F58: 3500000 | G58: 0 | H58: 0 | J58: =H58-D58 -> 0
A59: 2344100 | B59: ເຈົ້າໜີ້ບັນຊີຊື້-ຂາຍຫຼັກຊັບຕາມຄຳສັ່ງຊື້-ບັນຊີເງິນສົດ | C59: 0 | D59: 23694855 | E59: 5763349746 | F59: 5739654891 | G59: 0 | H59: 0 | J59: =H59-D59 -> -23694855
A60: 2344200 | B60: ບັນຊີເງິນລູກຄ້າ- Cash Balance | C60: 0 | D60: 39741098167 | E60: 653431862481 | F60: 669341712137 | G60: 0 | H60: 55650947823 | J60: =H60-D60 -> 15909849656
A61: 2344600 | B61: ບັນຊີເຈົ້າໜີ້ຄ່າຈອງຊື້ຮຸ້ນ | C61: 0 | D61: 0 | E61: 405151388000 | F61: 405151388000 | G61: 0 | H61: 0 | J61: =H61-D61 -> 0
... A78: 3810000 | B78: ກຳໄລ-ຂາດທຶນສະສົມ | C78: 0 | D78: 1.9182372e+08 | E78: 0 | F78: 0 | G78: 0 | H78: 1.9182372e+08 | J78: =H78-D78 -> 0
C81: =SUM(C5:C78) -> 1.4096742e+11 | D81: =SUM(D5:D78) -> 1.4096742e+11 | E81: =SUM(E5:E78) -> 3015176882011 | F81: =SUM(F5:F78) -> 3.0114127e+12 | G81: =SUM(G5:G78) -> 1.6298527e+11 | H81: =SUM(H5:H78) -> 1.5922106e+11 | I81: =SUM(I5:I78) -> 2.2055106e+10 | J81: =SUM(J5:J78) -> 1.8290891e+10
D83: =C81-D81 -> 0 | F83: =E81-F81 -> 3.7642156e+09 | H83: =G81-H81 -> 3.7642156e+09 | J83: =I81-J81 -> 3.7642156e+09
A86: 4102730 | B86: ຄ່າບໍລິການເຊົ່າລະບົບເທີມີນໍ່ LSX | C86: 0 | D86: 0 | E86: 2.4354702e+08 | F86: 0 | G86: 2.4354702e+08 | H86: 0 | J86: =F86-E86 -> -2.4354702e+08
A87: 4102731 | B87: ຄ່າບໍລິການເຊົ່າລະບົບດິດສເປຣເຢີ່ LSX | C87: 0 | D87: 0 | E87: 33168305 | F87: 0 | G87: 33168305 | H87: 0 | J87: =F87-E87 -> -33168305
A88: 4108210 | B88: ຄ່າທຳນຽມທະນາຄານ ( ຈ່າຍ ) | C88: 0 | D88: 0 | E88: 11148726 | F88: 0 | G88: 11148726 | H88: 0 | J88: =F88-E88 -> -11148726
A89: 4201100 | B89: ເງິນເດືອນພະນັກງານໃນການຈັດຕັ້ງ | C89: 0 | D89: 0 | E89: 1918944102 | F89: 0 | G89: 1918944102 | H89: 0 | J89: =F89-E89 -> -1918944102
A90: 4201200 | B90: ເງິນເດືອນພະນັກງານຊົ່ວຄາວ | C90: 0 | D90: 0 | E90: 23070661 | F90: 0 | G90: 23070661 | H90: 0 | J90: =F90-E90 -> -23070661
A91: 4201400 | B91: ເງິນເພີ່ມໂມງ | C91: 0 | D91: 0 | E91: 59776012 | F91: 0 | G91: 59776012 | H91: 0 | J91: =F91-E91 -> -59776012
A92: 4202110 | B92: ເງິນບຳເນັດ | C92: 0 | D92: 0 | E92: 9425000 | F92: 0 | G92: 9425000 | H92: 0 | J92: =F92-E92 -> -9425000
A93: 4202200 | B93: ລາຍຈ່າຍຄ່າປະກັນໄພພະນັກງານ | C93: 0 | D93: 0 | E93: 1.0562448e+08 | F93: 0 | G93: 1.0562448e+08 | H93: 0 | J93: =F93-E93 -> -1.0562448e+08
A94: 4202210 | B94: ລາຍຈ່າຍຄ່າຮັກສາພະຍາບານ | C94: 0 | D94: 0 | E94: 4473203 | F94: 0 | G94: 4473203 | H94: 0 | J94: =F94-E94 -> -4473203
A95: 4202220 | B95: ລາຍຈ່າຍຄ່ານ້ຳມັນລົດພະນັກງານ | C95: 0 | D95: 0 | E95: 187500000 | F95: 0 | G95: 187500000 | H95: 0 | J95: =F95-E95 -> -187500000
A96: 4202800 | B96: ລາຍຈ່າຍສະຫວັດດີການພະນັກງານອື່ນໆ | C96: 0 | D96: 0 | E96: 82586000 | F96: 0 | G96: 82586000 | H96: 0 | J96: =F96-E96 -> -82586000
A97: 4202811 | B97: ລາຍຈ່າຍເບ້ຍປະຊູມສະພາບໍລິຫານ | C97: 0 | D97: 0 | E97: 46695436 | F97: 642807 | G97: 46052629 | H97: 0 | J97: =F97-E97 -> -46052629
... A172: 5508400 | B172: ລາຍຮັບອື່ນໆ | C172: 0 | D172: 0 | E172: 0 | F172: 15099335 | G172: 0 | H172: 15099335 | J172: =F172-E172 -> 15099335
C174: =SUM(C86:C173) -> 0 | D174: =SUM(D86:D173) -> 0 | E174: =SUM(E86:E173) -> 5.4556957e+10 | F174: =SUM(F86:F173) -> 58321172365 | G174: =SUM(G86:G173) -> 5.0475178e+10 | H174: =SUM(H86:H173) -> 5.4239393e+10 | I174: =SUM(I86:I173) -> 0 | J174: =SUM(J86:J173) -> 3.7642156e+09
F176: =F174-E174 -> 3.7642156e+09 | H176: =H174-G174 -> 3.7642156e+09 | J176: =J174-H83 -> 0
B181: ລວມມູນຄ່າ | C181: 1.4096742e+11 | D181: 1.4096742e+11 | E181: 3.0697338e+12 | F181: 3.0697338e+12 | G181: 2.1346045e+11 | H181: 2.1346045e+11
C183: ນະຄອນຫຼວງວຽງຈັນ ວັນທີ : ......../......../............ , | D183: ຜູ້ອຳນວຍການ | E183: ທີ່ປຶກສາບັນຊີ | F183: ພະນັກງານບັນຊີ | G183: ຜູ້ສັງລວມ | H183: ............…………………...... | I183: ............…………………......

Sheet TB JAn'13
A1: ສາທາລະນະລັດ ປະຊາທິປະໄຕ ປະຊາຊົນລາວ | B1: ສັນຕິພາບ ເອກະລາດ ປະຊາທິປະໄຕ ເອກະພາບ ວັດທະນາຖາວອນ
D3: ໃບດູນດ່ຽງປະຈຳເດືອນ | E3: ເດືອນ 01/2013 | F3: ບໍລິສັດຫຼັກຊັບ ທຄຕລ-ກທ ຈຳກັດ_x000D_ ຊັ້ນ7, ຕຶກຕະຫຼາກຫຼັກຊັບລາວ, ຖະໜົນກຳແພງເມືອງ_x000D_ +856-21-265477+856-21-265488
C4: ໜີ້ | D4: ມີ | E4: ໜີ້ | F4: ມີ | G4: ໜີ້ | H4: ມີ
A5: 1101100 | B5: ເງິນສົດໃນຄັງ " HO " ກີບ | C5: 4468000 | D5: 0 | E5: 16629470 | F5: 11097470 | G5: 10000000 | H5: 0 | I5: =+G5-C5 -> 5532000 | J5: =+H5-D5 -> 0
A6: 1121110 | B6: ບັນຊີທຶນຈົດທະບຽນຂອງ ທຄຕລ-ກທ ຈຳກັດ ( ກີບ ) | C6: 2.2816035e+09 | D6: 0 | E6: 0 | F6: 0 | G6: 2.2816035e+09 | H6: 0 | I6: =+G6-C6 -> 0 | J6: =+H6-D6 -> 0
A7: 1131110 | B7: ບັນຊີກະແສລາຍວັນ ທຄຕລ: 010.0.11.00.24740 ( ກີບ ) | C7: 137607.24 | D7: 0 | E7: 0 | F7: 0 | G7: 137607.24 | H7: 0 | I7: =+G7-C7 -> 0 | J7: =+H7-D7 -> 0
A8: 1131111 | B8: ບັນຊີກະແສລາຍວັນ ທຄຕລ: 010.7.11.02.08233 ( ບາດ ) | C8: 1788525.4 | D8: 0 | E8: 1.3757003e+08 | F8: 137083.21 | G8: 1.3922147e+08 | H8: 0 | I8: =+G8-C8 -> 1.3743295e+08 | J8: =+H8-D8 -> 0
A9: 1131112 | B9: ບັນຊີກະແສລາຍວັນ ທຄຕລ: 010.9.11.01.19243 ( ໂດລ່າ ) | C9: 1594317.1 | D9: 0 | E9: 0 | F9: 9604.32 | G9: 1584712.8 | H9: 0 | I9: =+G9-C9 -> -9604.32 | J9: =+H9-D9 -> 0
A10: 1131113 | B10: ບັນຊີກະແສລາຍວັນ ທຄຕລ Proprietary AC: 010.4.19.00.00009 ( ກີບ ) | C10: 294629790 | D10: 0 | E10: 2491046499 | F10: 2562293702 | G10: 223382587 | H10: 0 | I10: =+G10-C10 -> -71247203 | J10: =+H10-D10 -> 0
A11: 1131115 | B11: ບັນຊີກະແສລາຍວັນ ທຄຕລ Aggregate AC: 010.4.19.00.00010 ( ກີບ ) | C11: 55650947823 | D11: 0 | E11: 8187959711 | F11: 20285288714 | G11: 43553618820 | H11: 0 | I11: =+G11-C11 -> -12097329003 | J11: =+H11-D11 -> 0
A12: 1131116 | B12: ບັນຊີກະແສລາຍວັນ ທຄຕລ for ETL staff IPO AC: 010.9.00.00001 ( ກີບ ) | C12: 100000 | D12: 0 | E12: 0 | F12: 0 | G12: 100000 | H12: 0 | I12: =+G12-C12 -> 0 | J12: =+H12-D12 -> 0
A13: 1131117 | B13: ບັນຊີກະແສລາຍວັນ ທຄຕລ ສຳລັບການຈອງ RO EDL-Gen :010.8.19.00.00012 LAk | C13: 0 | D13: 0 | E13: 0 | F13: 0 | G13: 0 | H13: 0 | I13: =+G13-C13 -> 0 | J13: =+H13-D13 -> 0
A14: 1131119 | B14: ບັນຊີກະແສລາຍວັນ ທຄຕລ ສຳລັບການ​ຈອງ PO EDL: 010.5.19.00.00013 Lak | C14: 3.8146973e-06 | D14: 0 | E14: 0 | F14: 0 | G14: 3.8146973e-06 | H14: 0 | I14: =+G14-C14 -> 0 | J14: =+H14-D14 -> 0
A15: 1131120 | B15: ບັນຊີກະແສລາຍວັນ ທຄຕລ ສຳລັບການ​ຈອງ PO EDL: 010.4.19.01.00006 USD | C15: 0 | D15: 1.3425946e-05 | E15: 0 | F15: 0 | G15: 0 | H15: 1.3425946e-05 | I15: =+G15-C15 -> 0 | J15: =+H15-D15 -> 0
A16: 1131121 | B16: ບັນຊີກະແສລາຍວັນ ເອຊີລີດາ 123359-1-1-101 | C16: 1000000 | D16: 0 | E16: 0 | F16: 0 | G16: 1000000 | H16: 0 | I16: =+G16-C16 -> 0 | J16: =+H16-D16 -> 0
... A74: 3908000 | B74: ຜົນໄດ້ຮັບ ລໍຖ້າຮັບຮອງ | C74: 0 | D74: 0 | E74: 0 | F74: 3.7642156e+09 | G74: 0 | H74: 3.7642156e+09 | I74: =+G74-C74 -> 0 | J74: =+H74-D74 -> 3.7642156e+09
B75: Total | C75: =SUM(C5:C74) -> 1.6298527e+11 | D75: =SUM(D5:D74) -> 1.6298527e+11 | E75: =SUM(E5:E74) -> 4.2050835e+10 | F75: =SUM(F5:F74) -> 4.1806911e+10 | G75: =SUM(G5:G74) -> 1.5114381e+11 | H75: =SUM(H5:H74) -> 1.5089988e+11 | I75: =SUM(I5:I74) -> -1.1841468e+10 | J75: =SUM(J5:J74) -> -1.2085392e+10
B76: Net profit | D76: =+C75-D75 -> 0 | F76: =+E75-F75 -> 2.4392347e+08 | H76: =+G75-H75 -> 2.4392347e+08 | J76: =+I75-J75 -> 2.4392347e+08 | L76: =+J76-H76 -> -1.335144e-05
C79: ໜີ້ | D79: ມີ | E79: ໜີ້ | F79: ມີ | G79: ໜີ້ | H79: ມີ | I79: Net profit
A80: 4102730 | B80: ຄ່າບໍລິການເຊົ່າລະບົບເທີມີນໍ່ LSX | C80: 0 | D80: 0 | E80: 21158280 | F80: 0 | G80: 21158280 | H80: 0 | I80: =+F80-E80 -> -21158280
A81: 4102731 | B81: ຄ່າບໍລິການເຊົ່າລະບົບດິດສເປຣເຢີ່ LSX | C81: 0 | D81: 0 | E81: 2566080 | F81: 0 | G81: 2566080 | H81: 0 | I81: =+F81-E81 -> -2566080
A82: 4108210 | B82: ຄ່າທຳນຽມທະນາຄານ ( ຈ່າຍ ) | C82: 0 | D82: 0 | E82: 369951.21 | F82: 0 | G82: 369951.21 | H82: 0 | I82: =+F82-E82 -> -369951.21
A83: 4201100 | B83: ເງິນເດືອນພະນັກງານໃນການຈັດຕັ້ງ | C83: 0 | D83: 0 | E83: 159159677 | F83: 0 | G83: 159159677 | H83: 0 | I83: =+F83-E83 -> -159159677
A84: 4201400 | B84: ເງິນເພີ່ມໂມງ | C84: 0 | D84: 0 | E84: 47351378 | F84: 0 | G84: 47351378 | H84: 0 | I84: =+F84-E84 -> -47351378
A85: 4202200 | B85: ລາຍຈ່າຍຄ່າປະກັນໄພພະນັກງານ | C85: 0 | D85: 0 | E85: 10198798 | F85: 0 | G85: 10198798 | H85: 0 | I85: =+F85-E85 -> -10198798
A86: 4202220 | B86: ລາຍຈ່າຍຄ່ານ້ຳມັນລົດພະນັກງານ | C86: 0 | D86: 0 | E86: 17283871 | F86: 0 | G86: 17283871 | H86: 0 | I86: =+F86-E86 -> -17283871
A87: 4202800 | B87: ລາຍຈ່າຍສະຫວັດດີການພະນັກງານອື່ນໆ | C87: 0 | D87: 0 | E87: 14000000 | F87: 0 | G87: 14000000 | H87: 0 | I87: =+F87-E87 -> -14000000
A88: 4202811 | B88: ລາຍຈ່າຍເບ້ຍປະຊູມສະພາບໍລິຫານ | C88: 0 | D88: 0 | E88: 10736842 | F88: 0 | G88: 10736842 | H88: 0 | I88: =+F88-E88 -> -10736842
A89: 4203100 | B89: ສຳມະນາ ແລະຝຶກອົບຮົມພາຍໃນປະເທດ | C89: 0 | D89: 0 | E89: 5000000 | F89: 0 | G89: 5000000 | H89: 0 | I89: =+F89-E89 -> -5000000
A90: 4208400 | B90: ຄ່າອາຫານຈັດປະຂູມພະນັກງານ | C90: 0 | D90: 0 | E90: 4087400 | F90: 0 | G90: 4087400 | H90: 0 | I90: =+F90-E90 -> -4087400
A91: 4208500 | B91: ນ້ຳດື່ມພະນັກງານ | C91: 0 | D91: 0 | E91: 2752000 | F91: 0 | G91: 2752000 | H91: 0 | I91: =+F91-E91 -> -2752000
... A136: 5508400 | B136: ລາຍຮັບອື່ນໆ | C136: 0 | D136: 0 | E136: 0 | F136: 2000 | G136: 0 | H136: 2000 | I136: =+F136-E136 -> 2000
B137: ລວມມູນຄ່າ | C137: =SUM(C80:C136) -> 0 | D137: =SUM(D80:D136) -> 0 | E137: =SUM(E80:E136) -> 6.6914401e+08 | F137: =SUM(F80:F136) -> 9.1306748e+08 | G137: =SUM(G80:G136) -> 6.4342647e+08 | H137: =SUM(H80:H136) -> 8.8734993e+08 | J137: 0 | K137: -5.859375e-05 | L137: ນະຄອນຫຼວງວຽງຈັນ ວັນທີ : ......../......../............ , | M137: ຜູ້ອຳນວຍການ | N137: ທີ່ປຶກສາບັນຊີ | O137: ພະນັກງານບັນຊີ | P137: ຜູ້ສັງລວມ | Q137: ............…………………...... | R137: ...…………………………..
A138: 1 | B138: Net Profit | E138: =+F137-E137 -> 2.4392347e+08 | G138: =+H137-G137 -> 2.4392347e+08 | I138: =SUM(I80:I136) -> 2.4392347e+08

Sheet TB Feb'13
A1: ສາທາລະນະລັດ ປະຊາທິປະໄຕ ປະຊາຊົນລາວ | B1: ສັນຕິພາບ ເອກະລາດ ປະຊາທິປະໄຕ ເອກະພາບ ວັດທະນາຖາວອນ
D3: ໃບດູນດ່ຽງປະຈຳເດືອນ | E3: ເດືອນ 02/2013 | F3: ບໍລິສັດຫຼັກຊັບ ທຄຕລ-ກທ ຈຳກັດ_x000D_ ຊັ້ນ7, ຕຶກຕະຫຼາກຫຼັກຊັບລາວ, ຖະໜົນກຳແພງເມືອງ_x000D_ +856-21-265477+856-21-265488
C4: ໜີ້ | D4: ມີ | E4: ໜີ້ | F4: ມີ | G4: ໜີ້ | H4: ມີ
A5: 1101100 | B5: ເງິນສົດໃນຄັງ " HO " ກີບ | C5: 10000000 | D5: 0 | E5: 6084000 | F5: 6084000 | G5: 10000000 | H5: 0 | I5: =+G5-C5 -> 0 | J5: =+H5-D5 -> 0
A6: 1121110 | B6: ບັນຊີທຶນຈົດທະບຽນຂອງ ທຄຕລ-ກທ ຈຳກັດ ( ກີບ ) | C6: 2.2816035e+09 | D6: 0 | E6: 0 | F6: 0 | G6: 2.2816035e+09 | H6: 0 | I6: =+G6-C6 -> 0 | J6: =+H6-D6 -> 0
A7: 1131110 | B7: ບັນຊີກະແສລາຍວັນ ທຄຕລ: 010.0.11.00.24740 ( ກີບ ) | C7: 137607.24 | D7: 0 | E7: 0 | F7: 0 | G7: 137607.24 | H7: 0 | I7: =+G7-C7 -> 0 | J7: =+H7-D7 -> 0
A8: 1131111 | B8: ບັນຊີກະແສລາຍວັນ ທຄຕລ: 010.7.11.02.08233 ( ບາດ ) | C8: 1.3922147e+08 | D8: 0 | E8: 0 | F8: 1512764.8 | G8: 1.3770871e+08 | H8: 0 | I8: =+G8-C8 -> -1512764.8 | J8: =+H8-D8 -> 0
A9: 1131112 | B9: ບັນຊີກະແສລາຍວັນ ທຄຕລ: 010.9.11.01.19243 ( ໂດລ່າ ) | C9: 1584712.8 | D9: 0 | E9: 0 | F9: 56448.14 | G9: 1528264.7 | H9: 0 | I9: =+G9-C9 -> -56448.14 | J9: =+H9-D9 -> 0
A10: 1131113 | B10: ບັນຊີກະແສລາຍວັນ ທຄຕລ Proprietary AC: 010.4.19.00.00009 ( ກີບ ) | C10: 223382587 | D10: 0 | E10: 4208520969 | F10: 4222432666 | G10: 209470890 | H10: 0 | I10: =+G10-C10 -> -13911697 | J10: =+H10-D10 -> 0
A11: 1131115 | B11: ບັນຊີກະແສລາຍວັນ ທຄຕລ Aggregate AC: 010.4.19.00.00010 ( ກີບ ) | C11: 43553618820 | D11: 0 | E11: 14707025363 | F11: 22424890783 | G11: 35835753400 | H11: 0 | I11: =+G11-C11 -> -7717865420 | J11: =+H11-D11 -> 0
A12: 1131116 | B12: ບັນຊີກະແສລາຍວັນ ທຄຕລ for ETL staff IPO AC: 010.9.00.00001 ( ກີບ ) | C12: 100000 | D12: 0 | E12: 0 | F12: 0 | G12: 100000 | H12: 0 | I12: =+G12-C12 -> 0 | J12: =+H12-D12 -> 0
A13: 1131117 | B13: ບັນຊີກະແສລາຍວັນ ທຄຕລ ສຳລັບການຈອງ RO EDL-Gen :010.8.19.00.00012 LAk | C13: 0 | D13: 0 | E13: 0 | F13: 0 | G13: 0 | H13: 0 | I13: =+G13-C13 -> 0 | J13: =+H13-D13 -> 0
A14: 1131119 | B14: ບັນຊີກະແສລາຍວັນ ທຄຕລ ສຳລັບການ​ຈອງ PO EDL: 010.5.19.00.00013 Lak | C14: 3.8146973e-06 | D14: 0 | E14: 0 | F14: 0 | G14: 3.8146973e-06 | H14: 0 | I14: =+G14-C14 -> 0 | J14: =+H14-D14 -> 0
A15: 1131120 | B15: ບັນຊີກະແສລາຍວັນ ທຄຕລ ສຳລັບການ​ຈອງ PO EDL: 010.4.19.01.00006 USD | C15: 0 | D15: 1.3425946e-05 | E15: 0 | F15: 0 | G15: 0 | H15: 1.3425946e-05 | I15: =+G15-C15 -> 0 | J15: =+H15-D15 -> 0
A16: 1131121 | B16: ບັນຊີກະແສລາຍວັນ ເອຊີລີດາ 123359-1-1-101 | C16: 1000000 | D16: 0 | E16: 0 | F16: 0 | G16: 1000000 | H16: 0 | I16: =+G16-C16 -> 0 | J16: =+H16-D16 -> 0
... A74: 3908000 | B74: ຜົນໄດ້ຮັບ ລໍຖ້າຮັບຮອງ | C74: 0 | D74: 3.7642156e+09 | E74: 0 | F74: 0 | G74: 0 | H74: 3.7642156e+09 | I74: =+G74-C74 -> 0 | J74: =+H74-D74 -> 0
C75: =SUM(C5:C74) -> 1.5114381e+11 | D75: =SUM(D5:D74) -> 1.5089988e+11 | E75: =SUM(E5:E74) -> 5.2954219e+10 | F75: =SUM(F5:F74) -> 5.2569874e+10 | G75: =SUM(G5:G74) -> 1.4234191e+11 | H75: =SUM(H5:H74) -> 1.4171364e+11 | I75: =SUM(I5:I74) -> -8.8018932e+09 | J75: =SUM(J5:J74) -> -9.1862385e+09
D76: =+C75-D75 -> 2.4392347e+08 | F76: =+E75-F75 -> 3.8434523e+08 | H76: =+G75-H75 -> 6.2826869e+08 | J76: =+I75-J75 -> 3.8434523e+08
C79: ໜີ້ | D79: ມີ | E79: ໜີ້ | F79: ມີ | G79: ໜີ້ | H79: ມີ | I79: Net profit
A80: 4102730 | B80: ຄ່າບໍລິການເຊົ່າລະບົບເທີມີນໍ່ LSX | C80: 21158280 | D80: 0 | E80: 21035391 | F80: 0 | G80: 42193671 | H80: 0 | I80: =+F80-E80 -> -21035391
A81: 4102731 | B81: ຄ່າບໍລິການເຊົ່າລະບົບດິດສເປຣເຢີ່ LSX | C81: 2566080 | D81: 0 | E81: 2551176 | F81: 0 | G81: 5117256 | H81: 0 | I81: =+F81-E81 -> -2551176
A82: 4108210 | B82: ຄ່າທຳນຽມທະນາຄານ ( ຈ່າຍ ) | C82: 369951.21 | D82: 0 | E82: 226048 | F82: 0 | G82: 595999.21 | H82: 0 | I82: =+F82-E82 -> -226048
A83: 4201100 | B83: ເງິນເດືອນພະນັກງານໃນການຈັດຕັ້ງ | C83: 159159677 | D83: 0 | E83: 156450000 | F83: 0 | G83: 315609677 | H83: 0 | I83: =+F83-E83 -> -156450000
A84: 4201400 | B84: ເງິນເພີ່ມໂມງ | C84: 47351378 | D84: 0 | E84: 2451289 | F84: 0 | G84: 49802667 | H84: 0 | I84: =+F84-E84 -> -2451289
A85: 4202200 | B85: ລາຍຈ່າຍຄ່າປະກັນໄພພະນັກງານ | C85: 10198798 | D85: 0 | E85: 9729001.1 | F85: 0 | G85: 19927800 | H85: 0 | I85: =+F85-E85 -> -9729001.1
A86: 4202220 | B86: ລາຍຈ່າຍຄ່ານ້ຳມັນລົດພະນັກງານ | C86: 17283871 | D86: 0 | E86: 16800000 | F86: 0 | G86: 34083871 | H86: 0 | I86: =+F86-E86 -> -16800000
A87: 4202800 | B87: ລາຍຈ່າຍສະຫວັດດີການພະນັກງານອື່ນໆ | C87: 14000000 | D87: 0 | E87: 0 | F87: 0 | G87: 14000000 | H87: 0 | I87: =+F87-E87 -> 0
A88: 4202811 | B88: ລາຍຈ່າຍເບ້ຍປະຊູມສະພາບໍລິຫານ | C88: 10736842 | D88: 0 | E88: 0 | F88: 0 | G88: 10736842 | H88: 0 | I88: =+F88-E88 -> 0
A89: 4203100 | B89: ສຳມະນາ ແລະຝຶກອົບຮົມພາຍໃນປະເທດ | C89: 5000000 | D89: 0 | E89: 0 | F89: 0 | G89: 5000000 | H89: 0 | I89: =+F89-E89 -> 0
A90: 4208300 | B90: ຄ່າໃຊ້ຈ່າຍໃນການຈັດກິດຈະກຳພະນັກງານ | C90: 0 | D90: 0 | E90: 500000 | F90: 0 | G90: 500000 | H90: 0 | I90: =+F90-E90 -> -500000
A91: 4208400 | B91: ຄ່າອາຫານຈັດປະຂູມພະນັກງານ | C91: 4087400 | D91: 0 | E91: 0 | F91: 0 | G91: 4087400 | H91: 0 | I91: =+F91-E91 -> 0
... A139: 5508400 | B139: ລາຍຮັບອື່ນໆ | C139: 0 | D139: 2000 | E139: 0 | F139: 1.2 | G139: 0 | H139: 2001.2 | I139: =+F139-E139 -> 1.2
B140: ລວມມູນຄ່າ | C140: =SUM(C80:C139) -> 6.4342647e+08 | D140: =SUM(D80:D139) -> 8.8734993e+08 | E140: =SUM(E80:E139) -> 7.9296976e+08 | F140: =SUM(F80:F139) -> 1.177315e+09 | G140: =SUM(G80:G139) -> 1.1942312e+09 | H140: =SUM(H80:H139) -> 1.8224998e+09 | I140: -5.859375e-05 | J140: 0 | K140: -3.90625e-05
A141: 1 | D141: =+D140-C140 -> 2.4392347e+08 | F141: =+F140-E140 -> 3.8434523e+08 | H141: =+H140-G140 -> 6.2826869e+08 | I141: =SUM(I80:I140) -> 3.8434523e+08

Sheet TB March'13
A1: ສາທາລະນະລັດ ປະຊາທິປະໄຕ ປະຊາຊົນລາວ | B1: ສັນຕິພາບ ເອກະລາດ ປະຊາທິປະໄຕ ເອກະພາບ ວັດທະນາຖາວອນ
D3: ໃບດູນດ່ຽງປະຈຳເດືອນ | E3: ເດືອນ 03/2013 | F3: ບໍລິສັດຫຼັກຊັບ ທຄຕລ-ກທ ຈຳກັດ_x000D_ ຊັ້ນ7, ຕຶກຕະຫຼາກຫຼັກຊັບລາວ, ຖະໜົນກຳແພງເມືອງ_x000D_ +856-21-265477+856-21-265488
C4: ໜີ້ | D4: ມີ | E4: ໜີ້ | F4: ມີ | G4: ໜີ້ | H4: ມີ | I4: Net profit
A5: 1101100 | B5: ເງິນສົດໃນຄັງ " HO " ກີບ | C5: 10000000 | D5: 0 | E5: 11551348 | F5: 11551348 | G5: 10000000 | H5: 0 | I5: =+G5-C5 -> 0 | J5: =+H5-D5 -> 0
A6: 1121110 | B6: ບັນຊີທຶນຈົດທະບຽນຂອງ ທຄຕລ-ກທ ຈຳກັດ ( ກີບ ) | C6: 2.2816035e+09 | D6: 0 | E6: 0 | F6: 0 | G6: 2.2816035e+09 | H6: 0 | I6: =+G6-C6 -> 0 | J6: =+H6-D6 -> 0
A7: 1131110 | B7: ບັນຊີກະແສລາຍວັນ ທຄຕລ: 010.0.11.00.24740 ( ກີບ ) | C7: 137607.24 | D7: 0 | E7: 0 | F7: 0 | G7: 137607.24 | H7: 0 | I7: =+G7-C7 -> 0 | J7: =+H7-D7 -> 0
A8: 1131111 | B8: ບັນຊີກະແສລາຍວັນ ທຄຕລ: 010.7.11.02.08233 ( ບາດ ) | C8: 1.3770871e+08 | D8: 0 | E8: 91415592 | F8: 1389351.2 | G8: 2.2773495e+08 | H8: 0 | I8: =+G8-C8 -> 90026240 | J8: =+H8-D8 -> 0
A9: 1131112 | B9: ບັນຊີກະແສລາຍວັນ ທຄຕລ: 010.9.11.01.19243 ( ໂດລ່າ ) | C9: 1528264.7 | D9: 0 | E9: 0 | F9: 27366.69 | G9: 1500898 | H9: 0 | I9: =+G9-C9 -> -27366.69 | J9: =+H9-D9 -> 0
A10: 1131113 | B10: ບັນຊີກະແສລາຍວັນ ທຄຕລ Proprietary AC: 010.4.19.00.00009 ( ກີບ ) | C10: 209470890 | D10: 0 | E10: 2847711383 | F10: 2886376382 | G10: 170805891 | H10: 0 | I10: =+G10-C10 -> -38664999 | J10: =+H10-D10 -> 0
A11: 1131115 | B11: ບັນຊີກະແສລາຍວັນ ທຄຕລ Aggregate AC: 010.4.19.00.00010 ( ກີບ ) | C11: 35835753400 | D11: 0 | E11: 6394665813 | F11: 11019585273 | G11: 31210833940 | H11: 0 | I11: =+G11-C11 -> -4624919460 | J11: =+H11-D11 -> 0
A12: 1131116 | B12: ບັນຊີກະແສລາຍວັນ ທຄຕລ for ETL staff IPO AC: 010.9.00.00001 ( ກີບ ) | C12: 100000 | D12: 0 | E12: 0 | F12: 0 | G12: 100000 | H12: 0 | I12: =+G12-C12 -> 0 | J12: =+H12-D12 -> 0
A13: 1131117 | B13: ບັນຊີກະແສລາຍວັນ ທຄຕລ ສຳລັບການຈອງ RO EDL-Gen :010.8.19.00.00012 LAk | C13: 0 | D13: 0 | E13: 0 | F13: 0 | G13: 0 | H13: 0 | I13: =+G13-C13 -> 0 | J13: =+H13-D13 -> 0
A14: 1131119 | B14: ບັນຊີກະແສລາຍວັນ ທຄຕລ ສຳລັບການ​ຈອງ PO EDL: 010.5.19.00.00013 Lak | C14: 3.8146973e-06 | D14: 0 | E14: 0 | F14: 0 | G14: 3.8146973e-06 | H14: 0 | I14: =+G14-C14 -> 0 | J14: =+H14-D14 -> 0
A15: 1131120 | B15: ບັນຊີກະແສລາຍວັນ ທຄຕລ ສຳລັບການ​ຈອງ PO EDL: 010.4.19.01.00006 USD | C15: 0 | D15: 1.3425946e-05 | E15: 0 | F15: 0 | G15: 0 | H15: 1.3425946e-05 | I15: =+G15-C15 -> 0 | J15: =+H15-D15 -> 0
A16: 1131121 | B16: ບັນຊີກະແສລາຍວັນ ເອຊີລີດາ 123359-1-1-101 | C16: 1000000 | D16: 0 | E16: 0 | F16: 0 | G16: 1000000 | H16: 0 | I16: =+G16-C16 -> 0 | J16: =+H16-D16 -> 0
A17: 1131130 | B17: ບັນຊີຝາກປະຢັດທີ່ ທຄຕລ: 013.2.12.00.00036 ກີບ | C17: 7.0766202e+09 | D17: 0 | E17: 2.2808393e+08 | F17: 4.8567068e+08 | G17: 6.8190335e+09 | H17: 0 | I17: =+G17-C17 -> -2.5758675e+08 | J17: =+H17-D17 -> 0 | L17: =+SUM(I5:I24) -> -4.4869567e+09 | M17: 1
A18: 1131131 | B18: ບັນຊີຝາກປະຢັດທີ່ ທຄຕລ: 013.9.12.01.00001 ( ໂດລ່າ ) | C18: 1.6945659e+08 | D18: 0 | E18: 246760.03 | F18: 70396783 | G18: 99306567 | H18: 0 | I18: =+G18-C18 -> -70150023 | J18: =+H18-D18 -> 0
A19: 1131134 | B19: ບັນຊີຝາກປະຢັດທີ່ ທສກ: 0402.0.00.220130 ( ກີບ ) | C19: 3808893026 | D19: 0 | E19: 153424658 | F19: 0 | G19: 3962317684 | H19: 0 | I19: =+G19-C19 -> 153424658 | J19: =+H19-D19 -> 0
A20: 1131137 | B20: ບັນຊີຝາກປະຍັດ ທຄຕລ-ກທ ທີ່ ເອຊີລີດາ 123359-1-0-0101 ( ກີບ ) | C20: 1.4076682e+09 | D20: 0 | E20: 2.6094098e+08 | F20: 0 | G20: 1.6686092e+09 | H20: 0 | I20: =+G20-C20 -> 2.6094098e+08 | J20: =+H20-D20 -> 0
A21: 1131153 | B21: ບັນຊີຝາກມີກຳນົດທີ່ ທສກ: 0402.0402.00.2131315.47.00000003 ( ກີບ ) | C21: 20000000000 | D21: 0 | E21: 0 | F21: 0 | G21: 20000000000 | H21: 0 | I21: =+G21-C21 -> 0 | J21: =+H21-D21 -> 0
A22: 1131154 | B22: ບັນຊີຝາກມີກຳນົດທີ່ ທສກ: 0402.0402.00.2131315.47.00000004 ( ກີບ ) | C22: 25000000000 | D22: 0 | E22: 0 | F22: 0 | G22: 25000000000 | H22: 0 | I22: =+G22-C22 -> 0 | J22: =+H22-D22 -> 0
A23: 1131159 | B23: ບັນຊີຝາກມີກຳນົດທີ່ ST Bank: 010.5.35.00.08899 ( ກີບ ) | C23: 5000000000 | D23: 0 | E23: 0 | F23: 0 | G23: 5000000000 | H23: 0 | I23: =+G23-C23 -> 0 | J23: =+H23-D23 -> 0
A24: 1131162 | B24: ບັນຊີເງິນຝາກມີກຳນົດ ທີ່ ທະນາຄານ ເອຊີລີດາ ( ກີບ ) | C24: 35000000000 | D24: 0 | E24: 0 | F24: 0 | G24: 35000000000 | H24: 0 | I24: =+G24-C24 -> 0 | J24: =+H24-D24 -> 0 | K24: =+SUM(I6:I24) -> -4.4869567e+09 | L24: =+K24+'Cash flow statement '!G20 -> 0
A25: 1137111 | B25: ດອກເບ້ຍຝາກມີກຳນົດ ຄ້າງຮັບ 1 ປີລົງມາ | C25: 6.0150114e+08 | D25: 0 | E25: 6.6170662e+08 | F25: 6.0150114e+08 | G25: 6.6170662e+08 | H25: 0 | I25: =+G25-C25 -> 60205479 | J25: =+H25-D25 -> 0
A26: 1138100 | B26: ກອງທຶນປົກປ້ອງຄວາມສ່ຽງໃນການຊຳລະສະສາງ | C26: 159699143 | D26: 0 | E26: 1161321 | F26: 0 | G26: 160860464 | H26: 0 | I26: =+G26-C26 -> 1161321 | J26: =+H26-D26 -> 0
A27: 1138810 | B27: ເງິນມັດຈຳຄ່າເຊົ່າ | C27: 11888910 | D27: 0 | E27: 0 | F27: 0 | G27: 11888910 | H27: 0 | I27: =+G27-C27 -> 0 | J27: =+H27-D27 -> 0 | L27: =-I25-I31 -> 7298891.9
A28: 1138830 | B28: ເງິນມັດຈຳອື່ນໆ | C28: 0 | D28: 0 | E28: 900898 | F28: 0 | G28: 900898 | H28: 0 | I28: =+G28-C28 -> 900898 | J28: =+H28-D28 -> 0
A29: 1201181 | B29: ລູກໜີ້ຊື້ຫຼັກຊັບຕາມຄຳສັ່ງຊື້-ບັນຊີເງິນສົດ | C29: 90243338 | D29: 0 | E29: 710154036 | F29: 800397374 | G29: 0 | H29: 0 | I29: =+G29-C29 -> -90243338 | J29: =+H29-D29 -> 0
A30: 1211110 | B30: ລູກໜີ້ບັນຊີຊື້-ຂາຍຫຼັກຊັບລະຫວ່າງບ/ສ ກັບ LSX | C30: 0 | D30: 0 | E30: 2606828749 | F30: 1847314009 | G30: 759514740 | H30: 0 | I30: =+G30-C30 -> 759514740 | J30: =+H30-D30 -> 0
A31: 1301720 | B31: ຄ່າທີ່ປຶກສາຄ້າງຮັບ | C31: 2.9469592e+08 | D31: 0 | E31: 69312147 | F31: 1.3681652e+08 | G31: 2.2719155e+08 | H31: 0 | I31: =+G31-C31 -> -67504371 | J31: =+H31-D31 -> 0
A32: 1302216 | B32: ເງິນລົງທືນຊົ່ວຄາວຫຼັກຊັບ-ເພື່ອຄ້າ-Port Trading | C32: 9.7325447e+08 | D32: 0 | E32: 278684380 | F32: 0 | G32: 1.2519388e+09 | H32: 0 | I32: =+G32-C32 -> 278684380 | J32: =+H32-D32 -> 0
A33: 1302218 | B33: ຄ່າປັບມູນຄ່າເງິນລົງທືນຊົ່ວຄາວຫຼັກຊັບ-ເພື່ອຄ້າ-Port trading | C33: 1.2994373e+08 | D33: 0 | E33: 1.1275875e+08 | F33: 1.2994373e+08 | G33: 1.1275875e+08 | H33: 0 | I33: =+G33-C33 -> -17184980 | J33: =+H33-D33 -> 0
A34: 1360000 | B34: ລູກໜີ້ອື່ນໆ | C34: 17950347 | D34: 0 | E34: 913950 | F34: 2895714 | G34: 15968583 | H34: 0 | I34: =+G34-C34 -> -1981764 | J34: =+H34-D34 -> 0
A35: 1361100 | B35: ອາກອນກຳໄລມອບລ່ວງໜ້າ | C35: 0 | D35: 0 | E35: 0 | F35: 0 | G35: 0 | H35: 0 | I35: =+G35-C35 -> 0 | J35: =+H35-D35 -> 0
A36: 1361300 | B36: ອາກອນອື່ນໆທີ່ຕ້ອງຮັບຄືນ | C36: 0 | D36: 0 | E36: 372200 | F36: 0 | G36: 372200 | H36: 0 | I36: =+G36-C36 -> 372200 | J36: =+H36-D36 -> 0
A37: 1362100 | B37: ເງິນຈ່າຍລ່ວງໜ້າເພື່ອເຄື່ອນໄຫວວຽກງານ | C37: 1955000 | D37: 0 | E37: 10000000 | F37: 7955000 | G37: 4000000 | H37: 0 | I37: =+G37-C37 -> 2045000 | J37: =+H37-D37 -> 0
A38: 1388110 | B38: ຄ່າເຊົ່າຈ່າຍລ່ວງໜ້າ | C38: 3.4188912e+08 | D38: 0 | E38: 51041361 | F38: 52260410 | G38: 3.4067007e+08 | H38: 0 | I38: =+G38-C38 -> -1219048.5 | J38: =+H38-D38 -> 0
A39: 1388120 | B39: ຄ່າປະກັນໄພຈ່າຍລ່ວງໜ້າ | C39: 1.1851435e+08 | D39: 0 | E39: 0 | F39: 12019417 | G39: 1.0649493e+08 | H39: 0 | I39: =+G39-C39 -> -12019417 | J39: =+H39-D39 -> 0
A40: 1388170 | B40: ຄ່າໜັງສືພີມ ຈ່າຍລ່ວງໜ້າອື່ນໆ | C40: 4642871 | D40: 0 | E40: 0 | F40: 448438.36 | G40: 4194432.6 | H40: 0 | I40: =+G40-C40 -> -448438.36 | J40: =+H40-D40 -> 0
A41: 1388180 | B41: ລາຍຈ່າຍ ຈ່າຍລ່ວງໜ້າອື່ນໆ | C41: 3988600 | D41: 0 | E41: 0 | F41: 846894.52 | G41: 3141705.5 | H41: 0 | I41: =+G41-C41 -> -846894.52 | J41: =+H41-D41 -> 0 | L41: =+SUM(I6:I41) -> -3.575521e+09
A42: 1441810 | B42: ຊັອບແວຄອມພີວເຕີ່ | C42: 3.0087805e+08 | D42: 0 | E42: 0 | F42: 0 | G42: 3.0087805e+08 | H42: 0 | I42: =+G42-C42 -> 0 | J42: =+H42-D42 -> 0
A43: 1442400 | B43: ພາຫະນະຂົນສົ່ງ | C43: 629368000 | D43: 0 | E43: 0 | F43: 0 | G43: 629368000 | H43: 0 | I43: =+G43-C43 -> 0 | J43: =+H43-D43 -> 0
A44: 1442510 | B44: ຄ່າຕົບແຕ່ງສຳນັກງານ | C44: 1.5525121e+09 | D44: 0 | E44: 0 | F44: 0 | G44: 1.5525121e+09 | H44: 0 | I44: =+G44-C44 -> 0 | J44: =+H44-D44 -> 0
A45: 1442610 | B45: ອຸປະກອນຄອມພີວເຕີ່ | C45: 6.4974202e+08 | D45: 0 | E45: 3722000 | F45: 3786644.9 | G45: 6.4967738e+08 | H45: 0 | I45: =+G45-C45 -> -64644.92 | J45: =+H45-D45 -> 0
A46: 1442710 | B46: ອຸປະກອນສຳນັກງານ | C46: 1.3821519e+08 | D46: 0 | E46: 0 | F46: 0 | G46: 1.3821519e+08 | H46: 0 | I46: =+G46-C46 -> 0 | J46: =+H46-D46 -> 0
A47: 1442720 | B47: ອຸປະກອນເຟີນີເຈີ່ | C47: 3.8108966e+08 | D47: 0 | E47: 0 | F47: 0 | G47: 3.8108966e+08 | H47: 0 | I47: =+G47-C47 -> 0 | J47: =+H47-D47 -> 0
A48: 1481181 | B48: ຄ່າຕັດຈຳໜ່າຍຄອມພີວເຕີ່ຊ້ອບແວສະສົມ | C48: 0 | D48: 62262985 | E48: 0 | F48: 5108006.3 | G48: 0 | H48: 67370991 | I48: =+G48-C48 -> 0 | J48: =+H48-D48 -> 5108006.3 | L48: =+SUM(J48:J53) -> 37983112
A49: 1481240 | B49: ຄ່າຫຼຸ່ຍຫ້ຽນສະສົມພາຫະນະ | C49: 0 | D49: 2.6454829e+08 | E49: 0 | F49: 10674717 | G49: 0 | H49: 2.7522301e+08 | I49: =+G49-C49 -> 0 | J49: =+H49-D49 -> 10674717 | L49: =+SUM(F48:F53) -> 38817563
A50: 1481251 | B50: ຄ່າຫຼຸ່ຍຫ້ຽນສະສົມ ຄ່າຕົບແຕ່ງສຳນັກງານ | C50: 0 | D50: 3.3144478e+08 | E50: 0 | F50: 13133827 | G50: 0 | H50: 3.4457861e+08 | I50: =+G50-C50 -> 0 | J50: =+H50-D50 -> 13133827 | L50: =+L49-J136 -> 0
A51: 1481261 | B51: ຄ່າຫຼຸ່ຍຫ້ຽນສະສົມ ອຸປະກອນຄອມພີວເຕີ່ | C51: 0 | D51: 1.2324706e+08 | E51: 834450.85 | F51: 5494017.7 | G51: 0 | H51: 1.2790663e+08 | I51: =+G51-C51 -> 0 | J51: =+H51-D51 -> 4659566.8
A52: 1481271 | B52: ຄ່າຫຼຸ່ຍຫ້ຽນສະສົມ ອຸປະກອນສຳນັກງານ | C52: 0 | D52: 22452543 | E52: 0 | F52: 1172980.6 | G52: 0 | H52: 23625523 | I52: =+G52-C52 -> 0 | J52: =+H52-D52 -> 1172980.6
A53: 1481272 | B53: ຄ່າຫຼຸ່ຍຫ້ຽນສະສົມ ເຟີນີເຈີ່ | C53: 0 | D53: 79558545 | E53: 0 | F53: 3234013.6 | G53: 0 | H53: 82792559 | I53: =+G53-C53 -> 0 | J53: =+H53-D53 -> 3234013.6
A54: 2211110 | B54: ເຈົ້າໜີ້ຕະຫຼາດຫຼັກຊັບ LSX | C54: 0 | D54: 85190134 | E54: 931276843 | F54: 846086709 | G54: 0 | H54: 0 | I54: =+G54-C54 -> 0 | J54: =+H54-D54 -> -85190134
A55: 2344100 | B55: ເຈົ້າໜີ້ບັນຊີຊື້-ຂາຍຫຼັກຊັບຕາມຄຳສັ່ງຊື້-ບັນຊີເງິນສົດ | C55: 0 | D55: 0 | E55: 1955099539 | F55: 2711065178 | G55: 0 | H55: 755965639 | I55: =+G55-C55 -> 0 | J55: =+H55-D55 -> 755965639
A56: 2344200 | B56: ບັນຊີເງິນລູກຄ້າ- Cash Balance | C56: 0 | D56: 35835753400 | E56: 11019585273 | F56: 6394665813 | G56: 0 | H56: 31210833940 | I56: =+G56-C56 -> 0 | J56: =+H56-D56 -> -4624919460
A57: 2344600 | B57: ບັນຊີເຈົ້າໜີ້ຄ່າຈອງຊື້ຮຸ້ນ | C57: 0 | D57: 0 | E57: 0 | F57: 0 | G57: 0 | H57: 0 | I57: =+G57-C57 -> 0 | J57: =+H57-D57 -> 0
A58: 2344700 | B58: ເຈົ້າໜີ້ລໍຖ້າຖອນເງີນຄືນ | C58: 1.3425946e-05 | D58: 0 | E58: 0 | F58: 0 | G58: 1.3425946e-05 | H58: 0 | I58: =+G58-C58 -> 0 | J58: =+H58-D58 -> 0
A59: 2361110 | B59: ອາກອນກຳໄລທີ່ຕ້ອງມອບເພີ່ມ | C59: 0 | D59: 0 | E59: 0 | F59: 2.1782006e+08 | G59: 0 | H59: 2.1782006e+08 | I59: =+G59-C59 -> 0 | J59: =+H59-D59 -> 2.1782006e+08
A60: 2361120 | B60: ອາກອນມູນຄ່າເພີ່ມທີ່ຕ້ອງມອບ | C60: 0 | D60: 8423360 | E60: 12588800 | F60: 6281040 | G60: 0 | H60: 2115600 | I60: =+G60-C60 -> 0 | J60: =+H60-D60 -> -6307760
A61: 2361130 | B61: ພາສີ ແລະອາກອນຕ່າງໆ ທີ່ຫັກໄວ້ຕ້ອງສົ່ງມອບ | C61: 0 | D61: 0 | E61: 0 | F61: 0 | G61: 0 | H61: 0 | I61: =+G61-C61 -> 0 | J61: =+H61-D61 -> 0
A62: 2361140 | B62: ອາກອນເງິນເດືອນຕ້ອງສົ່ງມອບ | C62: 0 | D62: 12550600 | E62: 21223017 | F62: 30204688 | G62: 0 | H62: 21532271 | I62: =+G62-C62 -> 0 | J62: =+H62-D62 -> 8981671
... A70: 2363683 | B70: ບັນຊີເຈົ້າໜີ້ BCEL | C70: 0 | D70: 0 | E70: 0 | F70: 0 | G70: 0 | H70: 0 | I70: =+G70-C70 -> 0 | J70: =+H70-D70 -> 0
A71: 2363684 | B71: ບັນຊີເຈົ້າໜີ້ອື່ນໆ | C71: 0 | D71: 0 | E71: 0 | F71: 0 | G71: 0 | H71: 0 | I71: =+G71-C71 -> 0 | J71: =+H71-D71 -> 0 | L71: =+SUM(J54:J71) -> -3.6501023e+09
A72: 3108210 | B72: ທຶນຈົດທະບຽນທີ່ຖອກແລ້ວ | C72: 0 | D72: 100000000000 | E72: 0 | F72: 0 | G72: 0 | H72: 100000000000 | I72: =+G72-C72 -> 0 | J72: =+H72-D72 -> 0 | L72: =+L71-'Cash flow statement '!G36 -> 0 | N72: Diff for check
A73: 3810000 | B73: ກຳໄລ-ຂາດທຶນສະສົມ | C73: 0 | D73: 1.9182372e+08 | E73: 0 | F73: 0 | G73: 0 | H73: 1.9182372e+08 | I73: =+G73-C73 -> 0 | J73: =+H73-D73 -> 0
A74: 3901000 | B74: ກຳໄລ-ຂາດ ທຶນໃນປີ | C74: 0 | D74: 0 | E74: 0 | F74: 0 | G74: 0 | H74: 0 | I74: =+G74-C74 -> 0 | J74: =+H74-D74 -> 0
A75: 3908000 | B75: ຜົນໄດ້ຮັບ ລໍຖ້າຮັບຮອງ | C75: 0 | D75: 3.7642156e+09 | E75: 0 | F75: 35663705 | G75: 0 | H75: 3.7998793e+09 | I75: =+G75-C75 -> 0 | J75: =+H75-D75 -> 35663705
B76: Total | C76: =SUM(C5:C75) -> 1.4234191e+11 | D76: =SUM(D5:D75) -> 1.4171364e+11 | E76: =SUM(E5:E75) -> 2.8510511e+10 | F76: =SUM(F5:F75) -> 2.8509641e+10 | G76: =SUM(G5:G75) -> 1.3876633e+11 | H76: =SUM(H5:H75) -> 1.3813719e+11 | I76: =SUM(I5:I75) -> -3.5755856e+09 | J76: =SUM(J5:J75) -> -3.5764555e+09
B77: Net profit | D77: =+C76-D76 -> 6.2826869e+08 | F77: =+E76-F76 -> 869899.41 | H77: =+G76-H76 -> 6.2913859e+08 | J77: =+I76-J76 -> 869899.41 | K77: =+J77-F77 -> 4.2915344e-06
C80: ໜີ້ | D80: ມີ | E80: ໜີ້ | F80: ມີ | G80: ໜີ້ | H80: ມີ | I80: Net profit
A81: 4102730 | B81: ຄ່າບໍລິການເຊົ່າລະບົບເທີມີນໍ່ LSX | C81: 42193671 | D81: 0 | E81: 20658710 | F81: 0 | G81: 62852380 | H81: 0 | I81: =+F81-E81 -> -20658710
A82: 4102731 | B82: ຄ່າບໍລິການເຊົ່າລະບົບດິດສເປຣເຢີ່ LSX | C82: 5117256 | D82: 0 | E82: 2505492 | F82: 0 | G82: 7622748 | H82: 0 | I82: =+F82-E82 -> -2505492
A83: 4108210 | B83: ຄ່າທຳນຽມທະນາຄານ ( ຈ່າຍ ) | C83: 595999.21 | D83: 0 | E83: 215998.21 | F83: 0 | G83: 811997.42 | H83: 0 | I83: =+F83-E83 -> -215998.21
A84: 4201100 | B84: ເງິນເດືອນພະນັກງານໃນການຈັດຕັ້ງ | C84: 315609677 | D84: 0 | E84: 156450000 | F84: 0 | G84: 472059677 | H84: 0 | I84: =+F84-E84 -> -156450000
A85: 4201400 | B85: ເງິນເພີ່ມໂມງ | C85: 49802667 | D85: 0 | E85: 1020750 | F85: 0 | G85: 50823417 | H85: 0 | I85: =+F85-E85 -> -1020750
A86: 4202200 | B86: ລາຍຈ່າຍຄ່າປະກັນໄພພະນັກງານ | C86: 19927800 | D86: 0 | E86: 10170857 | F86: 0 | G86: 30098656 | H86: 0 | I86: =+F86-E86 -> -10170857
A87: 4202210 | B87: ລາຍຈ່າຍຄ່າຮັກສາພະຍາບານ | C87: 0 | D87: 0 | E87: 500000 | F87: 0 | G87: 500000 | H87: 0 | I87: =+F87-E87 -> -500000
A88: 4202220 | B88: ລາຍຈ່າຍຄ່ານ້ຳມັນລົດພະນັກງານ | C88: 34083871 | D88: 0 | E88: 16800000 | F88: 0 | G88: 50883871 | H88: 0 | I88: =+F88-E88 -> -16800000
A89: 4202800 | B89: ລາຍຈ່າຍສະຫວັດດີການພະນັກງານອື່ນໆ | C89: 14000000 | D89: 0 | E89: 6800000 | F89: 0 | G89: 20800000 | H89: 0 | I89: =+F89-E89 -> -6800000
A90: 4202811 | B90: ລາຍຈ່າຍເບ້ຍປະຊູມສະພາບໍລິຫານ | C90: 10736842 | D90: 0 | E90: 0 | F90: 0 | G90: 10736842 | H90: 0 | I90: =+F90-E90 -> 0
A91: 4203100 | B91: ສຳມະນາ ແລະຝຶກອົບຮົມພາຍໃນປະເທດ | C91: 5000000 | D91: 0 | E91: 11506000 | F91: 0 | G91: 16506000 | H91: 0 | I91: =+F91-E91 -> -11506000
A92: 4208300 | B92: ຄ່າໃຊ້ຈ່າຍໃນການຈັດກິດຈະກຳພະນັກງານ | C92: 500000 | D92: 0 | E92: 300000 | F92: 0 | G92: 800000 | H92: 0 | I92: =+F92-E92 -> -300000
... A135: 4506100 | B135: ຂາດທຶນ ( ກຳໄລ ) ສະສາງຊັບສົມບັດຄົງທີ່ | C135: 0 | D135: 0 | E135: 2952194.1 | F135: 0 | G135: 2952194.1 | H135: 0 | I135: =+F135-E135 -> -2952194.1
A136: 4601124 | B136: ຄ່າຫຼຸ້ຍຫ້ຽນພາຫະນະຂົ່ນສົ່ງ | C136: 20338978 | D136: 0 | E136: 10674717 | F136: 0 | G136: 31013695 | H136: 0 | I136: =+F136-E136 -> -10674717 | J136: =+SUM(E136:E141) -> 38817563
A137: 4601125 | B137: ຄ່າຫຼຸ້ຍຫ້ຽນຄ່າຕົບແຕ່ງໃນຫ້ອງການ | C137: 24996639 | D137: 0 | E137: 13133827 | F137: 0 | G137: 38130467 | H137: 0 | I137: =+F137-E137 -> -13133827 | J137: =+J136-L48 -> 834450.85
A138: 4601126 | B138: ຄ່າຫຼຸ້ຍຫ້ຽນເຄື່ອງຈັກຮັບໃຊ້ຫ້ອງການ | C138: 10494238 | D138: 0 | E138: 5494017.7 | F138: 0 | G138: 15988256 | H138: 0 | I138: =+F138-E138 -> -5494017.7
A139: 4601127 | B139: ຄ່າຫຼຸ້ຍຫ້ຽນເຄື່ງໃຊ້ສຳນັກງານ | C139: 2206038.5 | D139: 0 | E139: 1172980.6 | F139: 0 | G139: 3379019 | H139: 0 | I139: =+F139-E139 -> -1172980.6
A140: 4601128 | B140: ຄ່າຫຼຸ່ຍຫ້ຽນເຟີນີເຈີ່ສຳນັກງານ | C140: 6155058.1 | D140: 0 | E140: 3234013.6 | F140: 0 | G140: 9389071.7 | H140: 0 | I140: =+F140-E140 -> -3234013.6
A141: 4602110 | B141: ຄ່າຕັດຈຳໜ່າຍ ແລະຄ່າເສື່ອມSoftware computer | C141: 10492400 | D141: 0 | E141: 5108006.3 | F141: 0 | G141: 15600406 | H141: 0 | I141: =+F141-E141 -> -5108006.3
A142: 4900000 | B142: ອາກອນກຳໄລບໍລິສັດ | C142: 0 | D142: 0 | E142: 2.1182937e+08 | F142: 0 | G142: 2.1182937e+08 | H142: 0 | I142: =+F142-E142 -> -2.1182937e+08
A143: 5101311 | B143: ດອກເບ້ຍເງິນຝາກຢູ່ທະນາຄານພາຍໃນປະເທດ | C143: 0 | D143: 1.2715829e+09 | E143: 0 | F143: 6.9804601e+08 | G143: 0 | H143: 1.9696289e+09 | I143: =+F143-E143 -> 6.9804601e+08
A144: 5103220 | B144: ກຳໄລ ( ຂາດທຶນ ) ຈາກການຊື້-ຂາຍຫຼັກຊັບ - Port- Trading | C144: 0 | D144: 0 | E144: 0 | F144: 0 | G144: 0 | H144: 0 | I144: =+F144-E144 -> 0
A145: 5103240 | B145: ກຳໄລ ( ຂາດທຶນ ) ທີ່ຍັງບໍ່ເກີດຈາກການຊື້-ຂາຍຫຼັກຊັບ - Port - Trading | C145: 0 | D145: 89243473 | E145: 1.2994373e+08 | F145: 1.1275875e+08 | G145: 0 | H145: 72058493 | I145: =+F145-E145 -> -17184980
A146: 5106100 | B146: ກຳໄລ ( ຂາດທຶນ ) ຈາກອັດຕາແລກປ່ຽນ | C146: 960573.08 | D146: 0 | E146: 2472747.3 | F146: 736983.77 | G146: 2696336.6 | H146: 0 | I146: =+F146-E146 -> -1735763.5
A147: 5108210 | B147: ຄ່ານາຍໜ້າຈາກການຊື້-ຂາຍຫຼັກຊັບ | C147: 0 | D147: 377437849 | E147: 0 | F147: 102025339 | G147: 0 | H147: 479463188 | I147: =+F147-E147 -> 102025339
A148: 5108310 | B148: ຄ່າບໍລິການທີ່ປຶກສາທາງດ້ານການເງິນ | C148: 0 | D148: 84233600 | E148: 41654400 | F148: 21156000 | G148: 0 | H148: 63735200 | I148: =+F148-E148 -> -20498400
A149: 5508400 | B149: ລາຍຮັບອື່ນໆ | C149: 0 | D149: 2001.2 | E149: 0 | F149: 0 | G149: 0 | H149: 2001.2 | I149: =+F149-E149 -> 0
A150: ລວມມູນຄ່າ | C150: =SUM(C81:C149) -> 1.1942312e+09 | D150: =SUM(D81:D149) -> 1.8224998e+09 | E150: =SUM(E81:E149) -> 9.5573022e+08 | F150: =SUM(F81:F149) -> 9.5660012e+08 | G150: =SUM(G81:G149) -> 1.9557492e+09 | H150: =SUM(H81:H149) -> 2.5848878e+09 | I150: -3.90625e-05 | J150: 0 | K150: -3.90625e-05 | L150: ນະຄອນຫຼວງວຽງຈັນ ວັນທີ : ......../......../............ , | M150: ຜູ້ອຳນວຍການ | N150: ທີ່ປຶກສາບັນຊີ | O150: ພະນັກງານບັນຊີ | P150: ຜູ້ສັງລວມ | Q150: ............…………………...... | R150: ...…………………………..
A151: 1 | D151: =+D150-C150 -> 6.2826869e+08 | F151: =+F150-E150 -> 869899.41 | H151: =+H150-G150 -> 6.2913859e+08 | I151: =SUM(I81:I150) -> 869899.41 | J151: =+I151-F151 -> -3.8987957e-05

Sheet TB June'13
A1: ສາທາລະນະລັດ ປະຊາທິປະໄຕ ປະຊາຊົນລາວ | B1: ສັນຕິພາບ ເອກະລາດ ປະຊາທິປະໄຕ ເອກະພາບ ວັດທະນາຖາວອນ
D3: ໃບດູນດ່ຽງປະຈຳເດືອນ | E3: ເດືອນ 06/2013 | F3: ບໍລິສັດຫຼັກຊັບ ທຄຕລ-ກທ ຈຳກັດ_x000D_ ຊັ້ນ7, ຕຶກຕະຫຼາກຫຼັກຊັບລາວ, ຖະໜົນກຳແພງເມືອງ_x000D_ +856-21-265477+856-21-265488
C4: ໜີ້ | D4: ມີ | E4: ໜີ້ | F4: ມີ | G4: ໜີ້ | H4: ມີ
A5: 1101100 | B5: ເງິນສົດໃນຄັງ " HO " ກີບ | C5: 10000000 | D5: 0 | E5: 15990718 | F5: 15990718 | G5: 10000000 | H5: 0 | I5: =+G5-C5 -> 0 | J5: =+H5-D5 -> 0
A6: 1121110 | B6: ບັນຊີທຶນຈົດທະບຽນຂອງ ທຄຕລ-ກທ ຈຳກັດ ( ກີບ ) | C6: 2.2816035e+09 | D6: 0 | E6: 0 | F6: 0 | G6: 2.2816035e+09 | H6: 0 | I6: =+G6-C6 -> 0 | J6: =+H6-D6 -> 0
A7: 1131110 | B7: ບັນຊີກະແສລາຍວັນ ທຄຕລ: 010.0.11.00.24740 ( ກີບ ) | C7: 137607.24 | D7: 0 | E7: 0 | F7: 20000 | G7: 117607.24 | H7: 0 | I7: =+G7-C7 -> -20000 | J7: =+H7-D7 -> 0
A8: 1131111 | B8: ບັນຊີກະແສລາຍວັນ ທຄຕລ: 010.7.11.02.08233 ( ບາດ ) | C8: 2.6401201e+08 | D8: 0 | E8: 0 | F8: 2.5585843e+08 | G8: 8153586.4 | H8: 0 | I8: =+G8-C8 -> -2.5585843e+08 | J8: =+H8-D8 -> 0
A9: 1131112 | B9: ບັນຊີກະແສລາຍວັນ ທຄຕລ: 010.9.11.01.19243 ( ໂດລ່າ ) | C9: 1488864.4 | D9: 0 | E9: 15333.11 | F9: 15500 | G9: 1488697.5 | H9: 0 | I9: =+G9-C9 -> -166.89 | J9: =+H9-D9 -> 0
A10: 1131113 | B10: ບັນຊີກະແສລາຍວັນ ທຄຕລ Proprietary AC: 010.4.19.00.00009 ( ກີບ ) | C10: 129974887 | D10: 0 | E10: 237694712 | F10: 300288018 | G10: 67381581 | H10: 0 | I10: =+G10-C10 -> -62593306 | J10: =+H10-D10 -> 0
A11: 1131115 | B11: ບັນຊີກະແສລາຍວັນ ທຄຕລ Aggregate AC: 010.4.19.00.00010 ( ກີບ ) | C11: 37956098685 | D11: 0 | E11: 2998047564 | F11: 6396092184 | G11: 34558054065 | H11: 0 | I11: =+G11-C11 -> -3398044620 | J11: =+H11-D11 -> 0
A12: 1131116 | B12: ບັນຊີກະແສລາຍວັນ ທຄຕລ for ETL staff IPO AC: 010.9.00.00001 ( ກີບ ) | C12: 100000 | D12: 0 | E12: 0 | F12: 0 | G12: 100000 | H12: 0 | I12: =+G12-C12 -> 0 | J12: =+H12-D12 -> 0
A13: 1131117 | B13: ບັນຊີກະແສລາຍວັນ ທຄຕລ ສຳລັບການຈອງ RO EDL-Gen :010.8.19.00.00012 LAk | C13: 0 | D13: 0 | E13: 0 | F13: 0 | G13: 0 | H13: 0 | I13: =+G13-C13 -> 0 | J13: =+H13-D13 -> 0
A14: 1131119 | B14: ບັນຊີກະແສລາຍວັນ ທຄຕລ ສຳລັບການ​ຈອງ PO EDL: 010.5.19.00.00013 Lak | C14: 3.8146973e-06 | D14: 0 | E14: 0 | F14: 0 | G14: 3.8146973e-06 | H14: 0 | I14: =+G14-C14 -> 0 | J14: =+H14-D14 -> 0
A15: 1131120 | B15: ບັນຊີກະແສລາຍວັນ ທຄຕລ ສຳລັບການ​ຈອງ PO EDL: 010.4.19.01.00006 USD | C15: 0 | D15: 1.3425946e-05 | E15: 0 | F15: 0 | G15: 0 | H15: 1.3425946e-05 | I15: =+G15-C15 -> 0 | J15: =+H15-D15 -> 0
A16: 1131121 | B16: ບັນຊີກະແສລາຍວັນ ເອຊີລີດາ 123359-1-1-101 | C16: 1000000 | D16: 0 | E16: 0 | F16: 0 | G16: 1000000 | H16: 0 | I16: =+G16-C16 -> 0 | J16: =+H16-D16 -> 0
... A28: 1138810 | B28: ເງິນມັດຈຳຄ່າເຊົ່າ | C28: 11888910 | D28: 0 | E28: 0 | F28: 0 | G28: 11888910 | H28: 0 | I28: =+G28-C28 -> 0 | J28: =+H28-D28 -> 0
A29: 1138830 | B29: ເງິນມັດຈຳອື່ນໆ | C29: 0 | D29: 0 | E29: 0 | F29: 0 | G29: 0 | H29: 0 | I29: =+G29-C29 -> 0 | J29: =+H29-D29 -> 0 | L29: =+SUM(I27:I29)+SUM(I35:I42) -> 2.5312468e+08
A30: 1201181 | B30: ລູກໜີ້ຊື້ຫຼັກຊັບຕາມຄຳສັ່ງຊື້-ບັນຊີເງິນສົດ | C30: 0 | D30: 0 | E30: 79527050 | F30: 69761435 | G30: 9765615 | H30: 0 | I30: =+G30-C30 -> 9765615 | J30: =+H30-D30 -> 0
A31: 1211110 | B31: ລູກໜີ້ບັນຊີຊື້-ຂາຍຫຼັກຊັບລະຫວ່າງບ/ສ ກັບ LSX | C31: 74092454 | D31: 0 | E31: 157466113 | F31: 167933277 | G31: 63625290 | H31: 0 | I31: =+G31-C31 -> -10467164 | J31: =+H31-D31 -> 0
A32: 1301720 | B32: ຄ່າທີ່ປຶກສາຄ້າງຮັບ | C32: 1.1920929e-07 | D32: 0 | E32: 0 | F32: 0 | G32: 1.1920929e-07 | H32: 0 | I32: =+G32-C32 -> 0 | J32: =+H32-D32 -> 0
A33: 1302216 | B33: ເງິນລົງທືນຊົ່ວຄາວຫຼັກຊັບ-ເພື່ອຄ້າ-Port Trading | C33: 1.4593232e+09 | D33: 0 | E33: 2.0306113e+08 | F33: 0 | G33: 1.6623843e+09 | H33: 0 | I33: =+G33-C33 -> 2.0306113e+08 | J33: =+H33-D33 -> 0
A34: 1302218 | B34: ຄ່າປັບມູນຄ່າເງິນລົງທືນຊົ່ວຄາວຫຼັກຊັບ-ເພື່ອຄ້າ-Port trading | C34: 32840178 | D34: 0 | E34: 27401751 | F34: 32840178 | G34: 27401751 | H34: 0 | I34: =+G34-C34 -> -5438427.2 | J34: =+H34-D34 -> 0
A35: 1360000 | B35: ລູກໜີ້ອື່ນໆ | C35: 15444583 | D35: 0 | E35: 1662732 | F35: 2246732 | G35: 14860583 | H35: 0 | I35: =+G35-C35 -> -584000 | J35: =+H35-D35 -> 0
A36: 1361100 | B36: ອາກອນກຳໄລມອບລ່ວງໜ້າ | C36: 5862058 | D36: 0 | E36: 427322763 | F36: 120995945 | G36: 312188876 | H36: 0 | I36: =+G36-C36 -> 306326818 | J36: =+H36-D36 -> 0
A37: 1361300 | B37: ອາກອນອື່ນໆທີ່ຕ້ອງຮັບຄືນ | C37: 0 | D37: 0 | E37: 0 | F37: 0 | G37: 0 | H37: 0 | I37: =+G37-C37 -> 0 | J37: =+H37-D37 -> 0
A38: 1362100 | B38: ເງິນຈ່າຍລ່ວງໜ້າເພື່ອເຄື່ອນໄຫວວຽກງານ | C38: 7000000 | D38: 0 | E38: 12000000 | F38: 12000000 | G38: 7000000 | H38: 0 | I38: =+G38-C38 -> 0 | J38: =+H38-D38 -> 0
A39: 1388110 | B39: ຄ່າເຊົ່າຈ່າຍລ່ວງໜ້າ | C39: 2.3982322e+08 | D39: 0 | E39: 0 | F39: 40644464 | G39: 1.9917876e+08 | H39: 0 | I39: =+G39-C39 -> -40644464 | J39: =+H39-D39 -> 0
A40: 1388120 | B40: ຄ່າປະກັນໄພຈ່າຍລ່ວງໜ້າ | C40: 82843824 | D40: 0 | E40: 0 | F40: 11631694 | G40: 71212131 | H40: 0 | I40: =+G40-C40 -> -11631694 | J40: =+H40-D40 -> 0
A41: 1388170 | B41: ຄ່າໜັງສືພີມ ຈ່າຍລ່ວງໜ້າອື່ນໆ | C41: 3312021.7 | D41: 0 | E41: 0 | F41: 433972.6 | G41: 2878049.1 | H41: 0 | I41: =+G41-C41 -> -433972.6 | J41: =+H41-D41 -> 0
A42: 1388180 | B42: ລາຍຈ່າຍ ຈ່າຍລ່ວງໜ້າອື່ນໆ | C42: 1475235.6 | D42: 0 | E42: 0 | F42: 819575.34 | G42: 655660.29 | H42: 0 | I42: =+G42-C42 -> -819575.34 | J42: =+H42-D42 -> 0 | L42: =-SUM(I27:I29)-SUM(I35:I42) -> -2.5312468e+08
A43: 1441810 | B43: ຊັອບແວຄອມພີວເຕີ່ | C43: 3.0087805e+08 | D43: 0 | E43: 0 | F43: 0 | G43: 3.0087805e+08 | H43: 0 | I43: =+G43-C43 -> 0 | J43: =+H43-D43 -> 0
A44: 1442400 | B44: ພາຫະນະຂົນສົ່ງ | C44: 629368000 | D44: 0 | E44: 0 | F44: 0 | G44: 629368000 | H44: 0 | I44: =+G44-C44 -> 0 | J44: =+H44-D44 -> 0
A45: 1442510 | B45: ຄ່າຕົບແຕ່ງສຳນັກງານ | C45: 1.5525121e+09 | D45: 0 | E45: 0 | F45: 0 | G45: 1.5525121e+09 | H45: 0 | I45: =+G45-C45 -> 0 | J45: =+H45-D45 -> 0
A46: 1442610 | B46: ອຸປະກອນຄອມພີວເຕີ່ | C46: 6.4967738e+08 | D46: 0 | E46: 4174500 | F46: 0 | G46: 6.5385188e+08 | H46: 0 | I46: =+G46-C46 -> 4174500 | J46: =+H46-D46 -> 0
A47: 1442710 | B47: ອຸປະກອນສຳນັກງານ | C47: 1.4222659e+08 | D47: 0 | E47: 0 | F47: 980000 | G47: 1.4124659e+08 | H47: 0 | I47: =+G47-C47 -> -980000 | J47: =+H47-D47 -> 0 | L47: =+SUM(I6:I48) -> -2.8455956e+09
A48: 1442720 | B48: ອຸປະກອນເຟີນີເຈີ່ | C48: 3.8108966e+08 | D48: 0 | E48: 0 | F48: 0 | G48: 3.8108966e+08 | H48: 0 | I48: =+G48-C48 -> 0 | J48: =+H48-D48 -> 0
A49: 1481181 | B49: ຄ່າຕັດຈຳໜ່າຍຄອມພີວເຕີ່ຊ້ອບແວສະສົມ | C49: 0 | D49: 77422229 | E49: 0 | F49: 4943231.9 | G49: 0 | H49: 82365461 | I49: =+G49-C49 -> 0 | J49: =+H49-D49 -> 4943231.9
A50: 1481240 | B50: ຄ່າຫຼຸ່ຍຫ້ຽນສະສົມພາຫະນະ | C50: 0 | D50: 2.9623562e+08 | E50: 0 | F50: 10337898 | G50: 0 | H50: 3.0657352e+08 | I50: =+G50-C50 -> 0 | J50: =+H50-D50 -> 10337898
A51: 1481251 | B51: ຄ່າຫຼຸ່ຍຫ້ຽນສະສົມ ຄ່າຕົບແຕ່ງສຳນັກງານ | C51: 0 | D51: 3.7056837e+08 | E51: 0 | F51: 12749915 | G51: 0 | H51: 3.8331829e+08 | I51: =+G51-C51 -> 0 | J51: =+H51-D51 -> 12749915
A52: 1481261 | B52: ຄ່າຫຼຸ່ຍຫ້ຽນສະສົມ ອຸປະກອນຄອມພີວເຕີ່ | C52: 0 | D52: 1.3855418e+08 | E52: 0 | F52: 5371098.3 | G52: 0 | H52: 1.4392528e+08 | I52: =+G52-C52 -> 0 | J52: =+H52-D52 -> 5371098.3
A53: 1481271 | B53: ຄ່າຫຼຸ່ຍຫ້ຽນສະສົມ ອຸປະກອນສຳນັກງານ | C53: 0 | D53: 25848578 | E53: 37568.46 | F53: 1160127.7 | G53: 0 | H53: 26971137 | I53: =+G53-C53 -> 0 | J53: =+H53-D53 -> 1122559.2
A54: 1481272 | B54: ຄ່າຫຼຸ່ຍຫ້ຽນສະສົມ ເຟີນີເຈີ່ | C54: 0 | D54: 89156263 | E54: 0 | F54: 3129690.5 | G54: 0 | H54: 92285953 | I54: =+G54-C54 -> 0 | J54: =+H54-D54 -> 3129690.5
A55: 2211110 | B55: ເຈົ້າໜີ້ຕະຫຼາດຫຼັກຊັບ LSX | C55: 0 | D55: 0 | E55: 67517477 | F55: 75648011 | G55: 0 | H55: 8130534 | I55: =+G55-C55 -> 0 | J55: =+H55-D55 -> 8130534
A56: 2344100 | B56: ເຈົ້າໜີ້ບັນຊີຊື້-ຂາຍຫຼັກຊັບຕາມຄຳສັ່ງຊື້-ບັນຊີເງິນສົດ | C56: 0 | D56: 104017012 | E56: 232770541 | F56: 334119424 | G56: 0 | H56: 205365895 | I56: =+G56-C56 -> 0 | J56: =+H56-D56 -> 101348883
A57: 2344200 | B57: ບັນຊີເງິນລູກຄ້າ- Cash Balance | C57: 0 | D57: 37956098685 | E57: 6396092184 | F57: 2998047564 | G57: 0 | H57: 34558054065 | I57: =+G57-C57 -> 0 | J57: =+H57-D57 -> -3398044620
A58: 2344600 | B58: ບັນຊີເຈົ້າໜີ້ຄ່າຈອງຊື້ຮຸ້ນ | C58: 0 | D58: 0 | E58: 0 | F58: 0 | G58: 0 | H58: 0 | I58: =+G58-C58 -> 0 | J58: =+H58-D58 -> 0
A59: 2344700 | B59: ເຈົ້າໜີ້ລໍຖ້າຖອນເງີນຄືນ | C59: 1.3425946e-05 | D59: 0 | E59: 0 | F59: 0 | G59: 1.3425946e-05 | H59: 0 | I59: =+G59-C59 -> 0 | J59: =+H59-D59 -> 0
... A77: 3908000 | B77: ຜົນໄດ້ຮັບ ລໍຖ້າຮັບຮອງ | C77: 0 | D77: 3.7998793e+09 | E77: 4.217205e+09 | F77: 417325707 | G77: 0 | H77: 0 | I77: =+G77-C77 -> 0 | J77: =+H77-D77 -> -3.7998793e+09
A78: Total | C78: =SUM(C5:C77) -> 1.4507383e+11 | D78: =SUM(D5:D77) -> 1.4421273e+11 | E78: =SUM(E5:E77) -> 1.7270832e+10 | F78: =SUM(F5:F77) -> 1.7109642e+10 | G78: =SUM(G5:G77) -> 1.4222823e+11 | H78: =SUM(H5:H77) -> 1.4120594e+11 | I78: =SUM(I5:I77) -> -2.8455956e+09 | J78: =SUM(J5:J77) -> -3.0067851e+09
B79: Diff ( P/L ) | D79: =+C78-D78 -> 8.6109995e+08 | F79: =+E78-F78 -> 1.611895e+08 | H79: =+G78-H78 -> 1.0222894e+09 | I79: =+I78-J78 -> 1.611895e+08 | J79: Gain for June'13
C82: ໜີ້ | D82: ມີ | E82: ໜີ້ | F82: ມີ | G82: ໜີ້ | H82: ມີ
A83: 4102730 | B83: ຄ່າບໍລິການເຊົ່າລະບົບເທີມີນໍ່ LSX | C83: 103735692 | D83: 0 | E83: 20704125 | F83: 0 | G83: 124439817 | H83: 0 | I83: =+F83-E83 -> -20704125
A84: 4102731 | B84: ຄ່າບໍລິການເຊົ່າລະບົບດິດສເປຣເຢີ່ LSX | C84: 12581568 | D84: 0 | E84: 2511000 | F84: 0 | G84: 15092568 | H84: 0 | I84: =+F84-E84 -> -2511000
A85: 4108210 | B85: ຄ່າທຳນຽມທະນາຄານ ( ຈ່າຍ ) | C85: 1093223.8 | D85: 0 | E85: 260631.4 | F85: 0 | G85: 1353855.2 | H85: 0 | I85: =+F85-E85 -> -260631.4
A86: 4201100 | B86: ເງິນເດືອນພະນັກງານໃນການຈັດຕັ້ງ | C86: 888315841 | D86: 0 | E86: 157750000 | F86: 0 | G86: 1046065841 | H86: 0 | I86: =+F86-E86 -> -157750000
A87: 4201400 | B87: ເງິນເພີ່ມໂມງ | C87: 52702167 | D87: 0 | E87: 1145625 | F87: 0 | G87: 53847792 | H87: 0 | I87: =+F87-E87 -> -1145625
A88: 4202200 | B88: ລາຍຈ່າຍຄ່າປະກັນໄພພະນັກງານ | C88: 50112277 | D88: 0 | E88: 9842764.4 | F88: 0 | G88: 59955042 | H88: 0 | I88: =+F88-E88 -> -9842764.4
A89: 4202210 | B89: ລາຍຈ່າຍຄ່າຮັກສາພະຍາບານ | C89: 1000000 | D89: 0 | E89: 890000 | F89: 0 | G89: 1890000 | H89: 0 | I89: =+F89-E89 -> -890000
A90: 4202220 | B90: ລາຍຈ່າຍຄ່ານ້ຳມັນລົດພະນັກງານ | C90: 83283871 | D90: 0 | E90: 16200000 | F90: 0 | G90: 99483871 | H90: 0 | I90: =+F90-E90 -> -16200000
A91: 4202800 | B91: ລາຍຈ່າຍສະຫວັດດີການພະນັກງານອື່ນໆ | C91: 47400000 | D91: 0 | E91: 0 | F91: 0 | G91: 47400000 | H91: 0 | I91: =+F91-E91 -> 0
A92: 4202811 | B92: ລາຍຈ່າຍເບ້ຍປະຊູມສະພາບໍລິຫານ | C92: 21473684 | D92: 0 | E92: 0 | F92: 0 | G92: 21473684 | H92: 0 | I92: =+F92-E92 -> 0
A93: 4203100 | B93: ສຳມະນາ ແລະຝຶກອົບຮົມພາຍໃນປະເທດ | C93: 68527320 | D93: 0 | E93: 0 | F93: 0 | G93: 68527320 | H93: 0 | I93: =+F93-E93 -> 0
A94: 4208300 | B94: ຄ່າໃຊ້ຈ່າຍໃນການຈັດກິດຈະກຳພະນັກງານ | C94: 1300000 | D94: 0 | E94: 2548000 | F94: 0 | G94: 3848000 | H94: 0 | I94: =+F94-E94 -> -2548000
... A159: 5508400 | B159: ລາຍຮັບອື່ນໆ | C159: 0 | D159: 2001.2 | E159: 30 | F159: 0.22 | G159: 0 | H159: 1971.42 | I159: =+F159-E159 -> -29.78
A160: ລວມມູນຄ່າ | C160: =SUM(C83:C159) -> 3.2806108e+09 | D160: =SUM(D83:D159) -> 4.1417108e+09 | E160: =SUM(E83:E159) -> 8.2392292e+08 | F160: =SUM(F83:F159) -> 9.8511242e+08 | G160: =SUM(G83:G159) -> 3.9517312e+09 | H160: =SUM(H83:H159) -> 4.9740206e+09 | I160: =SUM(I83:I159) -> 1.611895e+08 | J160: 0 | K160: -3.90625e-05 | L160: ນະຄອນຫຼວງວຽງຈັນ ວັນທີ : ......../......../............ , | M160: ຜູ້ອຳນວຍການ | N160: ທີ່ປຶກສາບັນຊີ | O160: ພະນັກງານບັນຊີ | P160: ຜູ້ສັງລວມ | Q160: ............…………………...... | R160: ...…………………………..
B161: P&L | D161: =+D160-C160 -> 8.6109995e+08 | F161: =+F160-E160 -> 1.611895e+08 | H161: =+H160-G160 -> 1.0222894e+09
D162: For Jan to May'13 | F162: For June 2013 | H162: For Six months

Sheet BS
A1: ສາທາລະນະລັດ ປະຊາທິປະໄຕ ປະຊາຊົນລາວ | B1: ສັນຕິພາບ ເອກະລາດ ປະຊາທິປະໄຕ ເອກະພາບ ວັດທະນາຖາວອນ
A2: ບໍລິສັດຫຼັກຊັບ ທຄຕລ-ກທ ຈຳກັດ_x000D_ ຊັ້ນ7, ຕຶກຕະຫຼາກຫຼັກຊັບລາວ, ຖະໜົນກຳແພງເມືອງ_x000D_ +856-21-265477+856-21-265488
D3: ໃບສະຫລຸບຊັບສົມບັດ | E3: ໃນປີ 2012
A4: ລ/ດ | B4: ເລກບັນຊີ | C4: ເນື້ອໃນລາຍການ | D4: ປີນີ້ | E4: ປີກ່ອນ
A5: 1 | B5: 1. ​ເງິນສົດ ​ແລະ ທຽບ​ເທົ່​າເງິນສົດ | D5: 4468000 | E5: 10000000
A6: 1 | B6: 1101100 | C6: ເງິນສົດໃນຄັງ " HO " ກີບ | D6: 4468000 | E6: 10000000
A7: 2 | B7: 2.1. ເງິນຝາກທະນາຄານ | D7: 1.5681483e+11 | E7: 1.3662937e+11
A8: 2 | B8: 1131115 | C8: ບັນຊີກະແສລາຍວັນ ທຄຕລ Aggregate AC: 010.4.19.00.00010 ( ກີບ ) | D8: 55650947823 | E8: 39741098167
A9: 3 | B9: 1131116 | C9: ບັນຊີກະແສລາຍວັນ ທຄຕລ for ETL staff IPO AC: 010.9.00.00001 ( ກີບ ) | D9: 100000 | E9: 100000
A10: 4 | B10: 1131154 | C10: ບັນຊີຝາກມີກຳນົດທີ່ ທສກ: 0402.0402.00.2131315.47.00000004 ( ກີບ ) | D10: 25000000000 | E10: 0
B11: 1131110 | C11: ບັນຊີກະແສລາຍວັນ ທຄຕລ: 010.0.11.00.24740 ( ກີບ ) | D11: 137607.24 | E11: 652607.74
A12: 6 | B12: 1131159 | C12: ບັນຊີຝາກມີກຳນົດທີ່ ST Bank: 010.5.35.00.08899 ( ກີບ ) | D12: 5000000000 | E12: 0
A13: 7 | B13: 1131113 | C13: ບັນຊີກະແສລາຍວັນ ທຄຕລ Proprietary AC: 010.4.19.00.00009 ( ກີບ ) | D13: 294629790 | E13: 92595445
A14: 8 | B14: 1131162 | C14: ບັນຊີເງິນຝາກມີກຳນົດ ທີ່ ທະນາຄານ ເອຊີລີດາ ( ກີບ ) | D14: 35000000000 | E14: 0
A15: 9 | B15: 1131111 | C15: ບັນຊີກະແສລາຍວັນ ທຄຕລ: 010.7.11.02.08233 ( ບາດ ) | D15: 1788525.4 | E15: 713249.55
A16: 10 | B16: 1131134 | C16: ບັນຊີຝາກປະຢັດທີ່ ທສກ: 0402.0.00.220130 ( ກີບ ) | D16: 3469166998 | E16: 1358879432
A17: 11 | B17: 1131131 | C17: ບັນຊີຝາກປະຢັດທີ່ ທຄຕລ: 013.9.12.01.00001 ( ໂດລ່າ ) | D17: 30012667 | E17: 8.9027339e+08
A18: 12 | B18: 1121110 | C18: ບັນຊີທຶນຈົດທະບຽນຂອງ ທຄຕລ-ກທ ຈຳກັດ ( ກີບ ) | D18: 2.2816035e+09 | E18: 7.2281614e+10
A19: 13 | B19: 1131112 | C19: ບັນຊີກະແສລາຍວັນ ທຄຕລ: 010.9.11.01.19243 ( ໂດລ່າ ) | D19: 1594317.1 | E19: 1641620.4
A20: 14 | B20: 1131121 | C20: ບັນຊີກະແສລາຍວັນ ເອຊີລີດາ 123359-1-1-101 | D20: 1000000 | E20: 0
A21: 15 | B21: 1131153 | C21: ບັນຊີຝາກມີກຳນົດທີ່ ທສກ: 0402.0402.00.2131315.47.00000003 ( ກີບ ) | D21: 20000000000 | E21: 20000000000
A22: 16 | B22: 1131130 | C22: ບັນຊີຝາກປະຢັດທີ່ ທຄຕລ: 013.2.12.00.00036 ກີບ | D22: 9.2493495e+09 | E22: 2.2618014e+09
A23: 17 | B23: 1131137 | C23: ບັນຊີຝາກປະຍັດ ທຄຕລ-ກທ ທີ່ ເອຊີລີດາ 123359-1-0-0101 ( ກີບ ) | D23: 8.3449851e+08 | E23: 0
A24: 3 | B24: 3.1. ເງິນລົງທຶນໄລຍະສັ້ນ | D24: 5.149202e+08 | E24: 79930000
A25: 18 | B25: 1302216 | C25: ເງິນລົງທືນຊົ່ວຄາວຫຼັກຊັບ-ເພື່ອຄ້າ-Port Trading | D25: 4.7421994e+08 | E25: 117180970
A26: 19 | B26: 1302218 | C26: ຄ່າປັບມູນຄ່າເງິນລົງທືນຊົ່ວຄາວຫຼັກຊັບ-ເພື່ອຄ້າ-Port trading | D26: 40700260 | E26: -37250970
A27: 4 | B27: 4.1. ໜີ້ຕ້ອງ​ຮັບ​ທາງການຄ້າ | D27: 58820889 | E27: 4284683
A28: 20 | B28: 1201181 | C28: ລູກໜີ້ຊື້ຫຼັກຊັບຕາມຄຳສັ່ງຊື້-ບັນຊີເງິນສົດ | D28: 58820889 | E28: 4284683
A29: 5 | B29: 4.3. ໜີ້ຕ້ອງ​ຮັບ​ລະຫວ່າງ​ບໍລິສັດໃນກຸ່ມ | C29: 0 | D29: 23823233
A30: 21 | B30: 1211110 | C30: ລູກໜີ້ບັນຊີຊື້-ຂາຍຫຼັກຊັບລະຫວ່າງບ/ສ ກັບ LSX | D30: 0 | E30: 23823233
A31: 6 | B31: 6. ຊັບສິນໝູນວຽນອື່ນໆ | D31: 6468583 | E31: 1.526439e+08
A32: 22 | B32: 1360000 | C32: ລູກໜີ້ອື່ນໆ | D32: 5968583 | E32: 61100181
A33: 23 | B33: 1361300 | C33: ອາກອນອື່ນໆທີ່ຕ້ອງຮັບຄືນ | D33: -7.4505806e-09 | E33: 27382364
A34: 24 | B34: 1362100 | C34: ເງິນຈ່າຍລ່ວງໜ້າເພື່ອເຄື່ອນໄຫວວຽກງານ | D34: 500000 | E34: 36400000
A35: 25 | B35: 1361100 | C35: ອາກອນກຳໄລມອບລ່ວງໜ້າ | D35: 0 | E35: 27761356
A36: 7 | B36: 2. ຊັບສິນຄົງທີ່ບໍ່ມີຕົວຕົນ | D36: 3.0777805e+08 | E36: 2.7021397e+08
A37: 26 | B37: 1441810 | C37: ຊັອບແວຄອມພີວເຕີ່ | D37: 3.0777805e+08 | E37: 2.7021397e+08
A38: 8 | B38: 3. ຊັບ​ສົມບັດຄົງ​ທີ່​ມີຕົວຕົນ | D38: 3.3460869e+09 | E38: 3.1995897e+09
A39: 27 | B39: 1442510 | C39: ຄ່າຕົບແຕ່ງສຳນັກງານ | D39: 1.5476721e+09 | E39: 1.5394821e+09
A40: 28 | B40: 1442400 | C40: ພາຫະນະຂົນສົ່ງ | D40: 629368000 | E40: 615368000
A41: 29 | B41: 1442710 | C41: ອຸປະກອນສຳນັກງານ | D41: 1.3821519e+08 | E41: 96539608
A42: 30 | B42: 1442610 | C42: ອຸປະກອນຄອມພີວເຕີ່ | D42: 6.4974202e+08 | E42: 5.7426087e+08
A43: 31 | B43: 1442720 | C43: ອຸປະກອນເຟີນີເຈີ່ | D43: 3.8108966e+08 | E43: 3.7393916e+08
A44: 9 | B44: 4. ຄ່າຫຼຸ້ຍຫ້ຽນສະສົມ ຊັບສົມບັດຄົງທີ່ | D44: -8.1573085e+08 | E44: -3.9703185e+08
A45: 32 | B45: 1481261 | C45: ຄ່າຫຼຸ່ຍຫ້ຽນສະສົມ ອຸປະກອນຄອມພີວເຕີ່ | D45: -1.1275282e+08 | E45: -49361921
A46: 33 | B46: 1481251 | C46: ຄ່າຫຼຸ່ຍຫ້ຽນສະສົມ ຄ່າຕົບແຕ່ງສຳນັກງານ | D46: -3.0644814e+08 | E46: -1.5065818e+08
A47: 34 | B47: 1481272 | C47: ຄ່າຫຼຸ່ຍຫ້ຽນສະສົມ ເຟີນີເຈີ່ | D47: -73403487 | E47: -35686254
A48: 35 | B48: 1481271 | C48: ຄ່າຫຼຸ່ຍຫ້ຽນສະສົມ ອຸປະກອນສຳນັກງານ | D48: -20246504 | E48: -7995341.2
A49: 36 | B49: 1481240 | C49: ຄ່າຫຼຸ່ຍຫ້ຽນສະສົມພາຫະນະ | D49: -2.4420932e+08 | E49: -1.1976696e+08
A50: 37 | B50: 1481181 | C50: ຄ່າຕັດຈຳໜ່າຍຄອມພີວເຕີ່ຊ້ອບແວສະສົມ | D50: -58670585 | E50: -33563188
A51: 10 | B51: 1. ດອກເບ້ຍແລະເງິນປັນຜົນຄ້າງຮັບ | D51: 1.1975661e+09 | E51: 169863014
A52: 38 | B52: 1137111 | C52: ດອກເບ້ຍຝາກມີກຳນົດ ຄ້າງຮັບ 1 ປີລົງມາ | D52: 6.6170662e+08 | E52: 169863014
A53: 39 | B53: 1301720 | C53: ຄ່າທີ່ປຶກສາຄ້າງຮັບ | D53: 535859520 | E53: 0
A54: 11 | B54: 2. ບັນຊີຊໍາລະສະສາງ | D54: 5.6699121e+08 | E54: 2.4204396e+08
A55: 40 | B55: 1388170 | C55: ຄ່າໜັງສືພີມ ຈ່າຍລ່ວງໜ້າອື່ນໆ | D55: 216393.45 | E55: 2.1599591e+08
A56: 41 | B56: 1388120 | C56: ຄ່າປະກັນໄພຈ່າຍລ່ວງໜ້າ | D56: 1.2029605e+08 | E56: 2097153.1
A57: 42 | B57: 1388110 | C57: ຄ່າເຊົ່າຈ່າຍລ່ວງໜ້າ | D57: 4.4076906e+08 | E57: 23950902
A58: 43 | B58: 1388180 | C58: ລາຍຈ່າຍ ຈ່າຍລ່ວງໜ້າອື່ນໆ | D58: 5709708.2 | E58: 0
A59: 12 | B59: 3. ເງິນວາງຄ້ຳປະກັນ | D59: 167344691 | E59: 148406524
A60: 44 | B60: 1138810 | C60: ເງິນມັດຈຳຄ່າເຊົ່າ | D60: 11888910 | E60: 11888910
A61: 45 | B61: 1138100 | C61: ກອງທຶນປົກປ້ອງຄວາມສ່ຽງໃນການຊຳລະສະສາງ | D61: 155455781 | E61: 136517614
A62: 13 | B62: 3. ໜີ້ຕ້ອງສົ່ງທາງທຸລະກຳຫລັກຊັບ | D62: -55676142471 | E62: -39764793022
A63: 46 | B63: 2344700 | C63: ເຈົ້າໜີ້ລໍຖ້າຖອນເງີນຄືນ | D63: -25194648 | E63: 0
A64: 47 | B64: 2344100 | C64: ເຈົ້າໜີ້ບັນຊີຊື້-ຂາຍຫຼັກຊັບຕາມຄຳສັ່ງຊື້-ບັນຊີເງິນສົດ | D64: 0 | E64: -23694855
A65: 48 | B65: 2344200 | C65: ບັນຊີເງິນລູກຄ້າ- Cash Balance | D65: -55650947823 | E65: -39741098167
A66: 14 | B66: 4. ໜີ້ຕ້ອງ​ສົ່ງ​ລະຫວ່າງ​ບໍລິສັດໃນກຸ່ມ | D66: -57237576 | E66: -3845762
A67: 49 | B67: 2211110 | C67: ເຈົ້າໜີ້ຕະຫຼາດຫຼັກຊັບ LSX | D67: -57237576 | E67: -3845762
A68: 15 | B68: 5. ອາກອນກຳໄລຄ້າງຈ່າຍ | D68: -1.4555616e+09 | E68: 0
A69: 50 | B69: 2361110 | C69: ອາກອນກຳໄລທີ່ຕ້ອງມອບເພີ່ມ | D69: -1.4555616e+09 | E69: 0
A70: 16 | B70: 6. ໜີ້ຕ້ອງສົ່ງອື່ນໆ | D70: -1.7115627e+08 | E70: -43421744
A71: 51 | B71: 2361120 | C71: ອາກອນມູນຄ່າເພີ່ມທີ່ຕ້ອງມອບເພີ່ມ | D71: 0.050000191 | E71: 0
A72: 52 | B72: 2361130 | C72: ພາສີ ແລະອາກອນຕ່າງໆ ທີ່ຫັກໄວ້ຕ້ອງສົ່ງມອບ | D72: -1.3973847e+08 | E72: 0
A73: 53 | B73: 2361140 | C73: ອາກອນເງິນເດືອນຕ້ອງສົ່ງມອບ | D73: -31417799 | E73: -43421744
A74: 17 | B74: 1. ບັນຊີຊໍາລະສະສາງ | D74: -8.5340598e+08 | E74: -5.2925179e+08
A75: 54 | B75: 2361420 | C75: ຄ່າ terminal LSX ຄ້າງຈ່າຍ | D75: -21286512 | E75: -17150000
A76: 55 | B76: 2361831 | C76: ຄ່າໄຟຟ້າຄ້າງຈ່າຍ | D76: -7239040 | E76: 0
A77: 56 | B77: 2361430 | C77: ຄ່າ Displayer LSX ຄ້າງຈ່າຍ | D77: -2581632 | E77: -2600000
A78: 57 | B78: 2363682 | C78: ບັນຊີເຈົ້າໜີ້ KTZmico Co.,Ltd | D78: -2.9070674e+08 | E78: 0
A79: 58 | B79: 2361440 | C79: ຄ່າໃຊ້ຈ່າຍຄ້າງຈ່າຍອື່ນໆ | D79: -3.7545304e+08 | E79: -3.0206731e+08
A80: 59 | B80: 2361410 | C80: ຄ່າບໍລິການຄ້າງຈ່າຍ | D80: -129098980 | E80: -139126366
A81: 60 | B81: 2361830 | C81: ຄ່າໄຟຟ້າ ແລະນ້ຳປະປາຄ້າງຈ່າຍ | D81: 0 | E81: -68308110
A82: 61 | B82: 2363684 | C82: ບັນຊີເຈົ້າໜີ້ອື່ນໆ | D82: -27040033 | E82: 0
A83: 18 | B83: 1.2 ທຶນຈົດທະບຽນຍັງບໍ່ທັນຖອກ | C83: -100000000000 | D83: -100000000000
A84: 62 | B84: 3108210 | C84: ທຶນຈົດທະບຽນທີ່ຖອກແລ້ວ | D84: -100000000000 | E84: -100000000000
A85: 19 | B85: 3. ກຳໄລ(ຂາດທຶນ)ສະສົມ | C85: -1.9182372e+08 | D85: -1.9182372e+08
A86: 63 | B86: 3810000 | C86: ກຳໄລ-ຂາດທຶນສະສົມ | D86: -1.9182372e+08 | E86: -1.9182372e+08
A87: 20 | B87: 5. ຜົນໄດ້ຮັບໃນປີ | C87: -3.7642156e+09 | D87: 0
A88: 64 | B88: 3901000 | C88: ກຳໄລ-ຂາດ ທຶນໃນປີ | D88: -3.7642156e+09 | E88: 0
A89: ນະຄອນຫຼວງວຽງຈັນ ວັນທີ : ......../......../............ , | B89: ຜູ້ອຳນວຍການ | C89: ທີ່ປຶກສາບັນຊີ | D89: ພະນັກງານບັນຊີ | E89: ຜູ້ສັງລວມ | F89: ............…………………...... | G89: ............…………………...... | H89: ............…………………...... | I89: ............…………………...... | J89: ...………………………….. | K89: ...………………………….. | L89: ...………………………….. | M89: ...…………………………..
A90: 1

Sheet PL
A1: ສາທາລະນະລັດ ປະຊາທິປະໄຕ ປະຊາຊົນລາວ | B1: ສັນຕິພາບ ເອກະລາດ ປະຊາທິປະໄຕ ເອກະພາບ ວັດທະນາຖາວອນ
A2: ບໍລິສັດຫຼັກຊັບ ທຄຕລ-ກທ ຈຳກັດ_x000D_ ຊັ້ນ7, ຕຶກຕະຫຼາກຫຼັກຊັບລາວ, ຖະໜົນກຳແພງເມືອງ_x000D_ +856-21-265477+856-21-265488
D3: ໃບລາຍງານຜົນໄດ້ຮັບ | E3: ໃນປີ 2012
A4: ເອກະສານຊ້ອນທ້າຍ
A5: ລຳດັບ | B5: ລາຍຮັບ | C5: 1.1 | D5: 0 | E5: 0
A6: I | B6: ລາຍຮັບຈາກການດຳເນີນງານ | C6: 1.1.1 | D6: 5.4220711e+10 | E6: 0
B7: 1. ຄ່ານາຍໜ້າຈາກການຊື້-ຂາຍຫຼັກຊັບ | C7: 1.1.1.1 | D7: 1698263965 | E7: 0
B8: 2. ຄ່າບໍລິການ | C8: 1.1.1.2 | D8: 4.7128415e+10 | E8: 0
B9: 2.1. ຄ່າບໍລິການໃຫ້ຄຳປຶກສາທາງດ້ານການເງິນ | C9: 1.1.1.2.1 | D9: 4.3376696e+09 | E9: 0
B10: 2.2. ຄ່າບໍລິການ ຄໍ້າປະກັນການຈັດຈຳໜ່າຍຫຼັກຊັບ | C10: 1.1.1.2.2 | D10: 42790745204 | E10: 0
B11: 2.3. ຄ່າບໍລິການ ເປັນຕົວແທນຈຳໝ່າຍຫຼັກຊັບ | C11: 1.1.1.2.3 | D11: 0 | E11: 0
B12: 3. ກຳໄລ(ຂາດທຶນ)ຈາກການຊື້ຂາຍຫຼັກຊັບ | C12: 1.1.1.3 | D12: 74367920 | E12: 0
B13: 4. ດອກເບ້ຍ ແລະ ເງິນປັນຜົນ | C13: 1.1.1.4 | D13: 5.3196641e+09 | E13: 0
A14: II | B14: ລາຍຮັບອື່ນໆ | C14: 1.1.2 | D14: -1.4064442e+08 | E14: 0
B15: ລາຍຮັບອື່ນໆ | C15: 1.1.2.5 | D15: -1.4064442e+08 | E15: 0
B16: ລວມຍອດລາຍຮັບ | C16: 1.13 | D16: 5.4080066e+10 | E16: 0
A17: ລຳດັບ | B17: ລາຍຈ່າຍ | C17: 1.2. | D17: 0 | E17: 0
A18: I | B18: ລາຍຈ່າຍຈາກການດຳເນີນງານ | C18: 1.2.1 | D18: 4.2748984e+10 | E18: 0
B19: 1. ລາຍຈ່າຍຄ່ານາຍໜ້າຊື້-ຂາຍຫຼັກຊັບ | C19: 1.2.1.1.1 | D19: 1.0378224e+09 | E19: 0
B20: 2. ລາຍຈ່າຍຄ່າໃຫ້ຄຳປຶກສາທາງການເງິນ | C20: 1.2.1.1.2 | D20: 4.1056803e+10 | E20: 0
B21: 3. ລາຍຈ່າຍຄ່າໃຫ້ການຄໍ້າປະກັນການຈັດຈຳໜ່າຍຫຼັກຊັບ | C21: 1.2.1.1.3 | D21: 0 | E21: 0
B22: 4. ລາຍຈ່າຍການຄ້າຫຼັກຊັບ | C22: 1.2.1.1.4 | D22: 0 | E22: 0
B23: 5. ລາຍຈ່າຍອື່ນໆທາງດ້ານຫຼັກຊັບ | C23: 1.2.1.1.5 | D23: 6.5435877e+08 | E23: 0
A24: II | B24: ລາຍຈ່າຍໃນການບໍລິຫານ | C24: 1.2.2 | D24: 6.0327915e+09 | E24: 0
B25: 1. ລາຍຈ່າຍກ່ຽວກັບພະນັກງານ | C25: 1.2.2.2.1 | D25: 3.3459934e+09 | E25: 0
B26: 2. ຄ່າຫລຸ້ຍຫ້ຽນອາຄານສະຖານທີ່ ແລະ ອຸປະກອນ | C26: 1.2.2.2.2 | D26: 4.3048138e+08 | E26: 0
B27: 3. ລາຍຈ່າຍພາສີອາກອນ | C27: 1.2.2.2.3 | D27: 77870728 | E27: 0
B28: 4. ລາຍຈ່າຍອື່ນໆ | C28: 1.2.2.2.4 | D28: 2.178446e+09 | E28: 0
A29: III | B29: ລາຍຈ່າຍດອກເບ້ຍເງິນກູ້ຢືມ | C29: 1.2.3 | D29: 0 | E29: 0
B30: ລາຍຈ່າຍດອກເບ້ຍເງິນກູ້ຢືມ | C30: 1.2.3.3.1 | D30: 0 | E30: 0
B31: ລວມຍອດລາຍຈ່າຍ | C31: 1.2.4 | D31: 4.8781776e+10 | E31: 0
B32: ກຳໄລກ່ອນອາກອນ | C32: 1.2.4.1 | D32: 5.2982905e+09 | E32: 0
B33: ອາກອນກຳໄລ | C33: 1.2.4.2 | D33: 1.534075e+09 | E33: 0
B34: ກຳໄລສຸດທິ | C34: 1.2.4.3 | D34: 3.7642156e+09 | E34: 0
A35: ນະຄອນຫຼວງວຽງຈັນ ວັນທີ : ......../......../............ , | B35: ຜູ້ອຳນວຍການ | C35: ທີ່ປຶກສາບັນຊີ | D35: ພະນັກງານບັນຊີ | E35: ຜູ້ສັງລວມ | F35: ............…………………...... | G35: ............…………………...... | H35: ............…………………...... | I35: ............…………………...... | J35: ...………………………….. | K35: ...………………………….. | L35: ...………………………….. | M35: ...…………………………..
A36: 1

Sheet TB Q I 2013
A1: ສາທາລະນະລັດ ປະຊາທິປະໄຕ ປະຊາຊົນລາວ | B1: ສັນຕິພາບ ເອກະລາດ ປະຊາທິປະໄຕ ເອກະພາບ ວັດທະນາຖາວອນ | D1: TB for Quarter
C3: Openning | E3: Movement | G3: Balance
C4: ໜີ້ | D4: ມີ | E4: ໜີ້ | F4: ມີ | G4: ໜີ້ | H4: ມີ
A5: 1101100 | B5: ເງິນສົດໃນຄັງ " HO " ກີບ | C5: 4468000 | D5: 0 | E5: 34264818 | F5: 28732818 | G5: 10000000 | H5: 0
A6: 1121110 | B6: ບັນຊີທຶນຈົດທະບຽນຂອງ ທຄຕລ-ກທ ຈຳກັດ ( ກີບ ) | C6: 2.2816035e+09 | D6: 0 | E6: 0 | F6: 0 | G6: 2.2816035e+09 | H6: 0
A7: 1131110 | B7: ບັນຊີກະແສລາຍວັນ ທຄຕລ: 010.0.11.00.24740 ( ກີບ ) | C7: 137607.24 | D7: 0 | E7: 0 | F7: 0 | G7: 137607.24 | H7: 0
A8: 1131111 | B8: ບັນຊີກະແສລາຍວັນ ທຄຕລ: 010.7.11.02.08233 ( ບາດ ) | C8: 1788525.4 | D8: 0 | E8: 2.2898562e+08 | F8: 3039199.2 | G8: 2.2773495e+08 | H8: 0
A9: 1131112 | B9: ບັນຊີກະແສລາຍວັນ ທຄຕລ: 010.9.11.01.19243 ( ໂດລ່າ ) | C9: 1594317.1 | D9: 0 | E9: 0 | F9: 93419.15 | G9: 1500898 | H9: 0
A10: 1131113 | B10: ບັນຊີກະແສລາຍວັນ ທຄຕລ Proprietary AC: 010.4.19.00.00009 ( ກີບ ) | C10: 294629790 | D10: 0 | E10: 9547278851 | F10: 9671102750 | G10: 170805891 | H10: 0
A11: 1131115 | B11: ບັນຊີກະແສລາຍວັນ ທຄຕລ Aggregate AC: 010.4.19.00.00010 ( ກີບ ) | C11: 55650947823 | D11: 0 | E11: 29289650887 | F11: 53729764770 | G11: 31210833940 | H11: 0
A12: 1131116 | B12: ບັນຊີກະແສລາຍວັນ ທຄຕລ for ETL staff IPO AC: 010.9.00.00001 ( ກີບ ) | C12: 100000 | D12: 0 | E12: 0 | F12: 0 | G12: 100000 | H12: 0
A13: 1131117 | B13: ບັນຊີກະແສລາຍວັນ ທຄຕລ ສຳລັບການຈອງ RO EDL-Gen :010.8.19.00.00012 LAk | C13: 0 | D13: 0 | E13: 0 | F13: 0 | G13: 0 | H13: 0
A14: 1131119 | B14: ບັນຊີກະແສລາຍວັນ ທຄຕລ ສຳລັບການ​ຈອງ PO EDL: 010.5.19.00.00013 Lak | C14: 3.8146973e-06 | D14: 0 | E14: 0 | F14: 0 | G14: 3.8146973e-06 | H14: 0
A15: 1131120 | B15: ບັນຊີກະແສລາຍວັນ ທຄຕລ ສຳລັບການ​ຈອງ PO EDL: 010.4.19.01.00006 USD | C15: 0 | D15: 1.3425946e-05 | E15: 0 | F15: 0 | G15: 0 | H15: 1.3425946e-05
A16: 1131121 | B16: ບັນຊີກະແສລາຍວັນ ເອຊີລີດາ 123359-1-1-101 | C16: 1000000 | D16: 0 | E16: 0 | F16: 0 | G16: 1000000 | H16: 0
... A75: 3908000 | B75: ຜົນໄດ້ຮັບ ລໍຖ້າຮັບຮອງ | C75: 0 | D75: 0 | E75: 0 | F75: 3.7998793e+09 | G75: 0 | H75: 3.7998793e+09
C76: =SUM(C5:C75) -> 1.6298527e+11 | D76: =SUM(D5:D75) -> 1.6298527e+11 | E76: =SUM(E5:E75) -> 1.2351557e+11 | F76: =SUM(F5:F75) -> 1.2288643e+11 | G76: =SUM(G5:G75) -> 1.3876633e+11 | H76: =SUM(H5:H75) -> 1.3813719e+11
D77: =+D76-C76 -> 0 | F77: =+F76-E76 -> -6.2913859e+08 | H77: =+H76-G76 -> -6.2913859e+08
H78: =+H77-F77 -> 0 | I78: OK
C83: Openning | E83: Movement | G83: Balance
C84: ໜີ້ | D84: ມີ | E84: ໜີ້ | F84: ມີ | G84: ໜີ້ | H84: ມີ
A85: 4102730 | B85: ຄ່າບໍລິການເຊົ່າລະບົບເທີມີນໍ່ LSX | C85: 0 | D85: 0 | E85: 62852380 | F85: 0 | G85: 62852380 | H85: 0
A86: 4102731 | B86: ຄ່າບໍລິການເຊົ່າລະບົບດິດສເປຣເຢີ່ LSX | C86: 0 | D86: 0 | E86: 7622748 | F86: 0 | G86: 7622748 | H86: 0
A87: 4108210 | B87: ຄ່າທຳນຽມທະນາຄານ ( ຈ່າຍ ) | C87: 0 | D87: 0 | E87: 811997.42 | F87: 0 | G87: 811997.42 | H87: 0
A88: 4201100 | B88: ເງິນເດືອນພະນັກງານໃນການຈັດຕັ້ງ | C88: 0 | D88: 0 | E88: 472059677 | F88: 0 | G88: 472059677 | H88: 0
A89: 4201400 | B89: ເງິນເພີ່ມໂມງ | C89: 0 | D89: 0 | E89: 50823417 | F89: 0 | G89: 50823417 | H89: 0
A90: 4202200 | B90: ລາຍຈ່າຍຄ່າປະກັນໄພພະນັກງານ | C90: 0 | D90: 0 | E90: 30098656 | F90: 0 | G90: 30098656 | H90: 0
A91: 4202210 | B91: ລາຍຈ່າຍຄ່າຮັກສາພະຍາບານ | C91: 0 | D91: 0 | E91: 500000 | F91: 0 | G91: 500000 | H91: 0
A92: 4202220 | B92: ລາຍຈ່າຍຄ່ານ້ຳມັນລົດພະນັກງານ | C92: 0 | D92: 0 | E92: 50883871 | F92: 0 | G92: 50883871 | H92: 0
A93: 4202800 | B93: ລາຍຈ່າຍສະຫວັດດີການພະນັກງານອື່ນໆ | C93: 0 | D93: 0 | E93: 20800000 | F93: 0 | G93: 20800000 | H93: 0
A94: 4202811 | B94: ລາຍຈ່າຍເບ້ຍປະຊູມສະພາບໍລິຫານ | C94: 0 | D94: 0 | E94: 10736842 | F94: 0 | G94: 10736842 | H94: 0
A95: 4203100 | B95: ສຳມະນາ ແລະຝຶກອົບຮົມພາຍໃນປະເທດ | C95: 0 | D95: 0 | E95: 16506000 | F95: 0 | G95: 16506000 | H95: 0
A96: 4208300 | B96: ຄ່າໃຊ້ຈ່າຍໃນການຈັດກິດຈະກຳພະນັກງານ | C96: 0 | D96: 0 | E96: 800000 | F96: 0 | G96: 800000 | H96: 0
... A153: 5508400 | B153: ລາຍຮັບອື່ນໆ | C153: 0 | D153: 0 | E153: 0 | F153: 2001.2 | G153: 0 | H153: 2001.2
C154: =SUM(C85:C153) -> 0 | D154: =SUM(D85:D153) -> 0 | E154: =SUM(E85:E153) -> 2.417844e+09 | F154: =SUM(F85:F153) -> 3.0469826e+09 | G154: =SUM(G85:G153) -> 1.9557492e+09 | H154: =SUM(H85:H153) -> 2.5848878e+09
D155: =+D154-C154 -> 0 | F155: =+F154-E154 -> 6.2913859e+08 | H155: =+H154-G154 -> 6.2913859e+08
H156: =+H155-F155 -> 0 | I156: OK
F157: =+F155+F77 -> 1.1920929e-05 | H157: =+H155+H77 -> 1.168251e-05

Sheet TB for 2013
A1: ສາທາລະນະລັດ ປະຊາທິປະໄຕ ປະຊາຊົນລາວ | B1: ສັນຕິພາບ ເອກະລາດ ປະຊາທິປະໄຕ ເອກະພາບ ວັດທະນາຖາວອນ
D2: ໃບດູນດ່ຽງປະຈຳປີ | E2: ໃນປີ 2013 | F2: ບໍລິສັດຫຼັກຊັບ ທຄຕລ-ກທ ຈຳກັດ_x000D_ ຊັ້ນ7, ຕຶກຕະຫຼາກຫຼັກຊັບລາວ, ຖະໜົນກຳແພງເມືອງ_x000D_ +856-21-265477+856-21-265488
C3: Opening | E3: Movement | G3: Balance | I3: Change | K3: Sum amount | L3: Note
C4: ໜີ້ | D4: ມີ | E4: ໜີ້ | F4: ມີ | G4: ໜີ້ | H4: ມີ | I4: ໜີ້ | J4: ມີ
A5: 1101100 | B5: ເງິນສົດໃນຄັງ " HO " ກີບ | C5: 4468000 | D5: 0 | E5: 144960445 | F5: 139428445 | G5: 10000000 | H5: 0 | I5: =+G5-C5 -> 5532000 | J5: =+H5-D5 -> 0
A6: 1121110 | B6: ບັນຊີທຶນຈົດທະບຽນຂອງ ທຄຕລ-ກທ ຈຳກັດ ( ກີບ ) | C6: 2.2816035e+09 | D6: 0 | E6: 0 | F6: 0 | G6: 2.2816035e+09 | H6: 0 | I6: =+G6-C6 -> 0 | J6: =+H6-D6 -> 0
A7: 1131110 | B7: ບັນຊີກະແສລາຍວັນ ທຄຕລ: 010.0.11.00.24740 ( ກີບ ) | C7: 137607.24 | D7: 0 | E7: 0 | F7: 40000 | G7: 97607.24 | H7: 0 | I7: =+G7-C7 -> -40000 | J7: =+H7-D7 -> 0
A8: 1131111 | B8: ບັນຊີກະແສລາຍວັນ ທຄຕລ: 010.7.11.02.08233 ( ບາດ ) | C8: 1788525.4 | D8: 0 | E8: 2.8019541e+08 | F8: 2.7770582e+08 | G8: 4278107.5 | H8: 0 | I8: =+G8-C8 -> 2489582.1 | J8: =+H8-D8 -> 0
A9: 1131112 | B9: ບັນຊີກະແສລາຍວັນ ທຄຕລ: 010.9.11.01.19243 ( ໂດລ່າ ) | C9: 1594317.1 | D9: 0 | E9: 71877.57 | F9: 144144.06 | G9: 1522050.6 | H9: 0 | I9: =+G9-C9 -> -72266.49 | J9: =+H9-D9 -> 0
A10: 1131113 | B10: ບັນຊີກະແສລາຍວັນ ທຄຕລ Proprietary AC: 010.4.19.00.00009 ( ກີບ ) | C10: 294629790 | D10: 0 | E10: 189653749624 | F10: 188911397946 | G10: 1036981468 | H10: 0 | I10: =+G10-C10 -> 742351678 | J10: =+H10-D10 -> 0
A11: 1131115 | B11: ບັນຊີກະແສລາຍວັນ ທຄຕລ Aggregate AC: 010.4.19.00.00010 ( ກີບ ) | C11: 55650947823 | D11: 0 | E11: 346268328873 | F11: 329674393383 | G11: 72244883313 | H11: 0 | I11: =+G11-C11 -> 16593935490 | J11: =+H11-D11 -> 0
A12: 1131116 | B12: ບັນຊີກະແສລາຍວັນ ທຄຕລ for ETL staff IPO AC: 010.9.00.00001 ( ກີບ ) | C12: 100000 | D12: 0 | E12: 0 | F12: 0 | G12: 100000 | H12: 0 | I12: =+G12-C12 -> 0 | J12: =+H12-D12 -> 0
A13: 1131117 | B13: ບັນຊີກະແສລາຍວັນ ທຄຕລ ສຳລັບການຈອງ RO EDL-Gen :010.8.19.00.00012 LAk | C13: 0 | D13: 0 | E13: 0 | F13: 0 | G13: 0 | H13: 0 | I13: =+G13-C13 -> 0 | J13: =+H13-D13 -> 0
A14: 1131119 | B14: ບັນຊີກະແສລາຍວັນ ທຄຕລ ສຳລັບການ​ຈອງ PO EDL: 010.5.19.00.00013 Lak | C14: 3.8146973e-06 | D14: 0 | E14: 0 | F14: 0 | G14: 3.8146973e-06 | H14: 0 | I14: =+G14-C14 -> 0 | J14: =+H14-D14 -> 0
A15: 1131120 | B15: ບັນຊີກະແສລາຍວັນ ທຄຕລ ສຳລັບການ​ຈອງ PO EDL: 010.4.19.01.00006 USD | C15: 0 | D15: 1.3425946e-05 | E15: 0 | F15: 0 | G15: 0 | H15: 1.3425946e-05 | I15: =+G15-C15 -> 0 | J15: =+H15-D15 -> 0
A16: 1131121 | B16: ບັນຊີກະແສລາຍວັນ ເອຊີລີດາ 123359-1-1-101 | C16: 1000000 | D16: 0 | E16: 0 | F16: 0 | G16: 1000000 | H16: 0 | I16: =+G16-C16 -> 0 | J16: =+H16-D16 -> 0
... A24: 1131137 | B24: ບັນຊີຝາກປະຍັດ ທຄຕລ-ກທ ທີ່ ເອຊີລີດາ 123359-1-0-0101 ( ກີບ ) | C24: 8.3449851e+08 | D24: 0 | E24: 3.8310785e+10 | F24: 35059873014 | G24: 4.0854102e+09 | H24: 0 | I24: =+G24-C24 -> 3.2509117e+09 | J24: =+H24-D24 -> 0
A25: 1131138 | B25: ບັນຊີຝາກປະຢັດທີ່ທະນາຄານ ເອັສທີ 010.3.12.00.04771 | C25: 0 | D25: 0 | E25: 3043726 | F25: 0 | G25: 3043726 | H25: 0 | I25: =+G25-C25 -> 3043726 | J25: =+H25-D25 -> 0 | K25: =+SUM(I6:I25) -> 2.0271093e+10 | L25: OK
A26: 1131150 | B26: ບັນຊີຝາກມີກຳນົດທີ່ ທຄຕລ:010.27.00000.80192001 | C26: 0 | D26: 0 | E26: 35000000000 | F26: 0 | G26: 35000000000 | H26: 0 | I26: =+G26-C26 -> 35000000000 | J26: =+H26-D26 -> 0
A27: 1131153 | B27: ບັນຊີຝາກມີກຳນົດທີ່ ທສກ: 0402.0402.00.2131315.47.00000003 ( ກີບ ) | C27: 20000000000 | D27: 0 | E27: 0 | F27: 0 | G27: 20000000000 | H27: 0 | I27: =+G27-C27 -> 0 | J27: =+H27-D27 -> 0
A28: 1131154 | B28: ບັນຊີຝາກມີກຳນົດທີ່ ທສກ: 0402.0402.00.2131315.47.00000004 ( ກີບ ) | C28: 25000000000 | D28: 0 | E28: 0 | F28: 10000000000 | G28: 15000000000 | H28: 0 | I28: =+G28-C28 -> -10000000000 | J28: =+H28-D28 -> 0
A29: 1131159 | B29: ບັນຊີຝາກມີກຳນົດທີ່ ST Bank: 010.5.35.00.08899 ( ກີບ ) | C29: 5000000000 | D29: 0 | E29: 0 | F29: 0 | G29: 5000000000 | H29: 0 | I29: =+G29-C29 -> 0 | J29: =+H29-D29 -> 0
A30: 1131162 | B30: ບັນຊີເງິນຝາກມີກຳນົດ ທີ່ ທະນາຄານ ເອຊີລີດາ ( ກີບ ) | C30: 35000000000 | D30: 0 | E30: 0 | F30: 35000000000 | G30: 0 | H30: 0 | I30: =+G30-C30 -> -35000000000 | J30: =+H30-D30 -> 0
A31: 1131163 | B31: ບັນຊີເງິນຝາກມີກຳນົດທີ່ ທະນາຄານ ເອຊີລີດາ-1 | C31: 0 | D31: 0 | E31: 10000000000 | F31: 0 | G31: 10000000000 | H31: 0 | I31: =+G31-C31 -> 10000000000 | J31: =+H31-D31 -> 0
A32: 1137111 | B32: ດອກເບ້ຍຝາກມີກຳນົດ ຄ້າງຮັບ 1 ປີລົງມາ | C32: 6.6170662e+08 | D32: 0 | E32: 7.786387e+09 | F32: 7.7971804e+09 | G32: 6.5091324e+08 | H32: 0 | I32: =+G32-C32 -> -10793380 | J32: =+H32-D32 -> 0
A33: 1138100 | B33: ກອງທຶນປົກປ້ອງຄວາມສ່ຽງໃນການຊຳລະສະສາງ | C33: 155455781 | D33: 0 | E33: 31219974 | F33: 0 | G33: 186675755 | H33: 0 | I33: =+G33-C33 -> 31219974 | J33: =+H33-D33 -> 0
A34: 1138810 | B34: ເງິນມັດຈຳຄ່າເຊົ່າ | C34: 11888910 | D34: 0 | E34: 0 | F34: 0 | G34: 11888910 | H34: 0 | I34: =+G34-C34 -> 0 | J34: =+H34-D34 -> 0
A35: 1138830 | B35: ເງິນມັດຈຳອື່ນໆ | C35: 0 | D35: 0 | E35: 900898 | F35: 900898 | G35: 0 | H35: 0 | I35: =+G35-C35 -> 0 | J35: =+H35-D35 -> 0
A36: 1201181 | B36: ລູກໜີ້ຊື້ຫຼັກຊັບຕາມຄຳສັ່ງຊື້-ບັນຊີເງິນສົດ | C36: 58820889 | D36: 0 | E36: 31199788058 | F36: 30831272740 | G36: 427336207 | H36: 0 | I36: =+G36-C36 -> 368515318 | J36: =+H36-D36 -> 0
A37: 1211110 | B37: ລູກໜີ້ບັນຊີຊື້-ຂາຍຫຼັກຊັບລະຫວ່າງບ/ສ ກັບ LSX | C37: 0 | D37: 0 | E37: 12652709134 | F37: 12642566438 | G37: 10142696 | H37: 0 | I37: =+G37-C37 -> 10142696 | J37: =+H37-D37 -> 0
A38: 1301720 | B38: ຄ່າທີ່ປຶກສາຄ້າງຮັບ | C38: 535859520 | D38: 0 | E38: 1.8818972e+08 | F38: 7.2404924e+08 | G38: 1.5258789e-07 | H38: 0 | I38: =+G38-C38 -> -5.3585952e+08 | J38: =+H38-D38 -> 0 | K38: =+I32+I38 -> -5.466529e+08
A39: 1302216 | B39: ເງິນລົງທືນຊົ່ວຄາວຫຼັກຊັບ-ເພື່ອຄ້າ-Port Trading | C39: 4.7421994e+08 | D39: 0 | E39: 1.1881644e+09 | F39: 2.0104029e+08 | G39: 1.4613441e+09 | H39: 0 | I39: =+G39-C39 -> 9.8712412e+08 | J39: =+H39-D39 -> 0
A40: 1302218 | B40: ຄ່າປັບມູນຄ່າເງິນລົງທືນຊົ່ວຄາວຫຼັກຊັບ-ເພື່ອຄ້າ-Port trading | C40: 40700260 | D40: 0 | E40: 1.3546595e+09 | F40: 1.2861853e+09 | G40: 1.0917444e+08 | H40: 0 | I40: =+G40-C40 -> 68474177 | J40: =+H40-D40 -> 0 | K40: =+I39+I40 -> 1.0555983e+09 | L40: OK
A41: 1360000 | B41: ລູກໜີ້ອື່ນໆ | C41: 5968583 | D41: 0 | E41: 49885561 | F41: 27873337 | G41: 27980807 | H41: 0 | I41: =+G41-C41 -> 22012224 | J41: =+H41-D41 -> 0
A42: 1361100 | B42: ອາກອນກຳໄລມອບລ່ວງໜ້າ | C42: 0 | D42: 0 | E42: 433353461 | F42: 433353461 | G42: 0 | H42: 0 | I42: =+G42-C42 -> 0 | J42: =+H42-D42 -> 0
A43: 1361300 | B43: ອາກອນອື່ນໆທີ່ຕ້ອງຮັບຄືນ | C43: 0 | D43: 0 | E43: 372200 | F43: 372200 | G43: 0 | H43: 0 | I43: =+G43-C43 -> 0 | J43: =+H43-D43 -> 0
A44: 1361500 | B44: ລູນໜີ້ ເຄທີຂີມີໂກ້ ຈຳກັດ | C44: 0 | D44: 0 | E44: 3003136 | F44: 3003136 | G44: 0 | H44: 0 | I44: =+G44-C44 -> 0 | J44: =+H44-D44 -> 0
A45: 1362100 | B45: ເງິນຈ່າຍລ່ວງໜ້າເພື່ອເຄື່ອນໄຫວວຽກງານ | C45: 500000 | D45: 0 | E45: 106505000 | F45: 89805000 | G45: 17200000 | H45: 0 | I45: =+G45-C45 -> 16700000 | J45: =+H45-D45 -> 0
A46: 1388110 | B46: ຄ່າເຊົ່າຈ່າຍລ່ວງໜ້າ | C46: 4.4076906e+08 | D46: 0 | E46: 1.2366886e+08 | F46: 5.5512818e+08 | G46: 9309734.2 | H46: 0 | I46: =+G46-C46 -> -4.3145932e+08 | J46: =+H46-D46 -> 0
A47: 1388120 | B47: ຄ່າປະກັນໄພຈ່າຍລ່ວງໜ້າ | C47: 1.2029605e+08 | D47: 0 | E47: 21767146 | F47: 1.3740636e+08 | G47: 4656844.9 | H47: 0 | I47: =+G47-C47 -> -1.1563921e+08 | J47: =+H47-D47 -> 0
A48: 1388170 | B48: ຄ່າໜັງສືພີມ ຈ່າຍລ່ວງໜ້າອື່ນໆ | C48: 216393.45 | D48: 0 | E48: 11352000 | F48: 5280043 | G48: 6288350.4 | H48: 0 | I48: =+G48-C48 -> 6071957 | J48: =+H48-D48 -> 0
A49: 1388180 | B49: ລາຍຈ່າຍ ຈ່າຍລ່ວງໜ້າອື່ນໆ | C49: 5709708.2 | D49: 0 | E49: 9108000 | F49: 9412278.1 | G49: 5405430.2 | H49: 0 | I49: =+G49-C49 -> -304278.07 | J49: =+H49-D49 -> 0
A50: 1388810 | B50: ບັນຊີພັກອື່ນໆທາງດ້ານຫຼັກຊັບ | C50: 0 | D50: 0 | E50: 391534065 | F50: 98013335 | G50: 293520730 | H50: 0 | I50: =+G50-C50 -> 293520730 | J50: =+H50-D50 -> 0 | K50: =+SUM(I33:I35)+SUM(I41:I50) -> -1.7787792e+08
A51: 1441810 | B51: ຊັອບແວຄອມພີວເຕີ່ | C51: 3.0777805e+08 | D51: 0 | E51: 0 | F51: 6900000 | G51: 3.0087805e+08 | H51: 0 | I51: =+G51-C51 -> -6900000 | J51: =+H51-D51 -> 0
A52: 1442400 | B52: ພາຫະນະຂົນສົ່ງ | C52: 629368000 | D52: 0 | E52: 0 | F52: 0 | G52: 629368000 | H52: 0 | I52: =+G52-C52 -> 0 | J52: =+H52-D52 -> 0
A53: 1442510 | B53: ຄ່າຕົບແຕ່ງສຳນັກງານ | C53: 1.5476721e+09 | D53: 0 | E53: 4840000 | F53: 0 | G53: 1.5525121e+09 | H53: 0 | I53: =+G53-C53 -> 4840000 | J53: =+H53-D53 -> 0
A54: 1442610 | B54: ອຸປະກອນຄອມພີວເຕີ່ | C54: 6.4974202e+08 | D54: 0 | E54: 8996500 | F54: 3786644.9 | G54: 6.5495188e+08 | H54: 0 | I54: =+G54-C54 -> 5209855.1 | J54: =+H54-D54 -> 0
A55: 1442710 | B55: ອຸປະກອນສຳນັກງານ | C55: 1.3821519e+08 | D55: 0 | E55: 4011400 | F55: 980000 | G55: 1.4124659e+08 | H55: 0 | I55: =+G55-C55 -> 3031400 | J55: =+H55-D55 -> 0 | K55: =+SUM(I51:I55) -> 6181255.1
A56: 1442720 | B56: ອຸປະກອນເຟີນີເຈີ່ | C56: 3.8108966e+08 | D56: 0 | E56: 0 | F56: 0 | G56: 3.8108966e+08 | H56: 0 | I56: =+G56-C56 -> 0 | J56: =+H56-D56 -> 0
A57: 1481181 | B57: ຄ່າຕັດຈຳໜ່າຍຄອມພີວເຕີ່ຊ້ອບແວສະສົມ | C57: 0 | D57: 58670585 | E57: 6900003 | F57: 60913369 | G57: 0 | H57: 1.1268395e+08 | I57: =+G57-C57 -> 0 | J57: =+H57-D57 -> 54013366
A58: 1481240 | B58: ຄ່າຫຼຸ່ຍຫ້ຽນສະສົມພາຫະນະ | C58: 0 | D58: 2.4420932e+08 | E58: 0 | F58: 1.2573887e+08 | G58: 0 | H58: 3.6994819e+08 | I58: =+G58-C58 -> 0 | J58: =+H58-D58 -> 1.2573887e+08
A59: 1481251 | B59: ຄ່າຫຼຸ່ຍຫ້ຽນສະສົມ ຄ່າຕົບແຕ່ງສຳນັກງານ | C59: 0 | D59: 3.0644814e+08 | E59: 0 | F59: 1.5506962e+08 | G59: 0 | H59: 4.6151776e+08 | I59: =+G59-C59 -> 0 | J59: =+H59-D59 -> 1.5506962e+08
A60: 1481261 | B60: ຄ່າຫຼຸ່ຍຫ້ຽນສະສົມ ອຸປະກອນຄອມພີວເຕີ່ | C60: 0 | D60: 1.1275282e+08 | E60: 834450.85 | F60: 65088002 | G60: 0 | H60: 1.7700637e+08 | I60: =+G60-C60 -> 0 | J60: =+H60-D60 -> 64253551
A61: 1481271 | B61: ຄ່າຫຼຸ່ຍຫ້ຽນສະສົມ ອຸປະກອນສຳນັກງານ | C61: 0 | D61: 20246504 | E61: 37568.46 | F61: 13863974 | G61: 0 | H61: 34072910 | I61: =+G61-C61 -> 0 | J61: =+H61-D61 -> 13826406
A62: 1481272 | B62: ຄ່າຫຼຸ່ຍຫ້ຽນສະສົມ ເຟີນີເຈີ່ | C62: 0 | D62: 73403487 | E62: 0 | F62: 38077902 | G62: 0 | H62: 1.1148139e+08 | I62: =+G62-C62 -> 0 | J62: =+H62-D62 -> 38077902 | K62: =+SUM(J57:J62) -> 4.5097972e+08 | L62: OK
A63: 1482280 | B63: ບັນຊີພັກອື່ນໆ | C63: 0 | D63: 0 | E63: 892558604 | F63: 892558604 | G63: 0 | H63: 0 | I63: =+G63-C63 -> 0 | J63: =+H63-D63 -> 0
A64: 2211110 | B64: ເຈົ້າໜີ້ຕະຫຼາດຫຼັກຊັບ LSX | C64: 0 | D64: 57237576 | E64: 30334388279 | F64: 30572071804 | G64: 0 | H64: 294921101 | I64: =+G64-C64 -> 0 | J64: =+H64-D64 -> 237683525 | K64: =+J64 -> 237683525
A65: 2344100 | B65: ເຈົ້າໜີ້ບັນຊີຊື້-ຂາຍຫຼັກຊັບຕາມຄຳສັ່ງຊື້-ບັນຊີເງິນສົດ | C65: 0 | D65: 0 | E65: 13191670417 | F65: 13191670417 | G65: 0 | H65: 0 | I65: =+G65-C65 -> 0 | J65: =+H65-D65 -> 0
A66: 2344200 | B66: ບັນຊີເງິນລູກຄ້າ- Cash Balance | C66: 0 | D66: 55650947823 | E66: 329674393383 | F66: 346268328873 | G66: 0 | H66: 72244883313 | I66: =+G66-C66 -> 0 | J66: =+H66-D66 -> 16593935490
A67: 2344600 | B67: ບັນຊີເຈົ້າໜີ້ຄ່າຈອງຊື້ຮຸ້ນ | C67: 0 | D67: 0 | E67: 65275946000 | F67: 65275946000 | G67: 0 | H67: 0 | I67: =+G67-C67 -> 0 | J67: =+H67-D67 -> 0
A68: 2344700 | B68: ເຈົ້າໜີ້ລໍຖ້າຖອນເງີນຄືນ | C68: 0 | D68: 25194648 | E68: 25194648 | F68: 0 | G68: 1.3427734e-05 | H68: 0 | I68: =+G68-C68 -> 1.3427734e-05 | J68: =+H68-D68 -> -25194648
A69: 2346000 | B69: ບັນຊີຊຳລະສະສາງອື່ນໆກ່ຽວກັບຫຼັກຊັບ | C69: 0 | D69: 0 | E69: 990571939 | F69: 1284092669 | G69: 0 | H69: 293520730 | I69: =+G69-C69 -> 0 | J69: =+H69-D69 -> 293520730 | K69: =+SUM(J65:J69) -> 1.6862262e+10
A70: 2361110 | B70: ອາກອນກຳໄລທີ່ຕ້ອງມອບເພີ່ມ | C70: 0 | D70: 1.4555616e+09 | E70: 2.0940763e+09 | F70: 1.0159372e+09 | G70: 0 | H70: 3.774225e+08 | I70: =+G70-C70 -> 0 | J70: =+H70-D70 -> -1.0781391e+09
A71: 2361120 | B71: ອາກອນມູນຄ່າເພີ່ມທີ່ຕ້ອງມອບ | C71: 9.5367432e-07 | D71: 0 | E71: 17025926 | F71: 198228696 | G71: 0 | H71: 1.8120277e+08 | I71: =+G71-C71 -> -9.5367432e-07 | J71: =+H71-D71 -> 1.8120277e+08
A72: 2361130 | B72: ພາສີ ແລະອາກອນຕ່າງໆ ທີ່ຫັກໄວ້ຕ້ອງສົ່ງມອບ | C72: 0 | D72: 1.3973847e+08 | E72: 1.5905745e+08 | F72: 19318977 | G72: 0 | H72: 0 | I72: =+G72-C72 -> 0 | J72: =+H72-D72 -> -1.3973847e+08
A73: 2361140 | B73: ອາກອນເງິນເດືອນຕ້ອງສົ່ງມອບ | C73: 0 | D73: 31417800 | E73: 261832047 | F73: 2.665039e+08 | G73: 0 | H73: 36089656 | I73: =+G73-C73 -> 0 | J73: =+H73-D73 -> 4671856.1
A74: 2361410 | B74: ຄ່າບໍລິການຄ້າງຈ່າຍ | C74: 0 | D74: 1.2909898e+08 | E74: 5.5032454e+08 | F74: 4.8447556e+08 | G74: 0 | H74: 63250000 | I74: =+G74-C74 -> 0 | J74: =+H74-D74 -> -65848980
A75: 2361420 | B75: ຄ່າ terminal LSX ຄ້າງຈ່າຍ | C75: 0 | D75: 21286512 | E75: 251382807 | F75: 2.51487e+08 | G75: 0 | H75: 21390700 | I75: =+G75-C75 -> 0 | J75: =+H75-D75 -> 104188.5
A76: 2361430 | B76: ຄ່າ Displayer LSX ຄ້າງຈ່າຍ | C76: 0 | D76: 2581632 | E76: 30487752 | F76: 30500388 | G76: 0 | H76: 2594268 | I76: =+G76-C76 -> 0 | J76: =+H76-D76 -> 12636
A77: 2361440 | B77: ຄ່າໃຊ້ຈ່າຍຄ້າງຈ່າຍອື່ນໆ | C77: 0 | D77: 3.7545304e+08 | E77: 7.8377782e+08 | F77: 6.6162555e+08 | G77: 0 | H77: 2.5330076e+08 | I77: =+G77-C77 -> 0 | J77: =+H77-D77 -> -1.2215228e+08
A78: 2361830 | B78: ຄ່າໄຟຟ້າ ແລະນ້ຳປະປາຄ້າງຈ່າຍ | C78: 0 | D78: 0 | E78: 0 | F78: 0 | G78: 0 | H78: 0 | I78: =+G78-C78 -> 0 | J78: =+H78-D78 -> 0
A79: 2361831 | B79: ຄ່າໄຟຟ້າຄ້າງຈ່າຍ | C79: 0 | D79: 7239040 | E79: 79814131 | F79: 86815301 | G79: 0 | H79: 14240210 | I79: =+G79-C79 -> 0 | J79: =+H79-D79 -> 7001170 | K79: =+SUM(J71:J79) -> -1.3474711e+08
A80: 2363682 | B80: ບັນຊີເຈົ້າໜີ້ KTZmico Co.,Ltd | C80: 0 | D80: 2.9070674e+08 | E80: 3.7809623e+08 | F80: 1.3361548e+09 | G80: 0 | H80: 1.2487653e+09 | I80: =+G80-C80 -> 0 | J80: =+H80-D80 -> 9.5805852e+08
A81: 2363683 | B81: ບັນຊີເຈົ້າໜີ້ BCEL | C81: 0 | D81: 0 | E81: 0 | F81: 0 | G81: 0 | H81: 0 | I81: =+G81-C81 -> 0 | J81: =+H81-D81 -> 0
A82: 2363684 | B82: ບັນຊີເຈົ້າໜີ້ອື່ນໆ | C82: 0 | D82: 27040033 | E82: 27040033 | F82: 0 | G82: 0 | H82: 0 | I82: =+G82-C82 -> 0 | J82: =+H82-D82 -> -27040033 | K82: =+SUM(J80:J82) -> 9.3101849e+08
A83: 3108210 | B83: ທຶນຈົດທະບຽນທີ່ຖອກແລ້ວ | C83: 0 | D83: 100000000000 | E83: 0 | F83: 0 | G83: 0 | H83: 100000000000 | I83: =+G83-C83 -> 0 | J83: =+H83-D83 -> 0
A84: 3202000 | B84: ຄັງສຳຮອງຕາມກົດໝາຍ | C84: 0 | D84: 0 | E84: 0 | F84: 7.0703648e+08 | G84: 0 | H84: 7.0703648e+08 | I84: =+G84-C84 -> 0 | J84: =+H84-D84 -> 7.0703648e+08
A85: 3810000 | B85: ກຳໄລ-ຂາດທຶນສະສົມ | C85: 0 | D85: 1.9182372e+08 | E85: 0 | F85: 3.837217e+09 | G85: 0 | H85: 4.0290408e+09 | I85: =+G85-C85 -> 0 | J85: =+H85-D85 -> 3.837217e+09
A86: 3901000 | B86: ກຳໄລ-ຂາດ ທຶນໃນປີ | C86: 0 | D86: 3.7642156e+09 | E86: 4.0912641e+09 | F86: 0 | G86: 3.2704856e+08 | H86: 0 | I86: =+G86-C86 -> 3.2704856e+08 | J86: =+H86-D86 -> -3.7642156e+09
A87: 3908000 | B87: ຜົນໄດ້ຮັບ ລໍຖ້າຮັບຮອງ | C87: 0 | D87: 0 | E87: 4.217205e+09 | F87: 4.217205e+09 | G87: 0 | H87: 0 | I87: =+G87-C87 -> 0 | J87: =+H87-D87 -> 0 | K87: =+SUM(J83:J87)-SUM(I83:I87) -> 4.5298941e+08 | L87: OK
C88: =SUM(C5:C87) -> 1.6298527e+11 | D88: =SUM(D5:D87) -> 1.6298527e+11 | E88: =SUM(E5:E87) -> 1.21161e+12 | F88: =SUM(F5:F87) -> 1.2083395e+12 | G88: =SUM(G5:G87) -> 1.8430485e+11 | H88: =SUM(H5:H87) -> 1.8103437e+11 | I88: =SUM(I5:I87) -> 2.1319581e+10 | J88: =SUM(J5:J87) -> 1.8049095e+10
D89: =+C88-D88 -> 0 | F89: =+E88-F88 -> 3.2704856e+09 | H89: =+G88-H88 -> 3.2704856e+09 | I89: =+I88-J88 -> 3.2704856e+09 | K89: OK
E94: Movement for the year 2013
A95: 4102730 | B95: ຄ່າບໍລິການເຊົ່າລະບົບເທີມີນໍ່ LSX | C95: 0 | D95: 0 | E95: 251317842 | F95: 414558 | G95: 250903284 | H95: 0 | I95: =+F95-E95 -> -250903284
A96: 4102731 | B96: ຄ່າບໍລິການເຊົ່າລະບົບດິດສເປຣເຢີ່ LSX | C96: 0 | D96: 0 | E96: 30430080 | F96: 0 | G96: 30430080 | H96: 0 | I96: =+F96-E96 -> -30430080
A97: 4108210 | B97: ຄ່າທຳນຽມທະນາຄານ ( ຈ່າຍ ) | C97: 0 | D97: 0 | E97: 3520376.9 | F97: 0 | G97: 3520376.9 | H97: 0 | I97: =+F97-E97 -> -3520376.9
A98: 4201100 | B98: ເງິນເດືອນພະນັກງານໃນການຈັດຕັ້ງ | C98: 0 | D98: 0 | E98: 2160359677 | F98: 0 | G98: 2160359677 | H98: 0 | I98: =+F98-E98 -> -2160359677
A99: 4201400 | B99: ເງິນເພີ່ມໂມງ | C99: 0 | D99: 0 | E99: 68587567 | F99: 0 | G99: 68587567 | H99: 0 | I99: =+F99-E99 -> -68587567
A100: 4202200 | B100: ລາຍຈ່າຍຄ່າປະກັນໄພພະນັກງານ | C100: 0 | D100: 0 | E100: 1.177451e+08 | F100: 0 | G100: 1.177451e+08 | H100: 0 | I100: =+F100-E100 -> -1.177451e+08
A101: 4202210 | B101: ລາຍຈ່າຍຄ່າຮັກສາພະຍາບານ | C101: 0 | D101: 0 | E101: 4652000 | F101: 0 | G101: 4652000 | H101: 0 | I101: =+F101-E101 -> -4652000
A102: 4202220 | B102: ລາຍຈ່າຍຄ່ານ້ຳມັນລົດພະນັກງານ | C102: 0 | D102: 0 | E102: 208083871 | F102: 0 | G102: 208083871 | H102: 0 | I102: =+F102-E102 -> -208083871
A103: 4202800 | B103: ລາຍຈ່າຍສະຫວັດດີການພະນັກງານອື່ນໆ | C103: 0 | D103: 0 | E103: 107000000 | F103: 0 | G103: 107000000 | H103: 0 | I103: =+F103-E103 -> -107000000
A104: 4202811 | B104: ລາຍຈ່າຍເບ້ຍປະຊູມສະພາບໍລິຫານ | C104: 0 | D104: 0 | E104: 51105263 | F104: 0 | G104: 51105263 | H104: 0 | I104: =+F104-E104 -> -51105263
A105: 4203100 | B105: ສຳມະນາ ແລະຝຶກອົບຮົມພາຍໃນປະເທດ | C105: 0 | D105: 0 | E105: 77527320 | F105: 0 | G105: 77527320 | H105: 0 | I105: =+F105-E105 -> -77527320
A106: 4208300 | B106: ຄ່າໃຊ້ຈ່າຍໃນການຈັດກິດຈະກຳພະນັກງານ | C106: 0 | D106: 0 | E106: 7149000 | F106: 0 | G106: 7149000 | H106: 0 | I106: =+F106-E106 -> -7149000
... A173: 5508400 | B173: ລາຍຮັບອື່ນໆ | C173: 0 | D173: 0 | E173: 30 | F173: 34718848 | G173: 0 | H173: 34718818 | I173: =+F173-E173 -> 34718818
A174: Total Expense + Income | C174: =SUM(C95:C173) -> 0 | D174: =SUM(D95:D173) -> 0 | E174: =SUM(E95:E173) -> 1.1540733e+10 | F174: =SUM(F95:F173) -> 1.4811219e+10 | G174: =SUM(G95:G173) -> 8.2463067e+09 | H174: =SUM(H95:H173) -> 1.1516792e+10
A175: Net Prfit for the year end 31.12.2013 | F175: =+F174-E174 -> 3.2704856e+09 | H175: =+H174-G174 -> 3.2704856e+09 | I175: =SUM(I95:I173) -> 3.2704856e+09
A178: ລວມມູນຄ່າ | C178: 1.6298527e+11 | D178: 1.6298527e+11 | E178: 1.2231507e+12 | F178: 1.2231507e+12 | G178: 1.9255116e+11 | H178: 1.9255116e+11
I179: =SUM(I95:I173) -> 3.2704856e+09 | J179: OK
...

Sheet C&E.2013
A1: ສາທາລະນະລັດ ປະຊາທິປະໄຕ ປະຊາຊົນລາວ
A2: ສັນຕິພາບ ເອກະລາດ ປະຊາທິປະໄຕ ເອກະພາບ ວັດທະນາຖາວອນ
A4: ໃບລາຍງານສ່ວນປ່ຽນແປງທຶນ
A5: ປະຈຳເດືອນ: 12/2013
A6: ບໍລິສັດຫຼັກຊັບ ທຄຕລ-ກທ ຈຳກັດ_x000D_ ຊັ້ນ7, ຕຶກຕະຫຼາກຫຼັກຊັບລາວ, ຖະໜົນກຳແພງເມືອງ_x000D_ +856-21-265477+856-21-265488 | G6: ບັນຊີ 3202000 ຂອງ ປີ N-2
A9: ເນື້ອໃນລາຍການ | B9: ເອກະສານຊ້ອນທ້າຍ | C9: ທຶນຈົດທະບຽນ | D9: ຄັງສຳຮອງຕາມກົດໝາຍ | E9: ຄັງສະສົມ ທົ່ວໄປ | F9: ກຳໄລ-ຂາດ ທຶນສະສົມ | G9: ລວມທຶນ ຕົນເອງ
A12: 1.- ຍອດເຫຼືອຕົ້ນປີ N-1 ( ປີກ່ອນ ) | C12: =+'TB for 2013'!D83 -> 100000000000 | D12: + | E12: +/- | F12: =+'TB for 2013'!H85 -> 4.0290408e+09 | G12: =+SUM(C12:F12) -> 1.0402904e+11
A13: # ການເຄື່ອນໄຫວປ່ຽນແປງທີ່ເກີດຂື້ນ ໃນປີ N-1 :
A14: - ຈ່າຍເງິນປັນຜົນສຳຫຼັບ ປີ N-2 | F14: - | G14: =+SUM(F14) -> 0
A15: - ໂອນກຳໄລສຸດທິ ປີ N-2 ເຂົ້າຄັງສຳຮອງຕາມກົດໝາຍ | D15: + | F15: =+D15 -> +
A16: - ໂອນກຳໄລສຸດທິ ປີ N-2 ເຂົ້າຄັງທົ່ວໄປ | B16: xxx | E16: + | F16: =+E16 -> +
A17: - ທຶນຈົດທະບຽນ ທີ່ໄດ້ຮັບ | C17: + | G17: =+C17 -> +
A18: - ກຳໄລ/ຂາດທຶນໃນປີ | F18: =+[1]Sheet1!$H$76 -> 3.7998793e+09 | H18: ບັນຊີ 3908000
A19: 2.- ຍອດເຫຼືອທ້າຍປີ N-1 | C19: =+SUM(C12:C18) -> 100000000000 | D19: =+SUM(D12:D18) -> 0 | E19: =+SUM(E12:E18) -> 0 | F19: =SUM(F12:F18) -> 7.82892e+09 | G19: =+SUM(C19:F19) -> 1.0782892e+11
A20: 3.- ຍອດເຫຼືອຕົ້ນປີ N - ( ປີນີ້ )
A21: - ຍອດຍົກມາຈາກທ້າຍປີ N-1 ( ປີກ່ອນ ) | C21: =+C19 -> 100000000000 | D21: =+D19 -> 0 | E21: =+E19 -> 0 | F21: =+F19 -> 7.82892e+09 | G21: =+SUM(C21:F21) -> 1.0782892e+11
A22: - ຜົນກະທົບຈາກອັດຕາແລກປ່ຽນເງິນຕາຕ່າງປະເທດ | C22: 0 | D22: 0 | E22: 0 | F22: 0 | G22: =+SUM(C22:F22) -> 0
A23: ຍອດເຫຼືອຕົ້ນປີ N ຫຼັງການດັດປັບອັດຕາແລກປ່ຽນ | C23: =+C21+C22 -> 100000000000 | D23: =+D21+D22 -> 0 | E23: =+E21+E22 -> 0 | F23: =+F21+F22 -> 7.82892e+09 | G23: =+G21+G22 -> 1.0782892e+11
A24: ການເຄື່ອນໄຫວປ່ຽນແປງທີ່ເກີດຂຶ້ນໃນປີ N :
A25: - ຈ່າຍເງິນປັນຜົນສຳຫຼັບປີ N-1 | F25: - | G25: -
A26: - ໂອນກຳໄລສຸດທິເຂົ້າຄັງສຳຮອງຕາມກົດໝາຍ | D26: 379987925 | F26: =-D26 -> -379987925 | H26: ບັນຊີ 3202000 ຂອງ ປີ N-1
A27: - ໂອນກຳໄລສຸດທິເຂົ້າຄັງສຳຮອງທົ່ວໄປ | B27: xxx | E27: + | F27: -
A28: - ທຶນຈົດທະບຽນທີ່ໄດ້ຮັບ | C28: + | G28: =+C28 -> +
A29: - ກຳໄລ/ຂາດທຶນໃນປີ | F29: =+[2]Sheet1!$F$94 -> 8.6109995e+08 | H29: ບັນຊີ 5-4 ( ຮັບ-ຈ່າຍ) ຫຼື ບັນຊີ 3901000, ແຕ່ບັນຊີ 3901000 ຈະເກີດຂື້ນໃນເວລາທ້າຍປີ ( ສະເໜີເອົາ 5-4 ເດີ )
A30: 4.- ຍອດເຫຼືອທ້າຍປີ N ( ປີນີ້ ) | C30: =+SUM(C23:C29) -> 100000000000 | D30: =+SUM(D23:D29) -> 379987925 | E30: =+SUM(E23:E29) -> 0 | F30: =+SUM(F23:F29) -> 8.310032e+09 | G30: =SUM(C30:F30) -> 1.0869002e+11
F32: ນະຄອນຫຼວງວຽງຈັນ ວັນທີ : …../….../......... ,
A34: ຜູ້ອຳນວຍການ | B34: ຫົວໜ້າພະແນກກວດກາ | D34: ຫົວໜ້າພະແນກບັນຊີ | F34: ຜູ້ສັງລວມ
A41: 3108210 | B41: ທຶນຈົດທະບຽນທີ່ຖອກແລ້ວ | G41: 0 | H41: 100000000000
A42: 3810000 | B42: ກຳໄລ-ຂາດທຶນສະສົມ | G42: 0 | H42: 1.9182372e+08
A43: 3901000 | B43: ກຳໄລ-ຂາດ ທຶນໃນປີ | G43: 0 | H43: 0
A44: 3908000 | B44: ຜົນໄດ້ຮັບ ລໍຖ້າຮັບຮອງ | G44: 0 | H44: 3.7998793e+09
H45: =SUM(H41:H44) -> 1.039917e+11
