Workbook

Sheet Sheet1
A1: ໂລໂກ້ | G1: Logo Company
A2: ບໍລິສັດ………….. | G2: BCEL-KT Securities Co.,Ltd
A3: ເບີໂທ..……………. | G3: Tel: , Fax:
B4: ໃບລາຍງານກະແສເງິນສົດ | H4: Cash flow statment
B5: ປະຈຳປີ............... | H5: Yearly:...............
B6: ຫົວໜ່ວຍ: 1.000.000ກີບ | H6: Unit: 1.000.000 Lak
A7: ລຳດັບ | B7: ລາຍການ | C7: ເອກະສານຊ້ອນທ້າຍ | D7: ຈຳນວນເງິນ | G7: No | H7: Descriptions | I7: Note | J7: Amount
D8: ປີນີ້ | E8: ປີກ່ອນ | J8: This Year | K8: Last Year
A9: I | B9: ກະແສເງິນສົດຈາກກິດຈະກຳການດຳເນີນງານ | G9: I | H9: Cash flows from operating activities
B10: 1. ​ກໍາໄລ ຫຼື ຂາດທຶນສຸດທິກ່ອນອາກອນ | D10: 0 | E10: 0 | H10: 1. ​Net profit before tax for the period | J10: 0 | K10: 0
B11: 2. ລາຍການປັບປຸງຍອດກຳໄລ ຫຼື ຍອດຂາດທຶນເປັນເງິນສົດຮັບ-ຈ່າຍ | D11: =+D12+D13+D14+D15+D16+D17 -> 0 | E11: =+E12+E13+E14+E15+E16+E17 -> 0 | H11: 2. Adjustments to reconcile net profit to | J11: =+J12+J13+J14+J15+J16+J17 -> 0 | K11: =+K12+K13+K14+K15+K16+K17 -> 0
B12: 2.1. ຄ່າຫຼຸ້ຍຫ້ຽນ ແລະ ຄ່າເສື່ອມມູນຄ່າສຸດທິຂອງຊັບສົມບັດຄົງທີ່ມີຕົວຕົນ ແລະ ບໍ່ມີຕົວຕົນ | D12: 0 | E12: 0 | H12: 2.1. Depreciation | J12: 0 | K12: 0
B13: 2.2. ຄ່າເສື່ອມມູນຄ່າສຸດທິຂອງເງິນລົງທຶນໃນຫຼັກຊັບ ແລະ ລາຍການອື່ນໆ | D13: 0 | E13: 0 | H13: 2.2. Amortization | J13: 0 | K13: 0
B14: 2.3. ຂາດທຶນຈາກການຂາຍຊັບສົມບັດຄົງທີ່ | D14: 0 | E14: 0 | H14: 2.3. Loss on Disposal | J14: 0 | K14: 0
B15: 2.4. ກຳໄລຈາກການຂາຍຊັບສົມບັດຄົງທີ່ | D15: 0 | E15: 0 | H15: 2.4. Gain on Disposal | J15: 0 | K15: 0
B16: 2.5. ສ່ວນປ່ຽນແປງໃນລາຍການດອກເບ້ຍ ແລະ ລາຍຮັບອື່ນໆຄ້າງຮັບ | D16: 0 | E16: 0 | H16: 2.5. Unrealized (gain) loss on investment | J16: 0 | K16: 0
B17: 2.6. ສ່ວນປ່ຽນແປງໃນລາຍການດອກເບ້ຍ ແລະ ລາຍຈ່າຍອື່ນໆຄ້າງຈ່າຍ | D17: 0 | E17: 0 | H17: 2.6. Unrealized gain(loss) on exchange rate | J17: 0 | K17: 0
B18: ກ. ກະແສເງິນສົດສຸດທິຈາກກິດຈະກຳການດຳເນີນງານກ່ອນການປ່ຽນແປງໃນລາຍການຊັບສິນ ແລະ ໜີ້ສິນໝູນວຽນ | D18: =+D10+D11 -> 0 | E18: =+E10+E11 -> 0 | H18: A. Net loss from operating activities before changes in operating assets and liabilities | J18: =+J10+J11 -> 0 | K18: =+K10+K11 -> 0
B19: 3. ການປ່ຽນແປງ(ເພີ່ມຂຶ້ນ ຫຼື ຫຼຸດລົງ) ໃນລາຍການຊັບສິນໝູນວຽນ | D19: =+D20+D21+D22+D23+D24+D25+D26+D27 -> 0 | E19: =+E20+E21+E22+E23+E24+E25+E26+E27 -> 0 | H19: 3. Increase/Decrease in operating assets:- | J19: =+J20+J21+J22+J23+J24+J25+J26+J27 -> 0 | K19: =+K20+K21+K22+K23+K24+K25+K26+K27 -> 0
B20: 3.1. ເງິນຝາກທະນາຄານ ແລະ ສະຖາບັນການເງິນ | D20: 0 | E20: 0 | H20: 3.1. Deposit with banks and financial institutions | J20: 0 | K20: 0
B21: 3.2. ເງິນລົງທຶນໄລຍະສັ້ນ | D21: 0 | E21: 0 | H21: 3.2. Shorterm Investement "Investment in securities" | J21: 0 | K21: 0
B22: 3.3. ໜີ້ຕ້ອງຮັບທາງການຄ້າ | D22: 0 | E22: 0 | H22: 3.3. A/R on business | J22: 0 | K22: 0
B23: 3.4. ໜີ້ຕ້ອງຮັບທາງທຸລະກຳຫຼັກຊັບ | D23: 0 | E23: 0 | H23: 3.4. A/R Securities on Business | J23: 0 | K23: 0
B24: 3.5. ໜີ້ຕ້ອງຮັບລະຫວ່າງບໍລິສັດໃນກຸ່ມ | D24: 0 | E24: 0 | H24: 3.5. A/R clearing house | J24: 0 | K24: 0
B25: 3.6. ໜີ້ຕ້ອງຮັບອື່ນໆ | D25: 0 | E25: 0 | H25: 3.6. Other account receivable | J25: 0 | K25: 0
B26: 3.7. ເຄື່ອງໃນສາງ | D26: 0 | E26: 0 | H26: 3.7. Inventory | J26: 0 | K26: 0
B27: 3.8. ຊັບສິນໝູນວຽນອື່ນໆ | D27: 0 | E27: 0 | H27: 3.8. Other current assets | J27: 0 | K27: 0
B28: ຂ. ກະແສເງິນສົດສຸດທິຈາກການປ່ຽນແປງໃນຊັບສິນໝູນວຽນ | D28: =+D19 -> 0 | E28: =+E19 -> 0 | H28: B. Net Cash flow statement in operating assets | J28: =+J19 -> 0 | K28: =+K19 -> 0
B29: 4. ການປ່ຽນແປງ(ເພີ່ມຂຶ້ນ ຫຼື ຫຼຸດລົງ) ໃນລາຍການໜີ້ສິນໝູນວຽນ | D29: =+D30+D31+D32+D33+D34+D35 -> 0 | E29: =+E30+E31+E32+E33+E34+E35 -> 0 | H29: 4. Increase/Decrease in operating liabilities:- | J29: =+J30+J31+J32+J33+J34+J35 -> 0 | K29: =+K30+K31+K32+K33+K34+K35 -> 0
B30: 4.1. ໜີ້ຕ້ອງສົ່ງທາງການຄ້າ | D30: 0 | E30: 0 | H30: 4.1. A/P on business | J30: 0 | K30: 0
B31: 4.2. ໜີ້ຕ້ອງສົ່ງທາງທຸລະກຳຫຼັກຊັບ | D31: 0 | E31: 0 | H31: 4.2. A/P Securities on Business | J31: 0 | K31: 0
B32: 4.3. ໜີ້ຕ້ອງສົ່ງລະຫວ່າງບໍລິສັດໃນກຸ່ມ | D32: 0 | E32: 0 | H32: 4.3. A/R clearing house | J32: 0 | K32: 0
B33: 4.4. ອາກອນກຳໄລຄ້າງຈ່າຍ | D33: 0 | E33: 0 | H33: 4.4. Accrued corporate income tax | J33: 0 | K33: 0
B34: 4.5. ໜີ້ຕ້ອງສົ່ງອື່ນໆ | D34: 0 | E34: 0 | H34: 4.5. Other liabilities | J34: 0 | K34: 0
B35: 4.6. ໜີ້ສິນໝູນວຽນອື່ນໆ | D35: 0 | E35: 0 | H35: 4.6. Subscription payable | J35: 0 | K35: 0
B36: ຄ. ກະແສເງິນສົດສຸດທິຈາກການປ່ຽນແປງໃນໜີ້ສິນໝູນວຽນ | D36: =+D29 -> 0 | E36: =+E29 -> 0 | H36: C. Net Cash flow statement in operating Liabilities | J36: =+J29 -> 0 | K36: =+K29 -> 0
B37: ກະແສເງິນສົດສຸດທິຈາກກິດຈະກຳດຳເນີນງານ | D37: =+D18+D28+D36 -> 0 | E37: =+E18+E28+E36 -> 0 | H37: Net Cash flows from operating activities | J37: =+J18+J28+J36 -> 0 | K37: =+K18+K28+K36 -> 0
A38: II | B38: ​ກະແສເງິນສົດຈາກກິດຈະກໍາລົງທຶນ | G38: II | H38: Cash flows from investing activities
B39: 1. ສ່ວນເພີ່ມຫຼືຫຼຸດໃນລາຍການເງິນລົງທຶນໄລຍະຍາວ | D39: 0 | E39: 0 | H39: 1. Increase/Decrease on long term investment | J39: 0 | K39: 0
B40: 2. ສ່ວນເພີ່ມຫຼືຫຼຸດໃນລາຍໜີ້ຕ້ອງຮັບໄລຍະຍາວ ແລະ ຊັບສິນໄລຍະຍາວອື່ນໆ | D40: 0 | E40: 0 | H40: 2. Increase/Decrease A/R and other assets on long term investment | J40: 0 | K40: 0
B41: 3. ສ່ວນເພີ່ມຫຼືຫຼຸດໃນລາຍການຊັບສົມບັດຄົງທີ່ | D41: 0 | E41: 0 | H41: 3. Increase/Decrease of fix assets | J41: 0 | K41: 0
B42: ກະແສເງິນສົດສຸດທິຈາກກິດຈະກຳລົງທຶນ | D42: =+SUM(D39:D41) -> 0 | E42: =+SUM(E39:E41) -> 0 | H42: Net cash flows used in investing activities | J42: =+SUM(J39:J41) -> 0 | K42: =+SUM(K39:K41) -> 0
A43: III | B43: ກະແສເງິນສົດຈາກກິດຈະກຳຈັດຫາເງິນ | G43: III | H43: Cash flows from financing activities
B44: 1. ສ່ວນເພີ່ມຫຼືຫຼຸດໃນລາຍການເງິນກູ້ຢືມມາ ແລະ ໜີ້ຕ້ອງສົ່ງໄລຍະຍາວອື່ນໆ | D44: 0 | E44: 0 | H44: 1. Increase/Decrease on loan and other long term liabilities | J44: 0 | K44: 0
B45: 2. ສ່ວນເພີ່ມຫຼືຫຼຸດໃນການອອກຮຸ້ນ | D45: 0 | E45: 0 | H45: 2. Proceeds from issue of ordinary shares | J45: 0 | K45: 0
B46: 3. ທຶນປະກອບທີ່ໄດ້ຮັບໃນປີ | D46: 0 | E46: 0 | H46: 3. Proceeds from paid-up of ordinary shares | J46: 0 | K46: 0
B47: 4. ຈ່າຍເງິນປັນຜົນ | D47: 0 | E47: 0 | H47: 4. Paid dividend | J47: 0 | K47: 0
B48: ກະແສເງິນສົດສຸດທິຈາກກິດຈະກຳຈັດຫາເງິນ | D48: =+SUM(D44:D47) -> 0 | E48: =+SUM(E44:E47) -> 0 | H48: Net cash flow provided by financing activities | J48: =+SUM(J44:J47) -> 0 | K48: =+SUM(K44:K47) -> 0
A49: IV | B49: ເງິນສົດ ແລະ ທຽບເທົ່າເງິນສົດ | G49: IV | H49: Cash and cash equivalents
B50: ເງິນສົດ ແລະ ທຽບເທົ່າເງິນສົດເພີ່ມຂຶ້ນ ຫຼື ຫຼຸດລົງສຸດທິໃນປີ | D50: =+D37+D42+D48 -> 0 | E50: =+E37+E42+E48 -> 0 | H50: Net increase in cash and cash equivalents for the year | J50: =+J37+J42+J48 -> 0 | K50: =+K37+K42+K48 -> 0
B51: ເງິນສົດ ແລະ ທຽບເທົ່າເງິນສົດຍັງເຫຼືອທ້າຍປີກ່ອນ | D51: 0 | E51: 0 | H51: Cash and cash equivalents at beginning of the year | J51: 0 | K51: 0
B52: ເງິນສົດ ແລະ ທຽບເທົ່າເງິນສົດຍັງເຫຼືອທ້າຍປີນີ້ | D52: =+SUM(D50:D51) -> 0 | E52: =+SUM(E50:E51) -> 0 | H52: Cash and cash equivalents at end of the year | J52: =+SUM(J50:J51) -> 0 | K52: =+SUM(K50:K51) -> 0
D54: ວັນທີ .. ../… ./2013 | J54: Vientiane, Date: / /2013
A55: ຜູ້ອຳນວຍການ ທີ່ປຶກສາບັນຊີ ຫົວໜ້າພະແນກບັນຊີ ຜູ້ສັງລວມ | G55: General Manager Consultant Chief of account | J55: Accounting:
H72: 2.1. ຄ່າຫຼຸ້ຍຫ້ຽນ ແລະ ຄ່າເສື່ອມມູນຄ່າສຸດທິຂອງຊັບສົມບັດຄົງທີ່ມີຕົວຕົນ ແລະ ບໍ່ມີຕົວຕົນ
H73: 2.2. ຄ່າເສື່ອມມູນຄ່າສຸດທິຂອງເງິນລົງທຶນໃນຫຼັກຊັບ ແລະ ລາຍການອື່ນໆ
H74: 2.3. ຂາດທຶນຈາກການຂາຍຊັບສົມບັດຄົງທີ່
H75: 2.4. ກຳໄລຈາກການຂາຍຊັບສົມບັດຄົງທີ່

Sheet Sheet2
A1: ໂລໂກ້
A2: ບໍລິສັດ…………..
A3: ເບີໂທ..…………….
B4: ໃບລາຍງານກະແສເງິນສົດ
B5: ປະຈຳປີ...............
B6: ຫົວໜ່ວຍ: 1.000.000ກີບ
A7: ລຳດັບ | B7: ລາຍການ
B8: ລາຍການ | C8: ເຄື່ອງໝາຍ | D8: ເລກບັນຊີ
A9: I | B9: ກະແສເງິນສົດຈາກກິດຈະກຳການດຳເນີນງານ
B10: 1. ​ກໍາໄລ ຫຼື ຂາດທຶນສຸດທິກ່ອນອາກອນ | D10: ຍອດເຫຼືອບັນຊີ 3901
B11: 2. ລາຍການປັບປຸງຍອດກຳໄລ ຫຼື ຍອດຂາດທຶນເປັນເງິນສົດຮັບ-ຈ່າຍ
B12: 2.1. ຄ່າຫຼຸ້ຍຫ້ຽນ ແລະ ຄ່າເສື່ອມມູນຄ່າສຸດທິຂອງຊັບສົມບັດຄົງທີ່ມີຕົວຕົນ ແລະ ບໍ່ມີຕົວຕົນ | C12: +/- | D12: ບ/ຊ 148
B13: 2.2. ຄ່າເສື່ອມມູນຄ່າສຸດທິຂອງເງິນລົງທຶນໃນຫຼັກຊັບ ແລະ ລາຍການອື່ນໆ | C13: +/- | D13: ບ/ຊ 1319+1419+1199111+1199121+1199131+1199141+1199211+1199231+1199241+
D14: 1299111+1299121+1299131+1299141+1299211+1299221+1299231+1199241+1199112+
D15: 1199113+1199122+1199123+1199132+1199133+1199142+1199143+1199212+1199213+
D16: 1199222+1199223+1199232+1199233+1199242+1199243+1299112+1299113+1299122+
D17: 1299123+1299132+1299133+1299142+1299143+1299212+1299222+1299232+1299142
B18: 2.3. ຂາດທຶນຈາກການຂາຍຊັບສົມບັດຄົງທີ່ | C18: + | D18: ບ/ຊ 4506+410416
B19: 2.4. ກຳໄລຈາກການຂາຍຊັບສົມບັດຄົງທີ່ | C19: - | D19: ບ/ຊ 5506+510416+510426
B20: 2.5. ສ່ວນປ່ຽນແປງໃນລາຍການດອກເບ້ຍ ແລະ ລາຍຮັບອື່ນໆຄ້າງຮັບ | D20: What account No ??????? | E20: None
B21: 2.6. ສ່ວນປ່ຽນແປງໃນລາຍການດອກເບ້ຍ ແລະ ລາຍຈ່າຍອື່ນໆຄ້າງຈ່າຍ | D21: What account No ??????? | E21: None
B22: ກ. ກະແສເງິນສົດສຸດທິຈາກກິດຈະກຳການດຳເນີນງານກ່ອນການປ່ຽນແປງໃນລາຍການຊັບສິນ ແລະ ໜີ້ສິນໝູນວຽນ | D22: ກ=3(Item 3.1 to Item 3.8)
B24: 3. ການປ່ຽນແປງ(ເພີ່ມຂຶ້ນ ຫຼື ຫຼຸດລົງ) ໃນລາຍການຊັບສິນໝູນວຽນ
B25: 3.1. ເງິນຝາກທະນາຄານ ແລະ ສະຖາບັນການເງິນ | C25: -/+ | D25: ບ/ຊ 1121+1131+1122
B26: 3.2. ເງິນລົງທຶນໄລຍະສັ້ນ | C26: -/+ | D26: ບ/ຊ 13011+13021+13025+13026+(130311-130391)+(130312-130392)+130351+130352+1311
B27: 3.3. ໜີ້ຕ້ອງຮັບທາງການຄ້າ | C27: -/+ | D27: ບ/ຊ 12011
B28: 3.4. ໜີ້ຕ້ອງຮັບທາງທຸລະກຳຫຼັກຊັບ | C28: -/+ | D28: ບ/ຊ 120611+12311+123151+1241+1261
B29: 3.5. ໜີ້ຕ້ອງຮັບລະຫວ່າງບໍລິສັດໃນກຸ່ມ | C29: -/+ | D29: ບ/ຊ 12111+121121
B30: 3.6. ໜີ້ຕ້ອງຮັບອື່ນໆ | C30: -/+ | D30: ບ/ຊ 113211+1132121+113221+1132221+119111+119121+119131+119141+119211+
D31: 119221+119231+119241+1207+129111+12921+129131+129141+129211+129221+129231+
D32: 129241
B33: 3.7. ເຄື່ອງໃນສາງ | C33: -/+ | D33: ບ/ຊ 1371+1373+1376+1378-1379
B34: 3.8. ຊັບສິນໝູນວຽນອື່ນໆ | C34: -/+ | D34: ບ/ຊ 1361+1362+138+1138
B35: ຂ. ກະແສເງິນສົດສຸດທິຈາກການປ່ຽນແປງໃນຊັບສິນໝູນວຽນ
B36: 4. ການປ່ຽນແປງ(ເພີ່ມຂຶ້ນ ຫຼື ຫຼຸດລົງ) ໃນລາຍການໜີ້ສິນໝູນວຽນ
B37: 4.1. ໜີ້ຕ້ອງສົ່ງທາງການຄ້າ | C37: +/- | D37: ບ/ຊ 2127+2137+21472167+2237+2247+2267+23017+23027+23317+23327+23357+23367+
D38: 2347+2367
B39: 4.2. ໜີ້ຕ້ອງສົ່ງທາງທຸລະກຳຫຼັກຊັບ | C39: +/- | D39: ບ/ຊ 23011+23021+23022+231+23311+23321+23351+2341+2342+2343+2344+2346
B40: 4.3. ໜີ້ຕ້ອງສົ່ງລະຫວ່າງບໍລິສັດໃນກຸ່ມ | C40: + | D40: ບ/ຊ 22111+22121
B41: 4.4. ອາກອນກຳໄລຄ້າງຈ່າຍ | C41: +/- | D41: ບ/ຊ 236111
B42: 4.5. ໜີ້ຕ້ອງສົ່ງອື່ນໆ | C42: +/- | D42: ບ/ຊ 2161+2261+23361+236112+236113+236114+236118+2362
B43: 4.6. ໜີ້ສິນໝູນວຽນອື່ນໆ | C43: +/- | D43: ບ/ຊ 23612+23613+23614+23618+238+2238
B44: ຄ. ກະແສເງິນສົດສຸດທິຈາກການປ່ຽນແປງໃນໜີ້ສິນໝູນວຽນ
B45: ກະແສເງິນສົດສຸດທິຈາກກິດຈະກຳດຳເນີນງານ
A46: II | B46: ​ກະແສເງິນສົດຈາກກິດຈະກໍາລົງທຶນ
B47: 1. ສ່ວນເພີ່ມຫຼືຫຼຸດໃນລາຍການເງິນລົງທຶນໄລຍະຍາວ | C47: -/+ | D47: ບ/ຊ 1411+(130411-130491)+(130412-130492)+130451+130452+13046+1412+1413+1414+
D48: 1415
B49: 2. ສ່ວນເພີ່ມຫຼືຫຼຸດໃນລາຍໜີ້ຕ້ອງຮັບໄລຍະຍາວ ແລະ ຊັບສິນໄລຍະຍາວອື່ນໆ | C49: -/+ | D49: ບ/ຊ 121122+121123+1132122+1132123+1132222+1132223+119112+119113+119122+
D50: 119123+119132+119133+119142+119143+119212+119213+119222+119223+119232+
D51: 119233+119242+119243+120612+120613+123152+129112+129113+129122+129123+
D52: 129132+129133+129142+129143+129212+129222+129232+129242
B53: 3. ສ່ວນເພີ່ມຫຼືຫຼຸດໃນລາຍການຊັບສົມບັດຄົງທີ່ | C53: -/+ | D53: ບ/ຊ 1431+1432-1439+1441-14491+1451-14951+1442-14492+1452-144952
B54: ກະແສເງິນສົດສຸດທິຈາກກິດຈະກຳລົງທຶນ
A55: III | B55: ກະແສເງິນສົດຈາກກິດຈະກຳຈັດຫາເງິນ
B56: 1. ສ່ວນເພີ່ມຫຼືຫຼຸດໃນລາຍການເງິນກູ້ຢືມມາ ແລະ ໜີ້ຕ້ອງສົ່ງໄລຍະຍາວອື່ນໆ | C56: +/- | D56: ບ/ຊ 212211+212212+2122151+212221+212222+2122251+213211+213212+2132151+
D57: 213221+213222+2132251+2141+2142+2231+22351+2241+2122152+2122153+2122252+
D58: 2122253+2132152+2132153+2132252+2132253+221122+221123
B59: 2. ສ່ວນເພີ່ມຫຼືຫຼຸດໃນການອອກຮຸ້ນ
B60: 3. ທຶນປະກອບທີ່ໄດ້ຮັບໃນປີ | C60: +/- | D60: ບ/ຊ 3101+3103+3104+3102+3108+3201
B61: 4. ຈ່າຍເງິນປັນຜົນ
B62: ກະແສເງິນສົດສຸດທິຈາກກິດຈະກຳຈັດຫາເງິນ
A63: IV | B63: ເງິນສົດ ແລະ ທຽບເທົ່າເງິນສົດ
B64: ເງິນສົດ ແລະ ທຽບເທົ່າເງິນສົດເພີ່ມຂຶ້ນ ຫຼື ຫຼຸດລົງສຸດທິໃນປີ
B65: ເງິນສົດ ແລະ ທຽບເທົ່າເງິນສົດຍັງເຫຼືອທ້າຍປີກ່ອນ | D65: ບ/ຊ 1101+1108
B66: ເງິນສົດ ແລະ ທຽບເທົ່າເງິນສົດຍັງເຫຼືອທ້າຍປີນີ້ | D66: ບ/ຊ 1101+1108
A70: ຜູ້ອຳນວຍການ ຫົວໜ້າພະແນກກວດກາ ຫົວໜ້າພະແນກບັນຊີ ຜູ້ສັງລວມ

Sheet FinalFormwFx2
A1: ໂລໂກ້
A2: ບໍລິສັດ…………..
A3: ເບີໂທ..…………….
B4: ໃບລາຍງານກະແສເງິນສົດ
B5: ປະຈຳປີ...............
B6: ຫົວໜ່ວຍ: 1.000.000ກີບ
A7: ລຳດັບ | B7: ລາຍການ
B8: ລາຍການ | C8: ເຄື່ອງໝາຍ | D8: ເລກບັນຊີ
A9: I | B9: ກະແສເງິນສົດຈາກກິດຈະກຳການດຳເນີນງານ
B10: 1. ​ກໍາໄລ ຫຼື ຂາດທຶນສຸດທິກ່ອນອາກອນ | D10: ຍອດເຫຼືອບັນຊີ 3901
B11: 2. ລາຍການປັບປຸງຍອດກຳໄລ ຫຼື ຍອດຂາດທຶນເປັນເງິນສົດຮັບ-ຈ່າຍ
B12: 2.1. ຄ່າຫຼຸ້ຍຫ້ຽນ ແລະ ຄ່າເສື່ອມມູນຄ່າສຸດທິຂອງຊັບສົມບັດຄົງທີ່ມີຕົວຕົນ ແລະ ບໍ່ມີຕົວຕົນ | C12: +/- | D12: ບ/ຊ 148
B13: 2.2. ຄ່າເສື່ອມມູນຄ່າສຸດທິຂອງເງິນລົງທຶນໃນຫຼັກຊັບ ແລະ ລາຍການອື່ນໆ | C13: +/- | D13: ບ/ຊ 1319+1419+1199111+1199121+1199131+1199141+1199211+1199231+1199241+
D14: 1299111+1299121+1299131+1299141+1299211+1299221+1299231+1199241+1199112+
D15: 1199113+1199122+1199123+1199132+1199133+1199142+1199143+1199212+1199213+
D16: 1199222+1199223+1199232+1199233+1199242+1199243+1299112+1299113+1299122+
D17: 1299123+1299132+1299133+1299142+1299143+1299212+1299222+1299232+1299142
B18: 2.3. ຂາດທຶນຈາກການຂາຍຊັບສົມບັດຄົງທີ່ | C18: + | D18: ບ/ຊ 4506+410416
B19: 2.4. ກຳໄລຈາກການຂາຍຊັບສົມບັດຄົງທີ່ | C19: - | D19: ບ/ຊ 5506+510416+510426
B20: 2.5. ສ່ວນປ່ຽນແປງໃນລາຍການດອກເບ້ຍ ແລະ ລາຍຮັບອື່ນໆຄ້າງຮັບ
B21: 2.6. ສ່ວນປ່ຽນແປງໃນລາຍການດອກເບ້ຍ ແລະ ລາຍຈ່າຍອື່ນໆຄ້າງຈ່າຍ
B22: ກ. ກະແສເງິນສົດສຸດທິຈາກກິດຈະກຳການດຳເນີນງານກ່ອນການປ່ຽນແປງໃນລາຍການຊັບສິນ ແລະ ໜີ້ສິນໝູນວຽນ
B24: 3. ການປ່ຽນແປງ(ເພີ່ມຂຶ້ນ ຫຼື ຫຼຸດລົງ) ໃນລາຍການຊັບສິນໝູນວຽນ
B25: 3.1. ເງິນຝາກທະນາຄານ ແລະ ສະຖາບັນການເງິນ | C25: -/+ | D25: ບ/ຊ 1121+1131+1122
B26: 3.2. ເງິນລົງທຶນໄລຍະສັ້ນ | C26: -/+ | D26: ບ/ຊ 13011+13021+13025+13026+(130311-130391)+(130312-130392)+130351+130352+1311
B27: 3.3. ໜີ້ຕ້ອງຮັບທາງການຄ້າ | C27: -/+ | D27: ບ/ຊ 12011
B28: 3.4. ໜີ້ຕ້ອງຮັບທາງທຸລະກຳຫຼັກຊັບ | C28: -/+ | D28: ບ/ຊ 120611+12311+123151+1241+1261
B29: 3.5. ໜີ້ຕ້ອງຮັບລະຫວ່າງບໍລິສັດໃນກຸ່ມ | C29: -/+ | D29: ບ/ຊ 12111+121121
B30: 3.6. ໜີ້ຕ້ອງຮັບອື່ນໆ | C30: -/+ | D30: ບ/ຊ 113211+1132121+113221+1132221+119111+119121+119131+119141+119211+
D31: 119221+119231+119241+1207+129111+12921+129131+129141+129211+129221+129231+
D32: 129241
B33: 3.7. ເຄື່ອງໃນສາງ | C33: -/+ | D33: ບ/ຊ 1371+1373+1376+1378-1379
B34: 3.8. ຊັບສິນໝູນວຽນອື່ນໆ | C34: -/+ | D34: ບ/ຊ 1361+1362+138+1138+1360000 | E34: ????????????
B35: ຂ. ກະແສເງິນສົດສຸດທິຈາກການປ່ຽນແປງໃນຊັບສິນໝູນວຽນ
B36: 4. ການປ່ຽນແປງ(ເພີ່ມຂຶ້ນ ຫຼື ຫຼຸດລົງ) ໃນລາຍການໜີ້ສິນໝູນວຽນ
B37: 4.1. ໜີ້ຕ້ອງສົ່ງທາງການຄ້າ | C37: +/- | D37: ບ/ຊ 2127+2137+21472167+2237+2247+2267+23017+23027+23317+23327+23357+23367+
D38: 2347+2367
B39: 4.2. ໜີ້ຕ້ອງສົ່ງທາງທຸລະກຳຫຼັກຊັບ | C39: +/- | D39: ບ/ຊ 23011+23021+23022+231+23311+23321+23351+2341+2342+2343+2344+2346
B40: 4.3. ໜີ້ຕ້ອງສົ່ງລະຫວ່າງບໍລິສັດໃນກຸ່ມ | C40: + | D40: ບ/ຊ 22111+22121
B41: 4.4. ອາກອນກຳໄລຄ້າງຈ່າຍ | C41: +/- | D41: ບ/ຊ 236111
B42: 4.5. ໜີ້ຕ້ອງສົ່ງອື່ນໆ | C42: +/- | D42: ບ/ຊ 2161+2261+23361+236112+236113+236114+236118+2362
B43: 4.6. ໜີ້ສິນໝູນວຽນອື່ນໆ | C43: +/- | D43: ບ/ຊ 23612+23613+23614+23618+238+2238
B44: ຄ. ກະແສເງິນສົດສຸດທິຈາກການປ່ຽນແປງໃນໜີ້ສິນໝູນວຽນ
B45: ກະແສເງິນສົດສຸດທິຈາກກິດຈະກຳດຳເນີນງານ
A46: II | B46: ​ກະແສເງິນສົດຈາກກິດຈະກໍາລົງທຶນ
B47: 1. ສ່ວນເພີ່ມຫຼືຫຼຸດໃນລາຍການເງິນລົງທຶນໄລຍະຍາວ | C47: -/+ | D47: ບ/ຊ 1411+(130411-130491)+(130412-130492)+130451+130452+13046+1412+1413+1414+
D48: 1415
B49: 2. ສ່ວນເພີ່ມຫຼືຫຼຸດໃນລາຍໜີ້ຕ້ອງຮັບໄລຍະຍາວ ແລະ ຊັບສິນໄລຍະຍາວອື່ນໆ | C49: -/+ | D49: ບ/ຊ 121122+121123+1132122+1132123+1132222+1132223+119112+119113+119122+
D50: 119123+119132+119133+119142+119143+119212+119213+119222+119223+119232+
D51: 119233+119242+119243+120612+120613+123152+129112+129113+129122+129123+
D52: 129132+129133+129142+129143+129212+129222+129232+129242
B53: 3. ສ່ວນເພີ່ມຫຼືຫຼຸດໃນລາຍການຊັບສົມບັດຄົງທີ່ | C53: -/+ | D53: ບ/ຊ 1431+1432-1439+1441-14491+1451-14951+1442-14492+1452-144952
B54: ກະແສເງິນສົດສຸດທິຈາກກິດຈະກຳລົງທຶນ
A55: III | B55: ກະແສເງິນສົດຈາກກິດຈະກຳຈັດຫາເງິນ
B56: 1. ສ່ວນເພີ່ມຫຼືຫຼຸດໃນລາຍການເງິນກູ້ຢືມມາ ແລະ ໜີ້ຕ້ອງສົ່ງໄລຍະຍາວອື່ນໆ | C56: +/- | D56: ບ/ຊ 212211+212212+2122151+212221+212222+2122251+213211+213212+2132151+
D57: 213221+213222+2132251+2141+2142+2231+22351+2241+2122152+2122153+2122252+
D58: 2122253+2132152+2132153+2132252+2132253+221122+221123
B59: 2. ສ່ວນເພີ່ມຫຼືຫຼຸດໃນການອອກຮຸ້ນ
B60: 3. ທຶນປະກອບທີ່ໄດ້ຮັບໃນປີ | C60: +/- | D60: ບ/ຊ 3101+3103+3104+3102+3108+3201
B61: 4. ຈ່າຍເງິນປັນຜົນ
B62: ກະແສເງິນສົດສຸດທິຈາກກິດຈະກຳຈັດຫາເງິນ
A63: IV | B63: ເງິນສົດ ແລະ ທຽບເທົ່າເງິນສົດ
B64: ເງິນສົດ ແລະ ທຽບເທົ່າເງິນສົດເພີ່ມຂຶ້ນ ຫຼື ຫຼຸດລົງສຸດທິໃນປີ
B65: ເງິນສົດ ແລະ ທຽບເທົ່າເງິນສົດຍັງເຫຼືອທ້າຍປີກ່ອນ | D65: ບ/ຊ 1101+1108
B66: ເງິນສົດ ແລະ ທຽບເທົ່າເງິນສົດຍັງເຫຼືອທ້າຍປີນີ້ | D66: ບ/ຊ 1101+1108
A70: ຜູ້ອຳນວຍການ ຫົວໜ້າພະແນກກວດກາ ຫົວໜ້າພະແນກບັນຊີ ຜູ້ສັງລວມ

Sheet FinalForm
A1: ໂລໂກ້
A2: ບໍລິສັດ…………..
A3: ເບີໂທ..…………….
B4: ໃບລາຍງານກະແສເງິນສົດ
B5: ປະຈຳປີ: 2012 | G5: Note for A/C
B6: ຫົວໜ່ວຍ: 1.000.000ກີບ
A7: ລຳດັບ | B7: ລາຍການ | C7: ເອກະສານຊ້ອນທ້າຍ | D7: ຈຳນວນເງິນ
D8: ປີນີ້ | E8: ປີກ່ອນ
A9: I | B9: ກະແສເງິນສົດຈາກກິດຈະກຳການດຳເນີນງານ
B10: 1. ​ກໍາໄລ ຫຼື ຂາດທຶນສຸດທິກ່ອນອາກອນ | D10: =SUM('TB 2012'!J86:J172)/1000 -> 3764215.6 | E10: 0 | F10: Cr-Dr " Movement of 4-5 "+ A/C: 49
B11: 2. ລາຍການປັບປຸງຍອດກຳໄລ ຫຼື ຍອດຂາດທຶນເປັນເງິນສົດຮັບ-ຈ່າຍ | D11: =+D12+D13+D14+D15+D16+D17 -> 418699.01 | E11: =+E12+E13+E14+E15+E16+E17 -> 0
B12: 2.1. ຄ່າຫຼຸ້ຍຫ້ຽນ ແລະ ຄ່າເສື່ອມມູນຄ່າສຸດທິຂອງຊັບສົມບັດຄົງທີ່ມີຕົວຕົນ ແລະ ບໍ່ມີຕົວຕົນ | D12: =SUM('TB 2012'!J50:J56)/1000 -> 418699.01 | E12: 0 | G12: 1481
B13: 2.2. ຄ່າເສື່ອມມູນຄ່າສຸດທິຂອງເງິນລົງທຶນໃນຫຼັກຊັບ ແລະ ລາຍການອື່ນໆ | D13: 0 | E13: 0
B14: 2.3. ຂາດທຶນຈາກການຂາຍຊັບສົມບັດຄົງທີ່ | D14: 0 | E14: 0
B15: 2.4. ກຳໄລຈາກການຂາຍຊັບສົມບັດຄົງທີ່ | D15: 0 | E15: 0
B16: 2.5. ສ່ວນປ່ຽນແປງໃນລາຍການດອກເບ້ຍ ແລະ ລາຍຮັບອື່ນໆຄ້າງຮັບ | D16: 0 | E16: 0
B17: 2.6. ສ່ວນປ່ຽນແປງໃນລາຍການດອກເບ້ຍ ແລະ ລາຍຈ່າຍອື່ນໆຄ້າງຈ່າຍ | D17: 0 | E17: 0
B18: ກ. ກະແສເງິນສົດສຸດທິຈາກກິດຈະກຳການດຳເນີນງານກ່ອນການປ່ຽນແປງໃນລາຍການຊັບສິນ ແລະ ໜີ້ສິນໝູນວຽນ | D18: =+D10+D11 -> 4182914.6 | E18: =+E10+E11 -> 0 | G18: 1+2
B19: 3. ການປ່ຽນແປງ (ເພີ່ມຂຶ້ນ) ຫຼື ຫຼຸດລົງ ໃນລາຍການຊັບສິນໝູນວຽນ | D19: =+D20+D21+D22+D23+D24+D25+D26+D27 -> -21876577 | E19: =+E20+E21+E22+E23+E24+E25+E26+E27 -> 0
B20: 3.1. ເງິນຝາກທະນາຄານ ແລະ ສະຖາບັນການເງິນ | D20: =-SUM('TB 2012'!I6:I25)/1000 -> -20185460 | E20: 0 | G20: 1121+1131
B21: 3.2. ເງິນລົງທຶນໄລຍະສັ້ນ | D21: =-('TB 2012'!I33+'TB 2012'!I34)/1000 -> -434990.2 | E21: 0 | G21: 1302216+1302218
B22: 3.3. ໜີ້ຕ້ອງຮັບທາງການຄ້າ | D22: =-'TB 2012'!I30/1000 -> -54536.206 | E22: 0 | G22: 1201181
B23: 3.4. ໜີ້ຕ້ອງຮັບທາງທຸລະກຳຫຼັກຊັບ | D23: 0 | E23: 0 | G23: ບ/ຊ 120611+12311+123151+1241+1261
B24: 3.5. ໜີ້ຕ້ອງຮັບລະຫວ່າງບໍລິສັດໃນກຸ່ມ | D24: =-'TB 2012'!I31/1000 -> 23823.233 | E24: 0 | G24: 1211110
B25: 3.6. ໜີ້ຕ້ອງຮັບອື່ນໆ | D25: =-('TB 2012'!I26+'TB 2012'!I32)/1000 -> -1027703.1 | E25: 0 | G25: 1137111+1301720
B26: 3.7. ເຄື່ອງໃນສາງ | D26: 0 | E26: 0 | G26: ບ/ຊ 1371+1373+1376+1378-1379
B27: 3.8. ຊັບສິນໝູນວຽນອື່ນໆ | D27: =-SUM('TB 2012'!I35:I43)/1000-SUM('TB 2012'!I27:I29)/1000 -> -197710.1 | E27: 0 | G27: 1138100+1138810+1138830+1360000+1361100+1361300+1361500+1362100+1388110+1388120+1388170+1388180
B28: ຂ. ກະແສເງິນສົດສຸດທິຈາກການປ່ຽນແປງໃນຊັບສິນໝູນວຽນ | D28: =+D19 -> -21876577 | E28: =+E19 -> 0
B29: 4. ການປ່ຽນແປງ ເພີ່ມຂຶ້ນ ຫຼື (ຫຼຸດລົງ) ໃນລາຍການໜີ້ສິນໝູນວຽນ | D29: =+D30+D31+D32+D33+D34+D35 -> 17872192 | E29: =+E30+E31+E32+E33+E34+E35 -> 0
B30: 4.1. ໜີ້ຕ້ອງສົ່ງທາງການຄ້າ | D30: 0 | E30: 0
B31: 4.2. ໜີ້ຕ້ອງສົ່ງທາງທຸລະກຳຫຼັກຊັບ | D31: =SUM('TB 2012'!J59:J62)/1000 -> 15911349 | E31: 0 | G31: 2344100+2344200+2344600+2344700
B32: 4.3. ໜີ້ຕ້ອງສົ່ງລະຫວ່າງບໍລິສັດໃນກຸ່ມ | D32: ='TB 2012'!J57/1000 -> 53391.814 | E32: 0 | G32: 2211110
B33: 4.4. ອາກອນກຳໄລຄ້າງຈ່າຍ | D33: ='TB 2012'!J63/1000 -> 1455561.6 | E33: 0 | G33: 2361110
B34: 4.5. ໜີ້ຕ້ອງສົ່ງອື່ນໆ | D34: =SUM('TB 2012'!J64:J72)/1000 -> 134141.94 | E34: 0 | G34: 2361120+2361130+2361140+2361410+2361420+2361430+2361440+2361830+2361831
B35: 4.6. ໜີ້ສິນໝູນວຽນອື່ນໆ | D35: =SUM('TB 2012'!J73:J75)/1000 -> 317746.77 | E35: 0 | G35: 2363682+2363683+2363684
B36: ຄ. ກະແສເງິນສົດສຸດທິຈາກການປ່ຽນແປງໃນໜີ້ສິນໝູນວຽນ | D36: =+D29 -> 17872192 | E36: =+E29 -> 0 | F36: ok for the formula
B37: ກະແສເງິນສົດສຸດທິຈາກກິດຈະກຳດຳເນີນງານ | D37: =+D18+D28+D36 -> 178529.32 | E37: =+E18+E28+E36 -> 0
A38: II | B38: ​ກະແສເງິນສົດຈາກກິດຈະກໍາລົງທຶນ
B39: 1. ສ່ວນ (ເພີ່ມຂຶ້ນ) ຫຼື ຫຼຸດລົງ ໃນລາຍການເງິນລົງທຶນໄລຍະຍາວ | D39: 0 | E39: 0
B40: 2. ສ່ວນ (ເພີ່ມຂຶ້ນ) ຫຼື ຫຼຸດລົງ ໃນລາຍໜີ້ຕ້ອງຮັບໄລຍະຍາວ ແລະ ຊັບສິນໄລຍະຍາວອື່ນໆ | D40: 0 | E40: 0
B41: 3. ສ່ວນ (ເພີ່ມຂຶ້ນ) ຫຼື ຫຼຸດລົງ ໃນລາຍການຊັບສົມບັດຄົງທີ່ | D41: =-SUM('TB 2012'!I44:I49)/1000 -> -184061.32 | E41: 0 | G41: 1441810+1442400+1442510+1442610+1442710+1442720
B42: ກະແສເງິນສົດສຸດທິຈາກກິດຈະກຳລົງທຶນ | D42: =+SUM(D39:D41) -> -184061.32 | E42: =+SUM(E39:E41) -> 0
A43: III | B43: ກະແສເງິນສົດຈາກກິດຈະກຳຈັດຫາເງິນ
B44: 1. ສ່ວນ ເພີ່ມຂຶ້ນ ຫຼື (ຫຼຸດລົງ) ໃນລາຍການເງິນກູ້ຢືມມາ ແລະ ໜີ້ຕ້ອງສົ່ງໄລຍະຍາວອື່ນໆ | D44: 0 | E44: 0
B45: 2. ສ່ວນ ເພີ່ມຂຶ້ນ ຫຼື (ຫຼຸດລົງ) ໃນການອອກຮຸ້ນ | D45: 0 | E45: 0
B46: 3. ທຶນປະກອບທີ່ໄດ້ຮັບໃນປີ | D46: 0 | E46: 0
B47: 4. ຈ່າຍເງິນປັນຜົນ | D47: 0 | E47: 0
B48: ກະແສເງິນສົດສຸດທິຈາກກິດຈະກຳຈັດຫາເງິນ | D48: =+SUM(D44:D47) -> 0 | E48: =+SUM(E44:E47) -> 0
A49: IV | B49: ເງິນສົດ ແລະ ທຽບເທົ່າເງິນສົດ
B50: ເງິນສົດ ແລະ ທຽບເທົ່າເງິນສົດເພີ່ມຂຶ້ນ ຫຼື ຫຼຸດລົງສຸດທິໃນປີ | D50: =+D37+D42+D48 -> -5532 | E50: =+E37+E42+E48 -> 0 | F50: =+'TB 2012'!L21/10000 -> -4482007.2 | G50: =+'TB 2012'!I5/1000 -> -5532
B51: ເງິນສົດ ແລະ ທຽບເທົ່າເງິນສົດຍັງເຫຼືອທ້າຍປີກ່ອນ | D51: ='TB 2012'!C5/1000 -> 10000 | E51: 0 | F51: =+F59/10000 -> 11663937 | G51: =+G50-D50 -> -4.9950031e-05
B52: ເງິນສົດ ແລະ ທຽບເທົ່າເງິນສົດຍັງເຫຼືອທ້າຍປີນີ້ | D52: =+SUM(D50:D51) -> 4468 | E52: =+SUM(E50:E51) -> 0 | F52: =+SUM(F50:F51) -> 7181929.7
D54: ວັນທີ ..../..../....
A55: ຜູ້ອຳນວຍການ ຫົວໜ້າພະແນກກວດກາ ຫົວໜ້າພະແນກບັນຊີ ຜູ້ສັງລວມ
E56: Note: that the amount" Cash and cash equarvalent for the year end is should be including Cash on hand+Cash at bank "
E57: Ex: Cash and cash equarvalent for the year end 30/12/2012
F59: =+'TB 2012'!L18 -> 1.1663937e+11 | G59: =+'TB 2012'!M18 -> Cash for 2011
B60: =+SUM('TB 2012'!C5:C20) -> 1.1663937e+11 | C60: 2011 | F60: =+'TB 2012'!L19 -> 7.1819297e+10 | G60: =+'TB 2012'!M19 -> Cash for 2012
B61: =+SUM('TB 2012'!G6) -> 2.2816035e+09 | C61: 2012 | F61: =+F60-F59 -> -4.4820072e+10 | G61: Change for the year
C62: 2013

Sheet TB 2012
A1: ສາທາລະນະລັດ ປະຊາທິປະໄຕ ປະຊາຊົນລາວ | B1: ສັນຕິພາບ ເອກະລາດ ປະຊາທິປະໄຕ ເອກະພາບ ວັດທະນາຖາວອນ | F1: 2012
A2: ບໍລິສັດຫຼັກຊັບ ທຄຕລ-ກທ ຈຳກັດ_x000D_ ຊັ້ນ7, ຕຶກຕະຫຼາກຫຼັກຊັບລາວ, ຖະໜົນກຳແພງເມືອງ_x000D_ +856-21-265477+856-21-265488
C3: Opening | E3: Movement | G3: Balance | I3: Change
C4: ໜີ້ | D4: ມີ | E4: ໜີ້ | F4: ມີ | G4: ໜີ້ | H4: ມີ | I4: ໜີ້ | J4: ມີ
A5: 1101100 | B5: ເງິນສົດໃນຄັງ " HO " ກີບ | C5: 10000000 | D5: 0 | E5: 1.4693651e+08 | F5: 1.5246851e+08 | G5: 4468000 | H5: 0 | I5: =G5-C5 -> -5532000 | L5: =+E5-F5 -> -5532000
A6: 1121110 | B6: ບັນຊີທຶນຈົດທະບຽນຂອງ ທຄຕລ-ກທ ຈຳກັດ ( ກີບ ) | C6: 7.2281614e+10 | D6: 0 | E6: 0 | F6: 70000010000 | G6: 2.2816035e+09 | H6: 0 | I6: =G6-C6 -> -70000010000 | L6: =+E6-F6 -> -70000010000
A7: 1131110 | B7: ບັນຊີກະແສລາຍວັນ ທຄຕລ: 010.0.11.00.24740 ( ກີບ ) | C7: 652607.74 | D7: 0 | E7: 2.6829711e+08 | F7: 268812113 | G7: 137607.24 | H7: 0 | I7: =G7-C7 -> -515000.5 | L7: =+E7-F7 -> -515000.5
A8: 1131111 | B8: ບັນຊີກະແສລາຍວັນ ທຄຕລ: 010.7.11.02.08233 ( ບາດ ) | C8: 713249.55 | D8: 0 | E8: 1196931.5 | F8: 121655.66 | G8: 1788525.4 | H8: 0 | I8: =G8-C8 -> 1075275.8 | L8: =+E8-F8 -> 1075275.8
A9: 1131112 | B9: ບັນຊີກະແສລາຍວັນ ທຄຕລ: 010.9.11.01.19243 ( ໂດລ່າ ) | C9: 1641620.4 | D9: 0 | E9: 69481101 | F9: 69528404 | G9: 1594317.1 | H9: 0 | I9: =G9-C9 -> -47303.28 | L9: =+E9-F9 -> -47303.28
A10: 1131113 | B10: ບັນຊີກະແສລາຍວັນ ທຄຕລ Proprietary AC: 010.4.19.00.00009 ( ກີບ ) | C10: 92595445 | D10: 0 | E10: 154946789255 | F10: 154744754910 | G10: 294629790 | H10: 0 | I10: =G10-C10 -> 202034345 | L10: =+E10-F10 -> 202034345
A11: 1131115 | B11: ບັນຊີກະແສລາຍວັນ ທຄຕລ Aggregate AC: 010.4.19.00.00010 ( ກີບ ) | C11: 39741098167 | D11: 0 | E11: 669329114813 | F11: 653419265157 | G11: 55650947823 | H11: 0 | I11: =G11-C11 -> 15909849656 | L11: =+E11-F11 -> 15909849656
A12: 1131116 | B12: ບັນຊີກະແສລາຍວັນ ທຄຕລ for ETL staff IPO AC: 010.9.00.00001 ( ກີບ ) | C12: 100000 | D12: 0 | E12: 0 | F12: 0 | G12: 100000 | H12: 0 | I12: =G12-C12 -> 0
A13: 1131117 | B13: ບັນຊີກະແສລາຍວັນ ທຄຕລ ສຳລັບການຈອງ RO EDL-Gen :010.8.19.00.00012 LAk | C13: 0 | D13: 0 | E13: 405151388000 | F13: 405151388000 | G13: 0 | H13: 0 | I13: =G13-C13 -> 0
A14: 1131119 | B14: ບັນຊີກະແສລາຍວັນ ທຄຕລ ສຳລັບການ​ຈອງ PO EDL: 010.5.19.00.00013 Lak | C14: 0 | D14: 0 | E14: 1.7653324e+10 | F14: 1.7653324e+10 | G14: 0 | H14: 0 | I14: =G14-C14 -> 0
A15: 1131120 | B15: ບັນຊີກະແສລາຍວັນ ທຄຕລ ສຳລັບການ​ຈອງ PO EDL: 010.4.19.01.00006 USD | C15: 0 | D15: 0 | E15: 1.7085271e+11 | F15: 1.7085271e+11 | G15: 0 | H15: 0 | I15: =G15-C15 -> 0 | L15: =+SUM(I5:I20) -> -4.4820072e+10 | M15: OK
A16: 1131121 | B16: ບັນຊີກະແສລາຍວັນ ເອຊີລີດາ 123359-1-1-101 | C16: 0 | D16: 0 | E16: 1000000 | F16: 0 | G16: 1000000 | H16: 0 | I16: =G16-C16 -> 1000000 | L16: =+L15-L21 -> 0
A17: 1131130 | B17: ບັນຊີຝາກປະຢັດທີ່ ທຄຕລ: 013.2.12.00.00036 ກີບ | C17: 2.2618014e+09 | D17: 0 | E17: 1.1798555e+11 | F17: 1.10998e+11 | G17: 9.2493495e+09 | H17: 0 | I17: =G17-C17 -> 6.9875481e+09
A18: 1131131 | B18: ບັນຊີຝາກປະຢັດທີ່ ທຄຕລ: 013.9.12.01.00001 ( ໂດລ່າ ) | C18: 8.9027339e+08 | D18: 0 | E18: 3.5927276e+10 | F18: 3.6787536e+10 | G18: 30012667 | H18: 0 | I18: =G18-C18 -> -8.6026073e+08 | L18: =+SUM(C5:C20) -> 1.1663937e+11 | M18: Cash for 2011
A19: 1131134 | B19: ບັນຊີຝາກປະຢັດທີ່ ທສກ: 0402.0.00.220130 ( ກີບ ) | C19: 1358879432 | D19: 0 | E19: 2110287566 | F19: 0 | G19: 3469166998 | H19: 0 | I19: =G19-C19 -> 2110287566 | L19: =+SUM(G5:G20) -> 7.1819297e+10 | M19: Cash for 2012
A20: 1131137 | B20: ບັນຊີຝາກປະຍັດ ທຄຕລ-ກທ ທີ່ ເອຊີລີດາ 123359-1-0-0101 ( ກີບ ) | C20: 0 | D20: 0 | E20: 3.5834499e+10 | F20: 35000000000 | G20: 8.3449851e+08 | H20: 0 | I20: =G20-C20 -> 8.3449851e+08
A21: 1131153 | B21: ບັນຊີຝາກມີກຳນົດທີ່ ທສກ: 0402.0402.00.2131315.47.00000003 ( ກີບ ) | C21: 20000000000 | D21: 0 | E21: 0 | F21: 0 | G21: 20000000000 | H21: 0 | I21: =G21-C21 -> 0 | L21: =+L19-L18 -> -4.4820072e+10 | M21: Change for the year
A22: 1131154 | B22: ບັນຊີຝາກມີກຳນົດທີ່ ທສກ: 0402.0402.00.2131315.47.00000004 ( ກີບ ) | C22: 0 | D22: 0 | E22: 25000000000 | F22: 0 | G22: 25000000000 | H22: 0 | I22: =G22-C22 -> 25000000000 | L22: =+L18 -> 1.1663937e+11 | M22: Cash and cash equarvalent for the last year / beginning for the year
A23: 1131156 | B23: ບັນຊີຝາກມີກຳນົດທີ່ Sacom Bank: 40.000006310.8 ( ກີບ ) | C23: 0 | D23: 0 | E23: 30000000000 | F23: 30000000000 | G23: 0 | H23: 0 | I23: =G23-C23 -> 0 | L23: =+SUM(L21:L22) -> 7.1819297e+10
A24: 1131159 | B24: ບັນຊີຝາກມີກຳນົດທີ່ ST Bank: 010.5.35.00.08899 ( ກີບ ) | C24: 0 | D24: 0 | E24: 5000000000 | F24: 0 | G24: 5000000000 | H24: 0 | I24: =G24-C24 -> 5000000000
A25: 1131162 | B25: ບັນຊີເງິນຝາກມີກຳນົດ ທີ່ ທະນາຄານ ເອຊີລີດາ ( ກີບ ) | C25: 0 | D25: 0 | E25: 35000000000 | F25: 0 | G25: 35000000000 | H25: 0 | I25: =G25-C25 -> 35000000000
A26: 1137111 | B26: ດອກເບ້ຍຝາກມີກຳນົດ ຄ້າງຮັບ 1 ປີລົງມາ | C26: 169863014 | D26: 0 | E26: 5824469182 | F26: 5.3326256e+09 | G26: 6.6170662e+08 | H26: 0 | I26: =G26-C26 -> 4.9184361e+08
A27: 1138100 | B27: ກອງທຶນປົກປ້ອງຄວາມສ່ຽງໃນການຊຳລະສະສາງ | C27: 136517614 | D27: 0 | E27: 18938509 | F27: 342 | G27: 155455781 | H27: 0 | I27: =G27-C27 -> 18938167
A28: 1138810 | B28: ເງິນມັດຈຳຄ່າເຊົ່າ | C28: 11888910 | D28: 0 | E28: 0 | F28: 0 | G28: 11888910 | H28: 0 | I28: =G28-C28 -> 0
A29: 1138830 | B29: ເງິນມັດຈຳອື່ນໆ | C29: 0 | D29: 0 | E29: 4449332 | F29: 4449332 | G29: 0 | H29: 0 | I29: =G29-C29 -> 0
A30: 1201181 | B30: ລູກໜີ້ຊື້ຫຼັກຊັບຕາມຄຳສັ່ງຊື້-ບັນຊີເງິນສົດ | C30: 4284683 | D30: 0 | E30: 23279067826 | F30: 23224531620 | G30: 58820889 | H30: 0 | I30: =G30-C30 -> 54536206
A31: 1211110 | B31: ລູກໜີ້ບັນຊີຊື້-ຂາຍຫຼັກຊັບລະຫວ່າງບ/ສ ກັບ LSX | C31: 23823233 | D31: 0 | E31: 5742141356 | F31: 5765964589 | G31: 0 | H31: 0 | I31: =G31-C31 -> -23823233
A32: 1301720 | B32: ຄ່າທີ່ປຶກສາຄ້າງຮັບ | C32: 0 | D32: 0 | E32: 1024442620 | F32: 488583100 | G32: 535859520 | H32: 0 | I32: =G32-C32 -> 535859520 | L32: =-SUM('TB 2012'!I35:I43)/1000-SUM('TB 2012'!I27:I29)/1000 -> -197710.1
A33: 1302216 | B33: ເງິນລົງທືນຊົ່ວຄາວຫຼັກຊັບ-ເພື່ອຄ້າ-Port Trading | C33: 117180970 | D33: 0 | E33: 5.5465994e+08 | F33: 197620970 | G33: 4.7421994e+08 | H33: 0 | I33: =G33-C33 -> 3.5703897e+08
A34: 1302218 | B34: ຄ່າປັບມູນຄ່າເງິນລົງທືນຊົ່ວຄາວຫຼັກຊັບ-ເພື່ອຄ້າ-Port trading | C34: 0 | D34: 37250970 | E34: 4.0190649e+08 | F34: 3.2395527e+08 | G34: 40700260 | H34: 0 | I34: =G34-C34+D34 -> 77951230 | L34: =+E34-F34 -> 77951230
A35: 1360000 | B35: ລູກໜີ້ອື່ນໆ | C35: 61100181 | D35: 0 | E35: 4846066 | F35: 59977664 | G35: 5968583 | H35: 0 | I35: =G35-C35 -> -55131598 | L35: =+E35-F35 -> -55131598
A36: 1361100 | B36: ອາກອນກຳໄລມອບລ່ວງໜ້າ | C36: 27761356 | D36: 0 | E36: 99581906 | F36: 1.2734326e+08 | G36: 0 | H36: 0 | I36: =G36-C36 -> -27761356 | L36: =+E36-F36 -> -27761356
A37: 1361300 | B37: ອາກອນອື່ນໆທີ່ຕ້ອງຮັບຄືນ | C37: 27382364 | D37: 0 | E37: 6845600 | F37: 34227964 | G37: 0 | H37: 4.7683716e-09 | I37: =G37-C37 -> -27382364 | L37: =+E37-F37 -> -27382364
A38: 1361500 | B38: ລູນໜີ້ ເຄທີຂີມີໂກ້ ຈຳກັດ | C38: 0 | D38: 0 | E38: 94848000 | F38: 94848000 | G38: 0 | H38: 0 | I38: =G38-C38 -> 0 | L38: =+E38-F38 -> 0
A39: 1362100 | B39: ເງິນຈ່າຍລ່ວງໜ້າເພື່ອເຄື່ອນໄຫວວຽກງານ | C39: 36400000 | D39: 0 | E39: 243979076 | F39: 279879076 | G39: 500000 | H39: 0 | I39: =G39-C39 -> -35900000 | L39: =+E39-F39 -> -35900000
A40: 1388110 | B40: ຄ່າເຊົ່າຈ່າຍລ່ວງໜ້າ | C40: 23950902 | D40: 0 | E40: 9.7255238e+08 | F40: 5.5573423e+08 | G40: 4.4076906e+08 | H40: 0 | I40: =G40-C40 -> 4.1681815e+08 | L40: =+E40-F40 -> 4.1681815e+08
A41: 1388120 | B41: ຄ່າປະກັນໄພຈ່າຍລ່ວງໜ້າ | C41: 2097153.1 | D41: 0 | E41: 2.447531e+08 | F41: 1.2655419e+08 | G41: 1.2029605e+08 | H41: 0 | I41: =G41-C41 -> 1.181989e+08 | L41: =+E41-F41 -> 1.181989e+08
A42: 1388170 | B42: ຄ່າໜັງສືພີມ ຈ່າຍລ່ວງໜ້າອື່ນໆ | C42: 2.1599591e+08 | D42: 0 | E42: 5280000 | F42: 2.2105951e+08 | G42: 216393.45 | H42: 0 | I42: =G42-C42 -> -2.1577951e+08 | L42: =+E42-F42 -> -2.1577951e+08
A43: 1388180 | B43: ລາຍຈ່າຍ ຈ່າຍລ່ວງໜ້າອື່ນໆ | C43: 0 | D43: 0 | E43: 9971500 | F43: 4261791.8 | G43: 5709708.2 | H43: 0 | I43: =G43-C43 -> 5709708.2 | L43: =+E43-F43 -> 5709708.2
A44: 1441810 | B44: ຊັອບແວຄອມພີວເຕີ່ | C44: 2.7021397e+08 | D44: 0 | E44: 48000000 | F44: 10435920 | G44: 3.0777805e+08 | H44: 0 | I44: =G44-C44 -> 37564080 | L44: =+E44-F44 -> 37564080
A45: 1442400 | B45: ພາຫະນະຂົນສົ່ງ | C45: 615368000 | D45: 0 | E45: 14000000 | F45: 0 | G45: 629368000 | H45: 0 | I45: =G45-C45 -> 14000000 | L45: =+E45-F45 -> 14000000
A46: 1442510 | B46: ຄ່າຕົບແຕ່ງສຳນັກງານ | C46: 1.5394821e+09 | D46: 0 | E46: 8190000 | F46: 0 | G46: 1.5476721e+09 | H46: 0 | I46: =G46-C46 -> 8190000 | L46: =+E46-F46 -> 8190000
... A49: 1442720 | B49: ອຸປະກອນເຟີນີເຈີ່ | C49: 3.7393916e+08 | D49: 0 | E49: 8485500 | F49: 1335000 | G49: 3.8108966e+08 | H49: 0 | I49: =G49-C49 -> 7150500 | L49: =+E49-F49 -> 7150500
A50: 1481181 | B50: ຄ່າຕັດຈຳໜ່າຍຄອມພີວເຕີ່ຊ້ອບແວສະສົມ | C50: 0 | D50: 33563188 | E50: 10435920 | F50: 35543316 | G50: 0 | H50: 58670585 | J50: =H50-D50 -> 25107396
A51: 1481240 | B51: ຄ່າຫຼຸ່ຍຫ້ຽນສະສົມພາຫະນະ | C51: 0 | D51: 1.1976696e+08 | E51: 0 | F51: 1.2444235e+08 | G51: 0 | H51: 2.4420932e+08 | J51: =H51-D51 -> 1.2444235e+08
A52: 1481251 | B52: ຄ່າຫຼຸ່ຍຫ້ຽນສະສົມ ຄ່າຕົບແຕ່ງສຳນັກງານ | C52: 0 | D52: 1.5065818e+08 | E52: 27897.87 | F52: 1.5581786e+08 | G52: 0 | H52: 3.0644814e+08 | J52: =H52-D52 -> 1.5578996e+08
A53: 1481261 | B53: ຄ່າຫຼຸ່ຍຫ້ຽນສະສົມ ອຸປະກອນຄອມພີວເຕີ່ | C53: 0 | D53: 49361921 | E53: 506325.48 | F53: 63897227 | G53: 0 | H53: 1.1275282e+08 | J53: =H53-D53 -> 63390901
A54: 1481271 | B54: ຄ່າຫຼຸ່ຍຫ້ຽນສະສົມ ອຸປະກອນສຳນັກງານ | C54: 0 | D54: 7995341.2 | E54: 579192.2 | F54: 12830355 | G54: 0 | H54: 20246504 | J54: =H54-D54 -> 12251163
A55: 1481272 | B55: ຄ່າຫຼຸ່ຍຫ້ຽນສະສົມ ເຟີນີເຈີ່ | C55: 0 | D55: 35686254 | E55: 260933.48 | F55: 37978167 | G55: 0 | H55: 73403487 | J55: =H55-D55 -> 37717233
A56: 1482280 | B56: ບັນຊີພັກອື່ນໆ | C56: 0 | D56: 0 | E56: 24371500 | F56: 24371500 | G56: 0 | H56: 0 | J56: =H56-D56 -> 0
A57: 2211110 | B57: ເຈົ້າໜີ້ຕະຫຼາດຫຼັກຊັບ LSX | C57: 0 | D57: 3845762 | E57: 23018403859 | F57: 23071795673 | G57: 0 | H57: 57237576 | J57: =H57-D57 -> 53391814
A58: 2267100 | B58: ຄ່າເບ້ຍປະຊຸມຄ້າງຈ່າຍ | C58: 0 | D58: 0 | E58: 3500000 | F58: 3500000 | G58: 0 | H58: 0 | J58: =H58-D58 -> 0
A59: 2344100 | B59: ເຈົ້າໜີ້ບັນຊີຊື້-ຂາຍຫຼັກຊັບຕາມຄຳສັ່ງຊື້-ບັນຊີເງິນສົດ | C59: 0 | D59: 23694855 | E59: 5763349746 | F59: 5739654891 | G59: 0 | H59: 0 | J59: =H59-D59 -> -23694855
A60: 2344200 | B60: ບັນຊີເງິນລູກຄ້າ- Cash Balance | C60: 0 | D60: 39741098167 | E60: 653431862481 | F60: 669341712137 | G60: 0 | H60: 55650947823 | J60: =H60-D60 -> 15909849656
A61: 2344600 | B61: ບັນຊີເຈົ້າໜີ້ຄ່າຈອງຊື້ຮຸ້ນ | C61: 0 | D61: 0 | E61: 405151388000 | F61: 405151388000 | G61: 0 | H61: 0 | J61: =H61-D61 -> 0
... A78: 3810000 | B78: ກຳໄລ-ຂາດທຶນສະສົມ | C78: 0 | D78: 1.9182372e+08 | E78: 0 | F78: 0 | G78: 0 | H78: 1.9182372e+08 | J78: =H78-D78 -> 0
C81: =SUM(C5:C78) -> 1.4096742e+11 | D81: =SUM(D5:D78) -> 1.4096742e+11 | E81: =SUM(E5:E78) -> 3015176882011 | F81: =SUM(F5:F78) -> 3.0114127e+12 | G81: =SUM(G5:G78) -> 1.6298527e+11 | H81: =SUM(H5:H78) -> 1.5922106e+11 | I81: =SUM(I5:I78) -> 2.2055106e+10 | J81: =SUM(J5:J78) -> 1.8290891e+10
D83: =C81-D81 -> 0 | F83: =E81-F81 -> 3.7642156e+09 | H83: =G81-H81 -> 3.7642156e+09 | J83: =I81-J81 -> 3.7642156e+09
A86: 4102730 | B86: ຄ່າບໍລິການເຊົ່າລະບົບເທີມີນໍ່ LSX | C86: 0 | D86: 0 | E86: 2.4354702e+08 | F86: 0 | G86: 2.4354702e+08 | H86: 0 | J86: =F86-E86 -> -2.4354702e+08
A87: 4102731 | B87: ຄ່າບໍລິການເຊົ່າລະບົບດິດສເປຣເຢີ່ LSX | C87: 0 | D87: 0 | E87: 33168305 | F87: 0 | G87: 33168305 | H87: 0 | J87: =F87-E87 -> -33168305
A88: 4108210 | B88: ຄ່າທຳນຽມທະນາຄານ ( ຈ່າຍ ) | C88: 0 | D88: 0 | E88: 11148726 | F88: 0 | G88: 11148726 | H88: 0 | J88: =F88-E88 -> -11148726
A89: 4201100 | B89: ເງິນເດືອນພະນັກງານໃນການຈັດຕັ້ງ | C89: 0 | D89: 0 | E89: 1918944102 | F89: 0 | G89: 1918944102 | H89: 0 | J89: =F89-E89 -> -1918944102
A90: 4201200 | B90: ເງິນເດືອນພະນັກງານຊົ່ວຄາວ | C90: 0 | D90: 0 | E90: 23070661 | F90: 0 | G90: 23070661 | H90: 0 | J90: =F90-E90 -> -23070661
A91: 4201400 | B91: ເງິນເພີ່ມໂມງ | C91: 0 | D91: 0 | E91: 59776012 | F91: 0 | G91: 59776012 | H91: 0 | J91: =F91-E91 -> -59776012
A92: 4202110 | B92: ເງິນບຳເນັດ | C92: 0 | D92: 0 | E92: 9425000 | F92: 0 | G92: 9425000 | H92: 0 | J92: =F92-E92 -> -9425000
A93: 4202200 | B93: ລາຍຈ່າຍຄ່າປະກັນໄພພະນັກງານ | C93: 0 | D93: 0 | E93: 1.0562448e+08 | F93: 0 | G93: 1.0562448e+08 | H93: 0 | J93: =F93-E93 -> -1.0562448e+08
A94: 4202210 | B94: ລາຍຈ່າຍຄ່າຮັກສາພະຍາບານ | C94: 0 | D94: 0 | E94: 4473203 | F94: 0 | G94: 4473203 | H94: 0 | J94: =F94-E94 -> -4473203
A95: 4202220 | B95: ລາຍຈ່າຍຄ່ານ້ຳມັນລົດພະນັກງານ | C95: 0 | D95: 0 | E95: 187500000 | F95: 0 | G95: 187500000 | H95: 0 | J95: =F95-E95 -> -187500000
A96: 4202800 | B96: ລາຍຈ່າຍສະຫວັດດີການພະນັກງານອື່ນໆ | C96: 0 | D96: 0 | E96: 82586000 | F96: 0 | G96: 82586000 | H96: 0 | J96: =F96-E96 -> -82586000
A97: 4202811 | B97: ລາຍຈ່າຍເບ້ຍປະຊູມສະພາບໍລິຫານ | C97: 0 | D97: 0 | E97: 46695436 | F97: 642807 | G97: 46052629 | H97: 0 | J97: =F97-E97 -> -46052629
... A172: 5508400 | B172: ລາຍຮັບອື່ນໆ | C172: 0 | D172: 0 | E172: 0 | F172: 15099335 | G172: 0 | H172: 15099335 | J172: =F172-E172 -> 15099335
C174: =SUM(C86:C173) -> 0 | D174: =SUM(D86:D173) -> 0 | E174: =SUM(E86:E173) -> 5.4556957e+10 | F174: =SUM(F86:F173) -> 58321172365 | G174: =SUM(G86:G173) -> 5.0475178e+10 | H174: =SUM(H86:H173) -> 5.4239393e+10 | I174: =SUM(I86:I173) -> 0 | J174: =SUM(J86:J173) -> 3.7642156e+09
F176: =F174-E174 -> 3.7642156e+09 | H176: =H174-G174 -> 3.7642156e+09 | J176: =J174-H83 -> 0
B181: ລວມມູນຄ່າ | C181: 1.4096742e+11 | D181: 1.4096742e+11 | E181: 3.0697338e+12 | F181: 3.0697338e+12 | G181: 2.1346045e+11 | H181: 2.1346045e+11
C183: ນະຄອນຫຼວງວຽງຈັນ ວັນທີ : ......../......../............ , | D183: ຜູ້ອຳນວຍການ | E183: ທີ່ປຶກສາບັນຊີ | F183: ພະນັກງານບັນຊີ | G183: ຜູ້ສັງລວມ | H183: ............…………………...... | I183: ............…………………......

Sheet BS
A1: ສາທາລະນະລັດ ປະຊາທິປະໄຕ ປະຊາຊົນລາວ | B1: ສັນຕິພາບ ເອກະລາດ ປະຊາທິປະໄຕ ເອກະພາບ ວັດທະນາຖາວອນ
A2: ບໍລິສັດຫຼັກຊັບ ທຄຕລ-ກທ ຈຳກັດ_x000D_ ຊັ້ນ7, ຕຶກຕະຫຼາກຫຼັກຊັບລາວ, ຖະໜົນກຳແພງເມືອງ_x000D_ +856-21-265477+856-21-265488
D3: ໃບສະຫລຸບຊັບສົມບັດ | E3: ໃນປີ 2012
A4: ລ/ດ | B4: ເລກບັນຊີ | C4: ເນື້ອໃນລາຍການ | D4: ປີນີ້ | E4: ປີກ່ອນ
A5: 1 | B5: 1. ​ເງິນສົດ ​ແລະ ທຽບ​ເທົ່​າເງິນສົດ | D5: 4468000 | E5: 10000000
A6: 1 | B6: 1101100 | C6: ເງິນສົດໃນຄັງ " HO " ກີບ | D6: 4468000 | E6: 10000000
A7: 2 | B7: 2.1. ເງິນຝາກທະນາຄານ | D7: 1.5681483e+11 | E7: 1.3662937e+11
A8: 2 | B8: 1131115 | C8: ບັນຊີກະແສລາຍວັນ ທຄຕລ Aggregate AC: 010.4.19.00.00010 ( ກີບ ) | D8: 55650947823 | E8: 39741098167
A9: 3 | B9: 1131116 | C9: ບັນຊີກະແສລາຍວັນ ທຄຕລ for ETL staff IPO AC: 010.9.00.00001 ( ກີບ ) | D9: 100000 | E9: 100000
A10: 4 | B10: 1131154 | C10: ບັນຊີຝາກມີກຳນົດທີ່ ທສກ: 0402.0402.00.2131315.47.00000004 ( ກີບ ) | D10: 25000000000 | E10: 0
B11: 1131110 | C11: ບັນຊີກະແສລາຍວັນ ທຄຕລ: 010.0.11.00.24740 ( ກີບ ) | D11: 137607.24 | E11: 652607.74
A12: 6 | B12: 1131159 | C12: ບັນຊີຝາກມີກຳນົດທີ່ ST Bank: 010.5.35.00.08899 ( ກີບ ) | D12: 5000000000 | E12: 0
A13: 7 | B13: 1131113 | C13: ບັນຊີກະແສລາຍວັນ ທຄຕລ Proprietary AC: 010.4.19.00.00009 ( ກີບ ) | D13: 294629790 | E13: 92595445
A14: 8 | B14: 1131162 | C14: ບັນຊີເງິນຝາກມີກຳນົດ ທີ່ ທະນາຄານ ເອຊີລີດາ ( ກີບ ) | D14: 35000000000 | E14: 0
A15: 9 | B15: 1131111 | C15: ບັນຊີກະແສລາຍວັນ ທຄຕລ: 010.7.11.02.08233 ( ບາດ ) | D15: 1788525.4 | E15: 713249.55
A16: 10 | B16: 1131134 | C16: ບັນຊີຝາກປະຢັດທີ່ ທສກ: 0402.0.00.220130 ( ກີບ ) | D16: 3469166998 | E16: 1358879432
A17: 11 | B17: 1131131 | C17: ບັນຊີຝາກປະຢັດທີ່ ທຄຕລ: 013.9.12.01.00001 ( ໂດລ່າ ) | D17: 30012667 | E17: 8.9027339e+08
A18: 12 | B18: 1121110 | C18: ບັນຊີທຶນຈົດທະບຽນຂອງ ທຄຕລ-ກທ ຈຳກັດ ( ກີບ ) | D18: 2.2816035e+09 | E18: 7.2281614e+10
A19: 13 | B19: 1131112 | C19: ບັນຊີກະແສລາຍວັນ ທຄຕລ: 010.9.11.01.19243 ( ໂດລ່າ ) | D19: 1594317.1 | E19: 1641620.4
A20: 14 | B20: 1131121 | C20: ບັນຊີກະແສລາຍວັນ ເອຊີລີດາ 123359-1-1-101 | D20: 1000000 | E20: 0
A21: 15 | B21: 1131153 | C21: ບັນຊີຝາກມີກຳນົດທີ່ ທສກ: 0402.0402.00.2131315.47.00000003 ( ກີບ ) | D21: 20000000000 | E21: 20000000000
A22: 16 | B22: 1131130 | C22: ບັນຊີຝາກປະຢັດທີ່ ທຄຕລ: 013.2.12.00.00036 ກີບ | D22: 9.2493495e+09 | E22: 2.2618014e+09
A23: 17 | B23: 1131137 | C23: ບັນຊີຝາກປະຍັດ ທຄຕລ-ກທ ທີ່ ເອຊີລີດາ 123359-1-0-0101 ( ກີບ ) | D23: 8.3449851e+08 | E23: 0
A24: 3 | B24: 3.1. ເງິນລົງທຶນໄລຍະສັ້ນ | D24: 5.149202e+08 | E24: 79930000
A25: 18 | B25: 1302216 | C25: ເງິນລົງທືນຊົ່ວຄາວຫຼັກຊັບ-ເພື່ອຄ້າ-Port Trading | D25: 4.7421994e+08 | E25: 117180970
A26: 19 | B26: 1302218 | C26: ຄ່າປັບມູນຄ່າເງິນລົງທືນຊົ່ວຄາວຫຼັກຊັບ-ເພື່ອຄ້າ-Port trading | D26: 40700260 | E26: -37250970
A27: 4 | B27: 4.1. ໜີ້ຕ້ອງ​ຮັບ​ທາງການຄ້າ | D27: 58820889 | E27: 4284683
A28: 20 | B28: 1201181 | C28: ລູກໜີ້ຊື້ຫຼັກຊັບຕາມຄຳສັ່ງຊື້-ບັນຊີເງິນສົດ | D28: 58820889 | E28: 4284683
A29: 5 | B29: 4.3. ໜີ້ຕ້ອງ​ຮັບ​ລະຫວ່າງ​ບໍລິສັດໃນກຸ່ມ | C29: 0 | D29: 23823233
A30: 21 | B30: 1211110 | C30: ລູກໜີ້ບັນຊີຊື້-ຂາຍຫຼັກຊັບລະຫວ່າງບ/ສ ກັບ LSX | D30: 0 | E30: 23823233
A31: 6 | B31: 6. ຊັບສິນໝູນວຽນອື່ນໆ | D31: 6468583 | E31: 1.526439e+08
A32: 22 | B32: 1360000 | C32: ລູກໜີ້ອື່ນໆ | D32: 5968583 | E32: 61100181
A33: 23 | B33: 1361300 | C33: ອາກອນອື່ນໆທີ່ຕ້ອງຮັບຄືນ | D33: -7.4505806e-09 | E33: 27382364
A34: 24 | B34: 1362100 | C34: ເງິນຈ່າຍລ່ວງໜ້າເພື່ອເຄື່ອນໄຫວວຽກງານ | D34: 500000 | E34: 36400000
A35: 25 | B35: 1361100 | C35: ອາກອນກຳໄລມອບລ່ວງໜ້າ | D35: 0 | E35: 27761356
A36: 7 | B36: 2. ຊັບສິນຄົງທີ່ບໍ່ມີຕົວຕົນ | D36: 3.0777805e+08 | E36: 2.7021397e+08
A37: 26 | B37: 1441810 | C37: ຊັອບແວຄອມພີວເຕີ່ | D37: 3.0777805e+08 | E37: 2.7021397e+08
A38: 8 | B38: 3. ຊັບ​ສົມບັດຄົງ​ທີ່​ມີຕົວຕົນ | D38: 3.3460869e+09 | E38: 3.1995897e+09
A39: 27 | B39: 1442510 | C39: ຄ່າຕົບແຕ່ງສຳນັກງານ | D39: 1.5476721e+09 | E39: 1.5394821e+09
A40: 28 | B40: 1442400 | C40: ພາຫະນະຂົນສົ່ງ | D40: 629368000 | E40: 615368000
A41: 29 | B41: 1442710 | C41: ອຸປະກອນສຳນັກງານ | D41: 1.3821519e+08 | E41: 96539608
A42: 30 | B42: 1442610 | C42: ອຸປະກອນຄອມພີວເຕີ່ | D42: 6.4974202e+08 | E42: 5.7426087e+08
A43: 31 | B43: 1442720 | C43: ອຸປະກອນເຟີນີເຈີ່ | D43: 3.8108966e+08 | E43: 3.7393916e+08
A44: 9 | B44: 4. ຄ່າຫຼຸ້ຍຫ້ຽນສະສົມ ຊັບສົມບັດຄົງທີ່ | D44: -8.1573085e+08 | E44: -3.9703185e+08
A45: 32 | B45: 1481261 | C45: ຄ່າຫຼຸ່ຍຫ້ຽນສະສົມ ອຸປະກອນຄອມພີວເຕີ່ | D45: -1.1275282e+08 | E45: -49361921
A46: 33 | B46: 1481251 | C46: ຄ່າຫຼຸ່ຍຫ້ຽນສະສົມ ຄ່າຕົບແຕ່ງສຳນັກງານ | D46: -3.0644814e+08 | E46: -1.5065818e+08
A47: 34 | B47: 1481272 | C47: ຄ່າຫຼຸ່ຍຫ້ຽນສະສົມ ເຟີນີເຈີ່ | D47: -73403487 | E47: -35686254
A48: 35 | B48: 1481271 | C48: ຄ່າຫຼຸ່ຍຫ້ຽນສະສົມ ອຸປະກອນສຳນັກງານ | D48: -20246504 | E48: -7995341.2
A49: 36 | B49: 1481240 | C49: ຄ່າຫຼຸ່ຍຫ້ຽນສະສົມພາຫະນະ | D49: -2.4420932e+08 | E49: -1.1976696e+08
A50: 37 | B50: 1481181 | C50: ຄ່າຕັດຈຳໜ່າຍຄອມພີວເຕີ່ຊ້ອບແວສະສົມ | D50: -58670585 | E50: -33563188
A51: 10 | B51: 1. ດອກເບ້ຍແລະເງິນປັນຜົນຄ້າງຮັບ | D51: 1.1975661e+09 | E51: 169863014
A52: 38 | B52: 1137111 | C52: ດອກເບ້ຍຝາກມີກຳນົດ ຄ້າງຮັບ 1 ປີລົງມາ | D52: 6.6170662e+08 | E52: 169863014
A53: 39 | B53: 1301720 | C53: ຄ່າທີ່ປຶກສາຄ້າງຮັບ | D53: 535859520 | E53: 0
A54: 11 | B54: 2. ບັນຊີຊໍາລະສະສາງ | D54: 5.6699121e+08 | E54: 2.4204396e+08
A55: 40 | B55: 1388170 | C55: ຄ່າໜັງສືພີມ ຈ່າຍລ່ວງໜ້າອື່ນໆ | D55: 216393.45 | E55: 2.1599591e+08
A56: 41 | B56: 1388120 | C56: ຄ່າປະກັນໄພຈ່າຍລ່ວງໜ້າ | D56: 1.2029605e+08 | E56: 2097153.1
A57: 42 | B57: 1388110 | C57: ຄ່າເຊົ່າຈ່າຍລ່ວງໜ້າ | D57: 4.4076906e+08 | E57: 23950902
A58: 43 | B58: 1388180 | C58: ລາຍຈ່າຍ ຈ່າຍລ່ວງໜ້າອື່ນໆ | D58: 5709708.2 | E58: 0
A59: 12 | B59: 3. ເງິນວາງຄ້ຳປະກັນ | D59: 167344691 | E59: 148406524
A60: 44 | B60: 1138810 | C60: ເງິນມັດຈຳຄ່າເຊົ່າ | D60: 11888910 | E60: 11888910
A61: 45 | B61: 1138100 | C61: ກອງທຶນປົກປ້ອງຄວາມສ່ຽງໃນການຊຳລະສະສາງ | D61: 155455781 | E61: 136517614
A62: 13 | B62: 3. ໜີ້ຕ້ອງສົ່ງທາງທຸລະກຳຫລັກຊັບ | D62: -55676142471 | E62: -39764793022
A63: 46 | B63: 2344700 | C63: ເຈົ້າໜີ້ລໍຖ້າຖອນເງີນຄືນ | D63: -25194648 | E63: 0
A64: 47 | B64: 2344100 | C64: ເຈົ້າໜີ້ບັນຊີຊື້-ຂາຍຫຼັກຊັບຕາມຄຳສັ່ງຊື້-ບັນຊີເງິນສົດ | D64: 0 | E64: -23694855
A65: 48 | B65: 2344200 | C65: ບັນຊີເງິນລູກຄ້າ- Cash Balance | D65: -55650947823 | E65: -39741098167
A66: 14 | B66: 4. ໜີ້ຕ້ອງ​ສົ່ງ​ລະຫວ່າງ​ບໍລິສັດໃນກຸ່ມ | D66: -57237576 | E66: -3845762
A67: 49 | B67: 2211110 | C67: ເຈົ້າໜີ້ຕະຫຼາດຫຼັກຊັບ LSX | D67: -57237576 | E67: -3845762
A68: 15 | B68: 5. ອາກອນກຳໄລຄ້າງຈ່າຍ | D68: -1.4555616e+09 | E68: 0
A69: 50 | B69: 2361110 | C69: ອາກອນກຳໄລທີ່ຕ້ອງມອບເພີ່ມ | D69: -1.4555616e+09 | E69: 0
A70: 16 | B70: 6. ໜີ້ຕ້ອງສົ່ງອື່ນໆ | D70: -1.7115627e+08 | E70: -43421744
A71: 51 | B71: 2361120 | C71: ອາກອນມູນຄ່າເພີ່ມທີ່ຕ້ອງມອບເພີ່ມ | D71: 0.050000191 | E71: 0
A72: 52 | B72: 2361130 | C72: ພາສີ ແລະອາກອນຕ່າງໆ ທີ່ຫັກໄວ້ຕ້ອງສົ່ງມອບ | D72: -1.3973847e+08 | E72: 0
A73: 53 | B73: 2361140 | C73: ອາກອນເງິນເດືອນຕ້ອງສົ່ງມອບ | D73: -31417799 | E73: -43421744
A74: 17 | B74: 1. ບັນຊີຊໍາລະສະສາງ | D74: -8.5340598e+08 | E74: -5.2925179e+08
A75: 54 | B75: 2361420 | C75: ຄ່າ terminal LSX ຄ້າງຈ່າຍ | D75: -21286512 | E75: -17150000
A76: 55 | B76: 2361831 | C76: ຄ່າໄຟຟ້າຄ້າງຈ່າຍ | D76: -7239040 | E76: 0
A77: 56 | B77: 2361430 | C77: ຄ່າ Displayer LSX ຄ້າງຈ່າຍ | D77: -2581632 | E77: -2600000
A78: 57 | B78: 2363682 | C78: ບັນຊີເຈົ້າໜີ້ KTZmico Co.,Ltd | D78: -2.9070674e+08 | E78: 0
A79: 58 | B79: 2361440 | C79: ຄ່າໃຊ້ຈ່າຍຄ້າງຈ່າຍອື່ນໆ | D79: -3.7545304e+08 | E79: -3.0206731e+08
A80: 59 | B80: 2361410 | C80: ຄ່າບໍລິການຄ້າງຈ່າຍ | D80: -129098980 | E80: -139126366
A81: 60 | B81: 2361830 | C81: ຄ່າໄຟຟ້າ ແລະນ້ຳປະປາຄ້າງຈ່າຍ | D81: 0 | E81: -68308110
A82: 61 | B82: 2363684 | C82: ບັນຊີເຈົ້າໜີ້ອື່ນໆ | D82: -27040033 | E82: 0
A83: 18 | B83: 1.2 ທຶນຈົດທະບຽນຍັງບໍ່ທັນຖອກ | C83: -100000000000 | D83: -100000000000
A84: 62 | B84: 3108210 | C84: ທຶນຈົດທະບຽນທີ່ຖອກແລ້ວ | D84: -100000000000 | E84: -100000000000
A85: 19 | B85: 3. ກຳໄລ(ຂາດທຶນ)ສະສົມ | C85: -1.9182372e+08 | D85: -1.9182372e+08
A86: 63 | B86: 3810000 | C86: ກຳໄລ-ຂາດທຶນສະສົມ | D86: -1.9182372e+08 | E86: -1.9182372e+08
A87: 20 | B87: 5. ຜົນໄດ້ຮັບໃນປີ | C87: -3.7642156e+09 | D87: 0
A88: 64 | B88: 3901000 | C88: ກຳໄລ-ຂາດ ທຶນໃນປີ | D88: -3.7642156e+09 | E88: 0
A89: ນະຄອນຫຼວງວຽງຈັນ ວັນທີ : ......../......../............ , | B89: ຜູ້ອຳນວຍການ | C89: ທີ່ປຶກສາບັນຊີ | D89: ພະນັກງານບັນຊີ | E89: ຜູ້ສັງລວມ | F89: ............…………………...... | G89: ............…………………...... | H89: ............…………………...... | I89: ............…………………...... | J89: ...………………………….. | K89: ...………………………….. | L89: ...………………………….. | M89: ...…………………………..
A90: 1

Sheet PL
A1: ສາທາລະນະລັດ ປະຊາທິປະໄຕ ປະຊາຊົນລາວ | B1: ສັນຕິພາບ ເອກະລາດ ປະຊາທິປະໄຕ ເອກະພາບ ວັດທະນາຖາວອນ
A2: ບໍລິສັດຫຼັກຊັບ ທຄຕລ-ກທ ຈຳກັດ_x000D_ ຊັ້ນ7, ຕຶກຕະຫຼາກຫຼັກຊັບລາວ, ຖະໜົນກຳແພງເມືອງ_x000D_ +856-21-265477+856-21-265488
D3: ໃບລາຍງານຜົນໄດ້ຮັບ | E3: ໃນປີ 2012
A4: ເອກະສານຊ້ອນທ້າຍ
A5: ລຳດັບ | B5: ລາຍຮັບ | C5: 1.1 | D5: 0 | E5: 0
A6: I | B6: ລາຍຮັບຈາກການດຳເນີນງານ | C6: 1.1.1 | D6: 5.4220711e+10 | E6: 0
B7: 1. ຄ່ານາຍໜ້າຈາກການຊື້-ຂາຍຫຼັກຊັບ | C7: 1.1.1.1 | D7: 1698263965 | E7: 0
B8: 2. ຄ່າບໍລິການ | C8: 1.1.1.2 | D8: 4.7128415e+10 | E8: 0
B9: 2.1. ຄ່າບໍລິການໃຫ້ຄຳປຶກສາທາງດ້ານການເງິນ | C9: 1.1.1.2.1 | D9: 4.3376696e+09 | E9: 0
B10: 2.2. ຄ່າບໍລິການ ຄໍ້າປະກັນການຈັດຈຳໜ່າຍຫຼັກຊັບ | C10: 1.1.1.2.2 | D10: 42790745204 | E10: 0
B11: 2.3. ຄ່າບໍລິການ ເປັນຕົວແທນຈຳໝ່າຍຫຼັກຊັບ | C11: 1.1.1.2.3 | D11: 0 | E11: 0
B12: 3. ກຳໄລ(ຂາດທຶນ)ຈາກການຊື້ຂາຍຫຼັກຊັບ | C12: 1.1.1.3 | D12: 74367920 | E12: 0
B13: 4. ດອກເບ້ຍ ແລະ ເງິນປັນຜົນ | C13: 1.1.1.4 | D13: 5.3196641e+09 | E13: 0
A14: II | B14: ລາຍຮັບອື່ນໆ | C14: 1.1.2 | D14: -1.4064442e+08 | E14: 0
B15: ລາຍຮັບອື່ນໆ | C15: 1.1.2.5 | D15: -1.4064442e+08 | E15: 0
B16: ລວມຍອດລາຍຮັບ | C16: 1.13 | D16: 5.4080066e+10 | E16: 0
A17: ລຳດັບ | B17: ລາຍຈ່າຍ | C17: 1.2. | D17: 0 | E17: 0
A18: I | B18: ລາຍຈ່າຍຈາກການດຳເນີນງານ | C18: 1.2.1 | D18: 4.2748984e+10 | E18: 0
B19: 1. ລາຍຈ່າຍຄ່ານາຍໜ້າຊື້-ຂາຍຫຼັກຊັບ | C19: 1.2.1.1.1 | D19: 1.0378224e+09 | E19: 0
B20: 2. ລາຍຈ່າຍຄ່າໃຫ້ຄຳປຶກສາທາງການເງິນ | C20: 1.2.1.1.2 | D20: 4.1056803e+10 | E20: 0
B21: 3. ລາຍຈ່າຍຄ່າໃຫ້ການຄໍ້າປະກັນການຈັດຈຳໜ່າຍຫຼັກຊັບ | C21: 1.2.1.1.3 | D21: 0 | E21: 0
B22: 4. ລາຍຈ່າຍການຄ້າຫຼັກຊັບ | C22: 1.2.1.1.4 | D22: 0 | E22: 0
B23: 5. ລາຍຈ່າຍອື່ນໆທາງດ້ານຫຼັກຊັບ | C23: 1.2.1.1.5 | D23: 6.5435877e+08 | E23: 0
A24: II | B24: ລາຍຈ່າຍໃນການບໍລິຫານ | C24: 1.2.2 | D24: 6.0327915e+09 | E24: 0
B25: 1. ລາຍຈ່າຍກ່ຽວກັບພະນັກງານ | C25: 1.2.2.2.1 | D25: 3.3459934e+09 | E25: 0
B26: 2. ຄ່າຫລຸ້ຍຫ້ຽນອາຄານສະຖານທີ່ ແລະ ອຸປະກອນ | C26: 1.2.2.2.2 | D26: 4.3048138e+08 | E26: 0
B27: 3. ລາຍຈ່າຍພາສີອາກອນ | C27: 1.2.2.2.3 | D27: 77870728 | E27: 0
B28: 4. ລາຍຈ່າຍອື່ນໆ | C28: 1.2.2.2.4 | D28: 2.178446e+09 | E28: 0
A29: III | B29: ລາຍຈ່າຍດອກເບ້ຍເງິນກູ້ຢືມ | C29: 1.2.3 | D29: 0 | E29: 0
B30: ລາຍຈ່າຍດອກເບ້ຍເງິນກູ້ຢືມ | C30: 1.2.3.3.1 | D30: 0 | E30: 0
B31: ລວມຍອດລາຍຈ່າຍ | C31: 1.2.4 | D31: 4.8781776e+10 | E31: 0
B32: ກຳໄລກ່ອນອາກອນ | C32: 1.2.4.1 | D32: 5.2982905e+09 | E32: 0
B33: ອາກອນກຳໄລ | C33: 1.2.4.2 | D33: 1.534075e+09 | E33: 0
B34: ກຳໄລສຸດທິ | C34: 1.2.4.3 | D34: 3.7642156e+09 | E34: 0
A35: ນະຄອນຫຼວງວຽງຈັນ ວັນທີ : ......../......../............ , | B35: ຜູ້ອຳນວຍການ | C35: ທີ່ປຶກສາບັນຊີ | D35: ພະນັກງານບັນຊີ | E35: ຜູ້ສັງລວມ | F35: ............…………………...... | G35: ............…………………...... | H35: ............…………………...... | I35: ............…………………...... | J35: ...………………………….. | K35: ...………………………….. | L35: ...………………………….. | M35: ...…………………………..
A36: 1
